{"inputConfig":{"gcsSource":{"uri":"gs://ocr-test-bucket-466/merged.pdf"},"mimeType":"application/pdf"},"responses":[{"fullTextAnnotation":{"pages":[{"property":{"detectedLanguages":[{"languageCode":"de","confidence":0.7499643},{"languageCode":"ka","confidence":0.15164444},{"languageCode":"af","confidence":0.03462557},{"languageCode":"lb","confidence":0.029464478},{"languageCode":"qu","confidence":0.023955509},{"languageCode":"fr","confidence":0.009743999}]},"width":170,"height":420,"blocks":[{"boundingBox":{"normalizedVertices":[{"x":0.03529412,"y":0.007142857},{"x":0.9823529,"y":0.014285714},{"x":0.9705882,"y":0.35238096},{"x":0.023529412,"y":0.3452381}]},"paragraphs":[{"boundingBox":{"normalizedVertices":[{"x":0.03529412,"y":0.007142857},{"x":0.2529412,"y":0.00952381},{"x":0.24705882,"y":0.026190476},{"x":0.03529412,"y":0.023809524}]},"words":[{"property":{"detectedLanguages":[{"languageCode":"fr","confidence":1}]},"boundingBox":{"normalizedVertices":[{"x":0.03529412,"y":0.007142857},{"x":0.064705886,"y":0.00952381},{"x":0.05882353,"y":0.023809524},{"x":0.03529412,"y":0.023809524}]},"symbols":[{"property":{"detectedBreak":{"type":"SPACE"}},"text":"à","confidence":0.24300347}],"confidence":0.24300347},{"property":{"detectedLanguages":[{"languageCode":"fr","confidence":1}]},"boundingBox":{"normalizedVertices":[{"x":0.08235294,"y":0.00952381},{"x":0.2529412,"y":0.00952381},{"x":0.24705882,"y":0.026190476},{"x":0.08235294,"y":0.023809524}]},"symbols":[{"text":"b","confidence":0.98325247},{"text":"i","confidence":0.9958979},{"text":"n","confidence":0.9942302},{"text":"d","confidence":0.9948483},{"text":"e","confidence":0.99411684},{"property":{"detectedBreak":{"type":"LINE_BREAK"}},"text":"n","confidence":0.9923271}],"confidence":0.99244547}],"confidence":0.88538235},{"boundingBox":{"normalizedVertices":[{"x":0.03529412,"y":0.035714287},{"x":0.5882353,"y":0.03809524},{"x":0.58235294,"y":0.057142857},{"x":0.03529412,"y":0.054761905}]},"words":[{"property":{"detectedLanguages":[{"languageCode":"de","confidence":1}]},"boundingBox":{"normalizedVertices":[{"x":0.03529412,"y":0.035714287},{"x":0.15294118,"y":0.035714287},{"x":0.14705883,"y":0.054761905},{"x":0.03529412,"y":0.054761905}]},"symbols":[{"text":"ბ","confidence":0.9749772},{"text":"ა","confidence":0.9950669},{"text":"ა","confidence":0.9980119},{"property":{"detectedBreak":{"type":"SPACE"}},"text":"ს","confidence":0.9983959}],"confidence":0.991613},{"property":{"detectedLanguages":[{"languageCode":"de","confidence":1}]},"boundingBox":{"normalizedVertices":[{"x":0.1764706,"y":0.03809524},{"x":0.2764706,"y":0.03809524},{"x":0.2764706,"y":0.054761905},{"x":0.1764706,"y":0.054761905}]},"symbols":[{"text":"s","confidence":0.9954657},{"text":"i","confidence":0.9908988},{"text":"c","confidence":0.9986978},{"property":{"detectedBreak":{"type":"SPACE"}},"text":"h","confidence":0.9992754}],"confidence":0.99608445},{"property":{"detectedLanguages":[{"languageCode":"de","confidence":1}]},"boundingBox":{"normalizedVertices":[{"x":0.30588236,"y":0.03809524},{"x":0.5882353,"y":0.03809524},{"x":0.58235294,"y":0.057142857},{"x":0.30588236,"y":0.054761905}]},"symbols":[{"text":"u","confidence":0.9982713},{"text":"n","confidence":0.9996787},{"text":"t","confidence":0.99992406},{"text":"e","confidence":0.99979645},{"text":"r","confidence":0.9999143},{"text":"h","confidence":0.99988896},{"text":"a","confidence":0.99999005},{"text":"l","confidence":0.999995},{"text":"t","confidence":0.9999774},{"text":"e","confidence":0.999973},{"property":{"detectedBreak":{"type":"LINE_BREAK"}},"text":"n","confidence":0.99854195}],"confidence":0.99963194}],"confidence":0.99719685},{"boundingBox":{"normalizedVertices":[{"x":0.03529412,"y":0.06428572},{"x":0.5588235,"y":0.06666667},{"x":0.5588235,"y":0.08809524},{"x":0.03529412,"y":0.083333336}]},"words":[{"property":{"detectedLanguages":[{"languageCode":"de","confidence":1}]},"boundingBox":{"normalizedVertices":[{"x":0.03529412,"y":0.06428572},{"x":0.18235295,"y":0.06666667},{"x":0.18235295,"y":0.08571429},{"x":0.03529412,"y":0.083333336}]},"symbols":[{"text":"d","confidence":0.3615426},{"text":"s","confidence":0.47151718},{"text":"d","confidence":0.3141409},{"text":"s","confidence":0.5233366},{"property":{"detectedBreak":{"type":"SPACE"}},"text":"б","confidence":0.27798668}],"confidence":0.3897048},{"property":{"detectedLanguages":[{"languageCode":"de","confidence":1}]},"boundingBox":{"normalizedVertices":[{"x":0.20588236,"y":0.06666667},{"x":0.37058824,"y":0.06666667},{"x":0.37058824,"y":0.08571429},{"x":0.20588236,"y":0.08571429}]},"symbols":[{"text":"z","confidence":0.9768774},{"text":"i","confidence":0.9954514},{"text":"t","confidence":0.9922593},{"text":"t","confidence":0.9906207},{"text":"e","confidence":0.9961299},{"text":"r","confidence":0.99105376},{"text":"n","confidence":0.9927118}],"confidence":0.99072915},{"property":{"detectedLanguages":[{"languageCode":"de","confidence":1}]},"boundingBox":{"normalizedVertices":[{"x":0.3764706,"y":0.06666667},{"x":0.38235295,"y":0.06666667},{"x":0.38235295,"y":0.08571429},{"x":0.37058824,"y":0.08571429}]},"symbols":[{"property":{"detectedBreak":{"type":"SPACE"}},"text":",","confidence":0.9797256}],"confidence":0.9797256},{"property":{"detectedLanguages":[{"languageCode":"de","confidence":1}]},"boundingBox":{"normalizedVertices":[{"x":0.4117647,"y":0.06666667},{"x":0.5588235,"y":0.06666667},{"x":0.5588235,"y":0.08809524},{"x":0.4117647,"y":0.08571429}]},"symbols":[{"text":"b","confidence":0.9892885},{"text":"e","confidence":0.993884},{"text":"b","confidence":0.99206185},{"text":"e","confidence":0.9960713},{"property":{"detectedBreak":{"type":"LINE_BREAK"}},"text":"n","confidence":0.98879015}],"confidence":0.9920192}],"confidence":0.82352495},{"boundingBox":{"normalizedVertices":[{"x":0.03529412,"y":0.092857145},{"x":0.9764706,"y":0.092857145},{"x":0.9705882,"y":0.34761906},{"x":0.029411765,"y":0.3452381}]},"words":[{"property":{"detectedLanguages":[{"languageCode":"de","confidence":1}]},"boundingBox":{"normalizedVertices":[{"x":0.03529412,"y":0.092857145},{"x":0.12352941,"y":0.092857145},{"x":0.12352941,"y":0.11666667},{"x":0.03529412,"y":0.11666667}]},"symbols":[{"text":"d","confidence":0.50950146},{"text":"u","confidence":0.2611584},{"property":{"detectedBreak":{"type":"SPACE"}},"text":"g","confidence":0.4402246}],"confidence":0.40362814},{"property":{"detectedLanguages":[{"languageCode":"de","confidence":1}]},"boundingBox":{"normalizedVertices":[{"x":0.1764706,"y":0.092857145},{"x":0.19411765,"y":0.092857145},{"x":0.19411765,"y":0.11666667},{"x":0.1764706,"y":0.11666667}]},"symbols":[{"text":"(","confidence":0.95971376}],"confidence":0.95971376},{"property":{"detectedLanguages":[{"languageCode":"de","confidence":1}]},"boundingBox":{"normalizedVertices":[{"x":0.19411765,"y":0.092857145},{"x":0.3,"y":0.0952381},{"x":0.3,"y":0.11666667},{"x":0.19411765,"y":0.11666667}]},"symbols":[{"text":"k","confidence":0.99480045},{"text":"h","confidence":0.99052495},{"text":"a","confidence":0.9874429},{"text":"r","confidence":0.98951894}],"confidence":0.9905718},{"property":{"detectedLanguages":[{"languageCode":"de","confidence":1}]},"boundingBox":{"normalizedVertices":[{"x":0.30588236,"y":0.0952381},{"x":0.31764707,"y":0.0952381},{"x":0.31764707,"y":0.11666667},{"x":0.30588236,"y":0.11666667}]},"symbols":[{"text":".","confidence":0.9866322}],"confidence":0.9866322},{"property":{"detectedLanguages":[{"languageCode":"de","confidence":1}]},"boundingBox":{"normalizedVertices":[{"x":0.32352942,"y":0.0952381},{"x":0.34117648,"y":0.0952381},{"x":0.34117648,"y":0.11666667},{"x":0.32352942,"y":0.11666667}]},"symbols":[{"property":{"detectedBreak":{"type":"SPACE"}},"text":")","confidence":0.98357075}],"confidence":0.98357075},{"property":{"detectedLanguages":[{"languageCode":"de","confidence":1}]},"boundingBox":{"normalizedVertices":[{"x":0.39411765,"y":0.0952381},{"x":0.43529412,"y":0.0952381},{"x":0.43529412,"y":0.11904762},{"x":0.39411765,"y":0.11666667}]},"symbols":[{"text":"1","confidence":0.951992},{"property":{"detectedBreak":{"type":"SPACE"}},"text":".","confidence":0.9850381}],"confidence":0.96851504},{"property":{"detectedLanguages":[{"languageCode":"de","confidence":1}]},"boundingBox":{"normalizedVertices":[{"x":0.48235294,"y":0.0952381},{"x":0.7352941,"y":0.0952381},{"x":0.7352941,"y":0.11904762},{"x":0.48235294,"y":0.11904762}]},"symbols":[{"text":"a","confidence":0.99779135},{"text":"u","confidence":0.9991703},{"text":"s","confidence":0.9982431},{"text":"p","confidence":0.9970967},{"text":"u","confidence":0.99565554},{"text":"t","confidence":0.9967225},{"text":"z","confidence":0.99597603},{"text":"e","confidence":0.9969182},{"property":{"detectedBreak":{"type":"SPACE"}},"text":"n","confidence":0.99081266}],"confidence":0.9964874},{"property":{"detectedLanguages":[{"languageCode":"de","confidence":1}]},"boundingBox":{"normalizedVertices":[{"x":0.7823529,"y":0.09761905},{"x":0.8,"y":0.09761905},{"x":0.8,"y":0.11904762},{"x":0.7823529,"y":0.11904762}]},"symbols":[{"text":"(","confidence":0.97883314}],"confidence":0.97883314},{"property":{"detectedLanguages":[{"languageCode":"de","confidence":1}]},"boundingBox":{"normalizedVertices":[{"x":0.8,"y":0.09761905},{"x":0.9588235,"y":0.09761905},{"x":0.9588235,"y":0.12142857},{"x":0.8,"y":0.11904762}]},"symbols":[{"text":"K","confidence":0.9987839},{"text":"r","confidence":0.99962205},{"text":"i","confidence":0.9997274},{"text":"p","confidence":0.9992215},{"text":"p","confidence":0.9989061},{"text":"e","confidence":0.9978516}],"confidence":0.9990188},{"property":{"detectedLanguages":[{"languageCode":"de","confidence":1}]},"boundingBox":{"normalizedVertices":[{"x":0.9588235,"y":0.09761905},{"x":0.9764706,"y":0.09761905},{"x":0.9764706,"y":0.12142857},{"x":0.9588235,"y":0.12142857}]},"symbols":[{"property":{"detectedBreak":{"type":"EOL_SURE_SPACE"}},"text":")","confidence":0.9878715}],"confidence":0.9878715},{"property":{"detectedLanguages":[{"languageCode":"de","confidence":1}]},"boundingBox":{"normalizedVertices":[{"x":0.0882353,"y":0.123809524},{"x":0.12941177,"y":0.123809524},{"x":0.12941177,"y":0.1452381},{"x":0.0882353,"y":0.1452381}]},"symbols":[{"text":"2","confidence":0.9860921},{"property":{"detectedBreak":{"type":"SPACE"}},"text":".","confidence":0.99542886}],"confidence":0.99076045},{"property":{"detectedLanguages":[{"languageCode":"de","confidence":1}]},"boundingBox":{"normalizedVertices":[{"x":0.15882353,"y":0.123809524},{"x":0.31764707,"y":0.123809524},{"x":0.31764707,"y":0.1452381},{"x":0.15882353,"y":0.1452381}]},"symbols":[{"text":"s","confidence":0.9984338},{"text":"e","confidence":0.9990465},{"text":"t","confidence":0.9990207},{"text":"z","confidence":0.9994419},{"text":"e","confidence":0.9988428},{"property":{"detectedBreak":{"type":"SPACE"}},"text":"n","confidence":0.9969235}],"confidence":0.9986182},{"property":{"detectedLanguages":[{"languageCode":"de","confidence":1}]},"boundingBox":{"normalizedVertices":[{"x":0.34117648,"y":0.123809524},{"x":0.35882354,"y":0.123809524},{"x":0.35882354,"y":0.1452381},{"x":0.34117648,"y":0.1452381}]},"symbols":[{"text":"(","confidence":0.99816006}],"confidence":0.99816006},{"property":{"detectedLanguages":[{"languageCode":"de","confidence":1}]},"boundingBox":{"normalizedVertices":[{"x":0.35882354,"y":0.123809524},{"x":0.49411765,"y":0.123809524},{"x":0.49411765,"y":0.1452381},{"x":0.35882354,"y":0.1452381}]},"symbols":[{"text":"j","confidence":0.9983723},{"text":"u","confidence":0.993283},{"text":"n","confidence":0.99768317},{"text":"g","confidence":0.98744106},{"property":{"detectedBreak":{"type":"SPACE"}},"text":"e","confidence":0.99658304}],"confidence":0.99467254},{"property":{"detectedLanguages":[{"languageCode":"de","confidence":1}]},"boundingBox":{"normalizedVertices":[{"x":0.5176471,"y":0.123809524},{"x":0.7705882,"y":0.123809524},{"x":0.7705882,"y":0.1452381},{"x":0.5176471,"y":0.1452381}]},"symbols":[{"text":"W","confidence":0.9988501},{"text":"e","confidence":0.99967146},{"text":"i","confidence":0.9994311},{"text":"n","confidence":0.9992},{"text":"r","confidence":0.9991642},{"text":"e","confidence":0.99819857},{"text":"b","confidence":0.9945601},{"text":"e","confidence":0.99873257},{"text":"n","confidence":0.9944739}],"confidence":0.9980313},{"property":{"detectedLanguages":[{"languageCode":"de","confidence":1}]},"boundingBox":{"normalizedVertices":[{"x":0.7764706,"y":0.123809524},{"x":0.7882353,"y":0.123809524},{"x":0.7882353,"y":0.1452381},{"x":0.7764706,"y":0.1452381}]},"symbols":[{"property":{"detectedBreak":{"type":"EOL_SURE_SPACE"}},"text":")","confidence":0.98327243}],"confidence":0.98327243},{"property":{"detectedLanguages":[{"languageCode":"de","confidence":1}]},"boundingBox":{"normalizedVertices":[{"x":0.03529412,"y":0.15238096},{"x":0.21176471,"y":0.15238096},{"x":0.21176471,"y":0.17380953},{"x":0.03529412,"y":0.17380953}]},"symbols":[{"text":"d","confidence":0.44624117},{"text":"s","confidence":0.2952059},{"text":"g","confidence":0.32977915},{"text":"d","confidence":0.31631115},{"text":"s","confidence":0.37936708},{"property":{"detectedBreak":{"type":"SPACE"}},"text":"g","confidence":0.52393013}],"confidence":0.38180578},{"property":{"detectedLanguages":[{"languageCode":"de","confidence":1}]},"boundingBox":{"normalizedVertices":[{"x":0.22941177,"y":0.15238096},{"x":0.24705882,"y":0.15238096},{"x":0.24705882,"y":0.17380953},{"x":0.22941177,"y":0.17380953}]},"symbols":[{"text":"(","confidence":0.98261017}],"confidence":0.98261017},{"property":{"detectedLanguages":[{"languageCode":"de","confidence":1}]},"boundingBox":{"normalizedVertices":[{"x":0.24705882,"y":0.15238096},{"x":0.3647059,"y":0.15238096},{"x":0.3647059,"y":0.17380953},{"x":0.24705882,"y":0.17380953}]},"symbols":[{"text":"p","confidence":0.9936812},{"text":"s","confidence":0.9765282},{"text":"c","confidence":0.98828423},{"text":"h","confidence":0.9887739}],"confidence":0.9868169},{"property":{"detectedLanguages":[{"languageCode":"de","confidence":1}]},"boundingBox":{"normalizedVertices":[{"x":0.3764706,"y":0.15238096},{"x":0.38235295,"y":0.15238096},{"x":0.38235295,"y":0.17380953},{"x":0.3764706,"y":0.17380953}]},"symbols":[{"text":".","confidence":0.9873489}],"confidence":0.9873489},{"property":{"detectedLanguages":[{"languageCode":"de","confidence":1}]},"boundingBox":{"normalizedVertices":[{"x":0.39411765,"y":0.15238096},{"x":0.4117647,"y":0.15238096},{"x":0.4117647,"y":0.17380953},{"x":0.39411765,"y":0.17380953}]},"symbols":[{"property":{"detectedBreak":{"type":"SPACE"}},"text":")","confidence":0.98677164}],"confidence":0.98677164},{"property":{"detectedLanguages":[{"languageCode":"de","confidence":1}]},"boundingBox":{"normalizedVertices":[{"x":0.43529412,"y":0.15238096},{"x":0.59411764,"y":0.15238096},{"x":0.59411764,"y":0.17380953},{"x":0.43529412,"y":0.17380953}]},"symbols":[{"text":"z","confidence":0.9969341},{"text":"i","confidence":0.99748623},{"text":"t","confidence":0.9970968},{"text":"t","confidence":0.99260694},{"text":"e","confidence":0.99674016},{"text":"r","confidence":0.99252456},{"text":"n","confidence":0.9935952}],"confidence":0.9952834},{"property":{"detectedLanguages":[{"languageCode":"de","confidence":1}]},"boundingBox":{"normalizedVertices":[{"x":0.6,"y":0.15238096},{"x":0.6117647,"y":0.15238096},{"x":0.6117647,"y":0.17380953},{"x":0.6,"y":0.17380953}]},"symbols":[{"property":{"detectedBreak":{"type":"SPACE"}},"text":",","confidence":0.9948362}],"confidence":0.9948362},{"property":{"detectedLanguages":[{"languageCode":"de","confidence":1}]},"boundingBox":{"normalizedVertices":[{"x":0.63529414,"y":0.15238096},{"x":0.7823529,"y":0.15238096},{"x":0.7823529,"y":0.17380953},{"x":0.63529414,"y":0.17380953}]},"symbols":[{"text":"b","confidence":0.9972187},{"text":"e","confidence":0.996699},{"text":"b","confidence":0.99242425},{"text":"e","confidence":0.99574995},{"property":{"detectedBreak":{"type":"EOL_SURE_SPACE"}},"text":"n","confidence":0.99095404}],"confidence":0.9946092},{"property":{"detectedLanguages":[{"languageCode":"de","confidence":1}]},"boundingBox":{"normalizedVertices":[{"x":0.03529412,"y":0.17857143},{"x":0.19411765,"y":0.18095239},{"x":0.19411765,"y":0.20476191},{"x":0.03529412,"y":0.20238096}]},"symbols":[{"text":"d","confidence":0.41086173},{"text":"â","confidence":0.21501747},{"text":"m","confidence":0.28511137},{"property":{"detectedBreak":{"type":"SPACE"}},"text":"б","confidence":0.30216002}],"confidence":0.30328766},{"property":{"detectedLanguages":[{"languageCode":"de","confidence":1}]},"boundingBox":{"normalizedVertices":[{"x":0.21176471,"y":0.18095239},{"x":0.41764706,"y":0.18095239},{"x":0.41764706,"y":0.20476191},{"x":0.21176471,"y":0.20476191}]},"symbols":[{"text":"t","confidence":0.9868766},{"text":"r","confidence":0.98978424},{"text":"a","confidence":0.98781323},{"text":"p","confidence":0.98931795},{"text":"p","confidence":0.98571014},{"text":"e","confidence":0.98976517},{"text":"l","confidence":0.99369234},{"text":"n","confidence":0.9964754}],"confidence":0.9899294},{"property":{"detectedLanguages":[{"languageCode":"de","confidence":1}]},"boundingBox":{"normalizedVertices":[{"x":0.42352942,"y":0.18095239},{"x":0.42941177,"y":0.18095239},{"x":0.42941177,"y":0.20476191},{"x":0.42352942,"y":0.20476191}]},"symbols":[{"property":{"detectedBreak":{"type":"SPACE"}},"text":",","confidence":0.9972298}],"confidence":0.9972298},{"property":{"detectedLanguages":[{"languageCode":"de","confidence":1}]},"boundingBox":{"normalizedVertices":[{"x":0.45882353,"y":0.18095239},{"x":0.6764706,"y":0.18333334},{"x":0.67058825,"y":0.20714286},{"x":0.45882353,"y":0.20476191}]},"symbols":[{"text":"t","confidence":0.9983144},{"text":"r","confidence":0.9985825},{"text":"a","confidence":0.99797964},{"text":"m","confidence":0.9977187},{"text":"p","confidence":0.9949993},{"text":"e","confidence":0.9943237},{"text":"l","confidence":0.9837666},{"property":{"detectedBreak":{"type":"EOL_SURE_SPACE"}},"text":"n","confidence":0.98813915}],"confidence":0.994228},{"property":{"detectedLanguages":[{"languageCode":"de","confidence":1}]},"boundingBox":{"normalizedVertices":[{"x":0.064705886,"y":0.21190476},{"x":0.12941177,"y":0.21190476},{"x":0.12941177,"y":0.23095238},{"x":0.064705886,"y":0.23095238}]},"symbols":[{"text":"s","confidence":0.30304205},{"property":{"detectedBreak":{"type":"SPACE"}},"text":"o","confidence":0.3239256}],"confidence":0.31348383},{"property":{"detectedLanguages":[{"languageCode":"de","confidence":1}]},"boundingBox":{"normalizedVertices":[{"x":0.15294118,"y":0.21190476},{"x":0.34705883,"y":0.21190476},{"x":0.34705883,"y":0.23095238},{"x":0.15294118,"y":0.23095238}]},"symbols":[{"text":"g","confidence":0.9847823},{"text":"e","confidence":0.99274945},{"text":"b","confidence":0.9916643},{"text":"ä","confidence":0.94888836},{"text":"r","confidence":0.99464655},{"text":"e","confidence":0.99118567},{"text":"n","confidence":0.9855752}],"confidence":0.9842131},{"property":{"detectedLanguages":[{"languageCode":"de","confidence":1}]},"boundingBox":{"normalizedVertices":[{"x":0.3529412,"y":0.21190476},{"x":0.3647059,"y":0.21190476},{"x":0.3647059,"y":0.23095238},{"x":0.3529412,"y":0.23095238}]},"symbols":[{"property":{"detectedBreak":{"type":"SPACE"}},"text":";","confidence":0.964435}],"confidence":0.964435},{"property":{"detectedLanguages":[{"languageCode":"de","confidence":1}]},"boundingBox":{"normalizedVertices":[{"x":0.3882353,"y":0.20952381},{"x":0.6882353,"y":0.20952381},{"x":0.6882353,"y":0.23095238},{"x":0.3882353,"y":0.23095238}]},"symbols":[{"text":"v","confidence":0.9931533},{"text":"e","confidence":0.9950378},{"text":"r","confidence":0.9956726},{"text":"u","confidence":0.9928343},{"text":"r","confidence":0.9942424},{"text":"s","confidence":0.99392176},{"text":"a","confidence":0.99523914},{"text":"c","confidence":0.99508333},{"text":"h","confidence":0.99598074},{"text":"e","confidence":0.9971564},{"property":{"detectedBreak":{"type":"EOL_SURE_SPACE"}},"text":"n","confidence":0.99411875}],"confidence":0.9947673},{"property":{"detectedLanguages":[{"languageCode":"de","confidence":1}]},"boundingBox":{"normalizedVertices":[{"x":0.03529412,"y":0.24047619},{"x":0.1882353,"y":0.24047619},{"x":0.1882353,"y":0.2595238},{"x":0.03529412,"y":0.2595238}]},"symbols":[{"text":"a","confidence":0.23772931},{"text":"s","confidence":0.28712422},{"text":"o","confidence":0.30284366},{"text":"s","confidence":0.40675974},{"property":{"detectedBreak":{"type":"SPACE"}},"text":"a","confidence":0.37182426}],"confidence":0.32125625},{"property":{"detectedLanguages":[{"languageCode":"de","confidence":1}]},"boundingBox":{"normalizedVertices":[{"x":0.21176471,"y":0.24047619},{"x":0.46470588,"y":0.24047619},{"x":0.46470588,"y":0.2595238},{"x":0.21176471,"y":0.2595238}]},"symbols":[{"text":"e","confidence":0.98957723},{"text":"i","confidence":0.9943041},{"text":"n","confidence":0.9919846},{"text":"k","confidence":0.9841355},{"text":"o","confidence":0.98965174},{"text":"c","confidence":0.9866912},{"text":"h","confidence":0.9936916},{"text":"e","confidence":0.9923004},{"property":{"detectedBreak":{"type":"SPACE"}},"text":"n","confidence":0.9940059}],"confidence":0.9907047},{"property":{"detectedLanguages":[{"languageCode":"de","confidence":1}]},"boundingBox":{"normalizedVertices":[{"x":0.4882353,"y":0.24047619},{"x":0.5058824,"y":0.24047619},{"x":0.5058824,"y":0.2595238},{"x":0.4882353,"y":0.2595238}]},"symbols":[{"text":"(","confidence":0.99043775}],"confidence":0.99043775},{"property":{"detectedLanguages":[{"languageCode":"de","confidence":1}]},"boundingBox":{"normalizedVertices":[{"x":0.5117647,"y":0.24047619},{"x":0.8117647,"y":0.24047619},{"x":0.8117647,"y":0.2595238},{"x":0.5117647,"y":0.2595238}]},"symbols":[{"text":"T","confidence":0.9941923},{"text":"r","confidence":0.99182993},{"text":"a","confidence":0.9902854},{"text":"u","confidence":0.99212146},{"text":"b","confidence":0.9922103},{"text":"e","confidence":0.99466467},{"text":"n","confidence":0.99523103},{"text":"s","confidence":0.99524975},{"text":"a","confidence":0.9944261},{"text":"f","confidence":0.9888734},{"text":"t","confidence":0.99168265}],"confidence":0.992797},{"property":{"detectedLanguages":[{"languageCode":"de","confidence":1}]},"boundingBox":{"normalizedVertices":[{"x":0.8117647,"y":0.24047619},{"x":0.82941175,"y":0.24047619},{"x":0.82941175,"y":0.2595238},{"x":0.8117647,"y":0.2595238}]},"symbols":[{"property":{"detectedBreak":{"type":"EOL_SURE_SPACE"}},"text":")","confidence":0.9725338}],"confidence":0.9725338},{"property":{"detectedLanguages":[{"languageCode":"de","confidence":1}]},"boundingBox":{"normalizedVertices":[{"x":0.064705886,"y":0.26904762},{"x":0.17058824,"y":0.26904762},{"x":0.17058824,"y":0.2904762},{"x":0.064705886,"y":0.2904762}]},"symbols":[{"text":"s","confidence":0.31467164},{"text":"o","confidence":0.28012925},{"property":{"detectedBreak":{"type":"SPACE"}},"text":"m","confidence":0.5189927}],"confidence":0.37126455},{"property":{"detectedLanguages":[{"languageCode":"de","confidence":1}]},"boundingBox":{"normalizedVertices":[{"x":0.2,"y":0.26904762},{"x":0.46470588,"y":0.26904762},{"x":0.46470588,"y":0.2904762},{"x":0.2,"y":0.2904762}]},"symbols":[{"text":"e","confidence":0.99317586},{"text":"b","confidence":0.991807},{"text":"e","confidence":0.99451804},{"text":"n","confidence":0.9921777},{"text":"b","confidence":0.9923453},{"text":"ü","confidence":0.9410268},{"text":"r","confidence":0.9895185},{"text":"t","confidence":0.99281204},{"text":"i","confidence":0.99187815},{"property":{"detectedBreak":{"type":"SPACE"}},"text":"g","confidence":0.9917473}],"confidence":0.98710066},{"property":{"detectedLanguages":[{"languageCode":"de","confidence":1}]},"boundingBox":{"normalizedVertices":[{"x":0.4882353,"y":0.26904762},{"x":0.59411764,"y":0.27142859},{"x":0.59411764,"y":0.2904762},{"x":0.4882353,"y":0.2904762}]},"symbols":[{"text":"s","confidence":0.9945154},{"text":"e","confidence":0.9948178},{"text":"i","confidence":0.99096555},{"text":"n","confidence":0.99319476}],"confidence":0.9933734},{"property":{"detectedLanguages":[{"languageCode":"de","confidence":1}]},"boundingBox":{"normalizedVertices":[{"x":0.59411764,"y":0.27142859},{"x":0.60588235,"y":0.27142859},{"x":0.60588235,"y":0.2904762},{"x":0.59411764,"y":0.2904762}]},"symbols":[{"property":{"detectedBreak":{"type":"SPACE"}},"text":";","confidence":0.9831257}],"confidence":0.9831257},{"property":{"detectedLanguages":[{"languageCode":"de","confidence":1}]},"boundingBox":{"normalizedVertices":[{"x":0.63529414,"y":0.27142859},{"x":0.84705883,"y":0.27142859},{"x":0.84705883,"y":0.29285714},{"x":0.63529414,"y":0.2904762}]},"symbols":[{"text":"e","confidence":0.99225503},{"text":"r","confidence":0.9924008},{"text":"s","confidence":0.99126756},{"text":"e","confidence":0.9906162},{"text":"t","confidence":0.9905306},{"text":"z","confidence":0.9911529},{"text":"e","confidence":0.99633384},{"property":{"detectedBreak":{"type":"EOL_SURE_SPACE"}},"text":"n","confidence":0.9937679}],"confidence":0.9922906},{"property":{"detectedLanguages":[{"languageCode":"de","confidence":1}]},"boundingBox":{"normalizedVertices":[{"x":0.03529412,"y":0.29761904},{"x":0.16470589,"y":0.29761904},{"x":0.16470589,"y":0.31666666},{"x":0.03529412,"y":0.31666666}]},"symbols":[{"text":"d","confidence":0.29092222},{"text":"o","confidence":0.27696848},{"property":{"detectedBreak":{"type":"SPACE"}},"text":"m","confidence":0.3372171}],"confidence":0.3017026},{"property":{"detectedLanguages":[{"languageCode":"de","confidence":1}]},"boundingBox":{"normalizedVertices":[{"x":0.2,"y":0.29761904},{"x":0.44117647,"y":0.29761904},{"x":0.44117647,"y":0.31904763},{"x":0.2,"y":0.31666666}]},"symbols":[{"text":"z","confidence":0.9618054},{"text":"u","confidence":0.9852132},{"text":"n","confidence":0.9912221},{"text":"e","confidence":0.99341136},{"text":"h","confidence":0.9936108},{"text":"m","confidence":0.9925477},{"text":"e","confidence":0.98844767},{"property":{"detectedBreak":{"type":"SPACE"}},"text":"n","confidence":0.99314386}],"confidence":0.98742527},{"property":{"detectedLanguages":[{"languageCode":"de","confidence":1}]},"boundingBox":{"normalizedVertices":[{"x":0.47058824,"y":0.3},{"x":0.48235294,"y":0.3},{"x":0.48235294,"y":0.31904763},{"x":0.47058824,"y":0.31904763}]},"symbols":[{"text":"(","confidence":0.987025}],"confidence":0.987025},{"property":{"detectedLanguages":[{"languageCode":"de","confidence":1}]},"boundingBox":{"normalizedVertices":[{"x":0.49411765,"y":0.3},{"x":0.5176471,"y":0.3},{"x":0.5176471,"y":0.31904763},{"x":0.49411765,"y":0.31904763}]},"symbols":[{"text":"v","confidence":0.9889899}],"confidence":0.9889899},{"property":{"detectedLanguages":[{"languageCode":"de","confidence":1}]},"boundingBox":{"normalizedVertices":[{"x":0.5235294,"y":0.3},{"x":0.5352941,"y":0.3},{"x":0.5352941,"y":0.31904763},{"x":0.5235294,"y":0.31904763}]},"symbols":[{"property":{"detectedBreak":{"type":"SPACE"}},"text":".","confidence":0.9883383}],"confidence":0.9883383},{"property":{"detectedLanguages":[{"languageCode":"de","confidence":1}]},"boundingBox":{"normalizedVertices":[{"x":0.5647059,"y":0.3},{"x":0.6882353,"y":0.3},{"x":0.6882353,"y":0.31904763},{"x":0.5647059,"y":0.31904763}]},"symbols":[{"text":"M","confidence":0.9952646},{"text":"o","confidence":0.994516},{"text":"n","confidence":0.9910096},{"text":"d","confidence":0.9910902}],"confidence":0.9929701},{"property":{"detectedLanguages":[{"languageCode":"de","confidence":1}]},"boundingBox":{"normalizedVertices":[{"x":0.69411767,"y":0.3},{"x":0.7117647,"y":0.3},{"x":0.7117647,"y":0.31904763},{"x":0.69411767,"y":0.31904763}]},"symbols":[{"text":")","confidence":0.9910397}],"confidence":0.9910397},{"property":{"detectedLanguages":[{"languageCode":"de","confidence":1}]},"boundingBox":{"normalizedVertices":[{"x":0.7176471,"y":0.3},{"x":0.7235294,"y":0.3},{"x":0.7235294,"y":0.31904763},{"x":0.7176471,"y":0.31904763}]},"symbols":[{"property":{"detectedBreak":{"type":"SPACE"}},"text":";","confidence":0.9914112}],"confidence":0.9914112},{"property":{"detectedLanguages":[{"languageCode":"de","confidence":1}]},"boundingBox":{"normalizedVertices":[{"x":0.7588235,"y":0.3},{"x":0.9,"y":0.3},{"x":0.9,"y":0.31904763},{"x":0.7588235,"y":0.31904763}]},"symbols":[{"text":"s","confidence":0.99038464},{"text":"c","confidence":0.99244255},{"text":"h","confidence":0.9857978},{"text":"ö","confidence":0.96850353},{"property":{"detectedBreak":{"type":"SPACE"}},"text":"n","confidence":0.9864575}],"confidence":0.9847172},{"property":{"detectedLanguages":[{"languageCode":"de","confidence":1}]},"boundingBox":{"normalizedVertices":[{"x":0.92941177,"y":0.3},{"x":0.9588235,"y":0.3},{"x":0.9588235,"y":0.31904763},{"x":0.92941177,"y":0.31904763}]},"symbols":[{"text":"w","confidence":0.9645636}],"confidence":0.9645636},{"property":{"detectedLanguages":[{"languageCode":"de","confidence":1}]},"boundingBox":{"normalizedVertices":[{"x":0.9647059,"y":0.3},{"x":0.9705882,"y":0.3},{"x":0.9705882,"y":0.31904763},{"x":0.9647059,"y":0.31904763}]},"symbols":[{"property":{"detectedBreak":{"type":"EOL_SURE_SPACE"}},"text":".","confidence":0.89602387}],"confidence":0.89602387},{"property":{"detectedLanguages":[{"languageCode":"de","confidence":1}]},"boundingBox":{"normalizedVertices":[{"x":0.08235294,"y":0.32857144},{"x":0.1,"y":0.32857144},{"x":0.1,"y":0.3452381},{"x":0.08235294,"y":0.3452381}]},"symbols":[{"text":"(","confidence":0.95486623}],"confidence":0.95486623},{"property":{"detectedLanguages":[{"languageCode":"de","confidence":1}]},"boundingBox":{"normalizedVertices":[{"x":0.105882354,"y":0.32857144},{"x":0.20588236,"y":0.32857144},{"x":0.20588236,"y":0.3452381},{"x":0.105882354,"y":0.3452381}]},"symbols":[{"text":"z","confidence":0.9437364},{"text":".","confidence":0.9917381},{"text":"B","confidence":0.9939222},{"property":{"detectedBreak":{"type":"SPACE"}},"text":".","confidence":0.9859301}],"confidence":0.97883165},{"property":{"detectedLanguages":[{"languageCode":"de","confidence":1}]},"boundingBox":{"normalizedVertices":[{"x":0.23529412,"y":0.32857144},{"x":0.34705883,"y":0.32857144},{"x":0.34705883,"y":0.3452381},{"x":0.23529412,"y":0.3452381}]},"symbols":[{"text":"F","confidence":0.9915228},{"text":"r","confidence":0.9950537},{"text":"a","confidence":0.9924216},{"text":"u","confidence":0.9903716}],"confidence":0.9923424},{"property":{"detectedLanguages":[{"languageCode":"de","confidence":1}]},"boundingBox":{"normalizedVertices":[{"x":0.3529412,"y":0.32857144},{"x":0.37058824,"y":0.32857144},{"x":0.37058824,"y":0.3452381},{"x":0.3529412,"y":0.3452381}]},"symbols":[{"property":{"detectedBreak":{"type":"LINE_BREAK"}},"text":")","confidence":0.96644944}],"confidence":0.96644944}],"confidence":0.91050136}],"blockType":"TEXT","confidence":0.910132},{"boundingBox":{"normalizedVertices":[{"x":0.03529412,"y":0.3547619},{"x":0.9705882,"y":0.35714287},{"x":0.9705882,"y":0.5190476},{"x":0.029411765,"y":0.51666665}]},"paragraphs":[{"boundingBox":{"normalizedVertices":[{"x":0.03529412,"y":0.3547619},{"x":0.7294118,"y":0.3547619},{"x":0.7294118,"y":0.40714285},{"x":0.03529412,"y":0.40714285}]},"words":[{"property":{"detectedLanguages":[{"languageCode":"de","confidence":1}]},"boundingBox":{"normalizedVertices":[{"x":0.03529412,"y":0.3547619},{"x":0.22941177,"y":0.3547619},{"x":0.22941177,"y":0.37619048},{"x":0.03529412,"y":0.37619048}]},"symbols":[{"text":"d","confidence":0.2677319},{"text":"s","confidence":0.26732984},{"text":"o","confidence":0.27072278},{"text":"m","confidence":0.33906195},{"text":"a","confidence":0.28600335},{"property":{"detectedBreak":{"type":"SPACE"}},"text":"g","confidence":0.37131014}],"confidence":0.30036},{"property":{"detectedLanguages":[{"languageCode":"de","confidence":1}]},"boundingBox":{"normalizedVertices":[{"x":0.2529412,"y":0.35714287},{"x":0.48235294,"y":0.35714287},{"x":0.48235294,"y":0.37619048},{"x":0.2529412,"y":0.37619048}]},"symbols":[{"text":"b","confidence":0.99205834},{"text":"e","confidence":0.9938622},{"text":"g","confidence":0.98949677},{"text":"l","confidence":0.9945698},{"text":"e","confidence":0.99280894},{"text":"i","confidence":0.99467725},{"text":"t","confidence":0.9957553},{"text":"e","confidence":0.9942555},{"text":"n","confidence":0.9906832}],"confidence":0.9931297},{"property":{"detectedLanguages":[{"languageCode":"de","confidence":1}]},"boundingBox":{"normalizedVertices":[{"x":0.4882353,"y":0.35714287},{"x":0.5,"y":0.35714287},{"x":0.5,"y":0.37619048},{"x":0.4882353,"y":0.37619048}]},"symbols":[{"property":{"detectedBreak":{"type":"SPACE"}},"text":",","confidence":0.98989314}],"confidence":0.98989314},{"property":{"detectedLanguages":[{"languageCode":"de","confidence":1}]},"boundingBox":{"normalizedVertices":[{"x":0.5294118,"y":0.35714287},{"x":0.7294118,"y":0.35714287},{"x":0.7294118,"y":0.37619048},{"x":0.5294118,"y":0.37619048}]},"symbols":[{"text":"g","confidence":0.9931725},{"text":"e","confidence":0.99586},{"text":"l","confidence":0.99368054},{"text":"e","confidence":0.9961332},{"text":"i","confidence":0.99491596},{"text":"t","confidence":0.99610716},{"text":"e","confidence":0.99656606},{"property":{"detectedBreak":{"type":"EOL_SURE_SPACE"}},"text":"n","confidence":0.993591}],"confidence":0.9950033},{"property":{"detectedLanguages":[{"languageCode":"de","confidence":1}]},"boundingBox":{"normalizedVertices":[{"x":0.03529412,"y":0.38333333},{"x":0.1882353,"y":0.38333333},{"x":0.1882353,"y":0.40714285},{"x":0.03529412,"y":0.40714285}]},"symbols":[{"text":"ბ","confidence":0.9995689},{"text":"ა","confidence":0.99992573},{"text":"ვ","confidence":0.99988616},{"text":"შ","confidence":0.9966833},{"property":{"detectedBreak":{"type":"SPACE"}},"text":"ვ","confidence":0.9837515}],"confidence":0.9959631},{"property":{"detectedLanguages":[{"languageCode":"de","confidence":1}]},"boundingBox":{"normalizedVertices":[{"x":0.21764706,"y":0.38333333},{"x":0.42352942,"y":0.38333333},{"x":0.42352942,"y":0.40714285},{"x":0.21764706,"y":0.40714285}]},"symbols":[{"text":"k","confidence":0.99989545},{"text":"i","confidence":0.9997342},{"text":"n","confidence":0.99989504},{"text":"d","confidence":0.99901414},{"text":"i","confidence":0.99865884},{"text":"s","confidence":0.99982285},{"text":"c","confidence":0.99988186},{"property":{"detectedBreak":{"type":"SPACE"}},"text":"h","confidence":0.9993054}],"confidence":0.99952596},{"property":{"detectedLanguages":[{"languageCode":"de","confidence":1}]},"boundingBox":{"normalizedVertices":[{"x":0.45294118,"y":0.38333333},{"x":0.5529412,"y":0.38333333},{"x":0.5529412,"y":0.40714285},{"x":0.45294118,"y":0.40714285}]},"symbols":[{"text":"s","confidence":0.9506509},{"text":"e","confidence":0.9882456},{"text":"i","confidence":0.99894166},{"property":{"detectedBreak":{"type":"LINE_BREAK"}},"text":"n","confidence":0.9890257}],"confidence":0.981716}],"confidence":0.8925155},{"boundingBox":{"normalizedVertices":[{"x":0.03529412,"y":0.41190475},{"x":0.62352943,"y":0.41428572},{"x":0.62352943,"y":0.43333334},{"x":0.03529412,"y":0.43333334}]},"words":[{"property":{"detectedLanguages":[{"languageCode":"de","confidence":1}]},"boundingBox":{"normalizedVertices":[{"x":0.03529412,"y":0.41190475},{"x":0.0882353,"y":0.41190475},{"x":0.0882353,"y":0.43333334},{"x":0.03529412,"y":0.43333334}]},"symbols":[{"text":"d","confidence":0.39838582},{"text":"5","confidence":0.24490668}],"confidence":0.32164624},{"property":{"detectedLanguages":[{"languageCode":"de","confidence":1}]},"boundingBox":{"normalizedVertices":[{"x":0.09411765,"y":0.41190475},{"x":0.12941177,"y":0.41190475},{"x":0.12941177,"y":0.43333334},{"x":0.09411765,"y":0.43333334}]},"symbols":[{"property":{"detectedBreak":{"type":"SPACE"}},"text":"%","confidence":0.94183975}],"confidence":0.94183975},{"property":{"detectedLanguages":[{"languageCode":"de","confidence":1}]},"boundingBox":{"normalizedVertices":[{"x":0.15294118,"y":0.41190475},{"x":0.17058824,"y":0.41190475},{"x":0.17058824,"y":0.43333334},{"x":0.15294118,"y":0.43333334}]},"symbols":[{"text":"(","confidence":0.97892576}],"confidence":0.97892576},{"property":{"detectedLanguages":[{"languageCode":"de","confidence":1}]},"boundingBox":{"normalizedVertices":[{"x":0.1764706,"y":0.41190475},{"x":0.28235295,"y":0.41190475},{"x":0.28235295,"y":0.43333334},{"x":0.1764706,"y":0.43333334}]},"symbols":[{"text":"i","confidence":0.9891787},{"text":"m","confidence":0.9906166},{"text":"e","confidence":0.9912237},{"text":"r","confidence":0.98938715}],"confidence":0.9901016},{"property":{"detectedLanguages":[{"languageCode":"de","confidence":1}]},"boundingBox":{"normalizedVertices":[{"x":0.28235295,"y":0.41190475},{"x":0.29411766,"y":0.41190475},{"x":0.29411766,"y":0.43333334},{"x":0.28235295,"y":0.43333334}]},"symbols":[{"text":".","confidence":0.97172743}],"confidence":0.97172743},{"property":{"detectedLanguages":[{"languageCode":"de","confidence":1}]},"boundingBox":{"normalizedVertices":[{"x":0.30588236,"y":0.41190475},{"x":0.31764707,"y":0.41190475},{"x":0.31764707,"y":0.43333334},{"x":0.30588236,"y":0.43333334}]},"symbols":[{"property":{"detectedBreak":{"type":"SPACE"}},"text":",","confidence":0.98417145}],"confidence":0.98417145},{"property":{"detectedLanguages":[{"languageCode":"de","confidence":1}]},"boundingBox":{"normalizedVertices":[{"x":0.34117648,"y":0.41190475},{"x":0.41764706,"y":0.41428572},{"x":0.41764706,"y":0.43333334},{"x":0.34117648,"y":0.43333334}]},"symbols":[{"text":"g","confidence":0.99049073},{"text":"u","confidence":0.98711896},{"text":"r","confidence":0.9851316}],"confidence":0.9875804},{"property":{"detectedLanguages":[{"languageCode":"de","confidence":1}]},"boundingBox":{"normalizedVertices":[{"x":0.42352942,"y":0.41428572},{"x":0.43529412,"y":0.41428572},{"x":0.43529412,"y":0.43333334},{"x":0.42352942,"y":0.43333334}]},"symbols":[{"text":".","confidence":0.9851319}],"confidence":0.9851319},{"property":{"detectedLanguages":[{"languageCode":"de","confidence":1}]},"boundingBox":{"normalizedVertices":[{"x":0.44117647,"y":0.41428572},{"x":0.45882353,"y":0.41428572},{"x":0.45882353,"y":0.43333334},{"x":0.44117647,"y":0.43333334}]},"symbols":[{"property":{"detectedBreak":{"type":"SPACE"}},"text":")","confidence":0.97491014}],"confidence":0.97491014},{"property":{"detectedLanguages":[{"languageCode":"de","confidence":1}]},"boundingBox":{"normalizedVertices":[{"x":0.4764706,"y":0.41428572},{"x":0.62352943,"y":0.41428572},{"x":0.62352943,"y":0.43333334},{"x":0.4764706,"y":0.43333334}]},"symbols":[{"text":"r","confidence":0.99500495},{"text":"e","confidence":0.99538153},{"text":"i","confidence":0.9959572},{"text":"f","confidence":0.99600136},{"text":"e","confidence":0.99632597},{"property":{"detectedBreak":{"type":"LINE_BREAK"}},"text":"n","confidence":0.99213403}],"confidence":0.9951342}],"confidence":0.9225691},{"boundingBox":{"normalizedVertices":[{"x":0.09411765,"y":0.43809524},{"x":0.8,"y":0.44285715},{"x":0.8,"y":0.46190476},{"x":0.09411765,"y":0.45714286}]},"words":[{"property":{"detectedLanguages":[{"languageCode":"de","confidence":1}]},"boundingBox":{"normalizedVertices":[{"x":0.09411765,"y":0.43809524},{"x":0.2,"y":0.44047618},{"x":0.19411765,"y":0.4595238},{"x":0.09411765,"y":0.45714286}]},"symbols":[{"text":"%","confidence":0.60887116},{"property":{"detectedBreak":{"type":"SPACE"}},"text":"%","confidence":0.6012909}],"confidence":0.605081},{"property":{"detectedLanguages":[{"languageCode":"de","confidence":1}]},"boundingBox":{"normalizedVertices":[{"x":0.22941177,"y":0.44047618},{"x":0.24705882,"y":0.44047618},{"x":0.24705882,"y":0.4595238},{"x":0.22941177,"y":0.4595238}]},"symbols":[{"property":{"detectedBreak":{"type":"SPACE"}},"text":"+","confidence":0.42573678}],"confidence":0.42573678},{"property":{"detectedLanguages":[{"languageCode":"de","confidence":1}]},"boundingBox":{"normalizedVertices":[{"x":0.27058825,"y":0.44047618},{"x":0.46470588,"y":0.44047618},{"x":0.46470588,"y":0.4595238},{"x":0.27058825,"y":0.4595238}]},"symbols":[{"text":"h","confidence":0.9846985},{"text":"a","confidence":0.99549276},{"text":"n","confidence":0.9945397},{"text":"d","confidence":0.9950109},{"text":"e","confidence":0.9922528},{"text":"l","confidence":0.99094707},{"property":{"detectedBreak":{"type":"SPACE"}},"text":"n","confidence":0.99288076}],"confidence":0.99226034},{"property":{"detectedLanguages":[{"languageCode":"de","confidence":1}]},"boundingBox":{"normalizedVertices":[{"x":0.4882353,"y":0.44047618},{"x":0.5058824,"y":0.44047618},{"x":0.5,"y":0.4595238},{"x":0.4882353,"y":0.4595238}]},"symbols":[{"text":"(","confidence":0.9908077}],"confidence":0.9908077},{"property":{"detectedLanguages":[{"languageCode":"de","confidence":1}]},"boundingBox":{"normalizedVertices":[{"x":0.5117647,"y":0.44047618},{"x":0.5882353,"y":0.44047618},{"x":0.58235294,"y":0.4595238},{"x":0.5117647,"y":0.4595238}]},"symbols":[{"text":"m","confidence":0.99406666},{"text":"i","confidence":0.989433},{"property":{"detectedBreak":{"type":"SPACE"}},"text":"t","confidence":0.987892}],"confidence":0.99046385},{"property":{"detectedLanguages":[{"languageCode":"de","confidence":1}]},"boundingBox":{"normalizedVertices":[{"x":0.60588235,"y":0.44047618},{"x":0.7823529,"y":0.44285715},{"x":0.7823529,"y":0.46190476},{"x":0.60588235,"y":0.4595238}]},"symbols":[{"text":"S","confidence":0.98854417},{"text":"t","confidence":0.98505867},{"text":"o","confidence":0.991162},{"text":"f","confidence":0.9940762},{"text":"f","confidence":0.9952815},{"text":"e","confidence":0.9937698},{"text":"n","confidence":0.9949487}],"confidence":0.99183446},{"property":{"detectedLanguages":[{"languageCode":"de","confidence":1}]},"boundingBox":{"normalizedVertices":[{"x":0.7823529,"y":0.44285715},{"x":0.8,"y":0.44285715},{"x":0.8,"y":0.46190476},{"x":0.7823529,"y":0.46190476}]},"symbols":[{"property":{"detectedBreak":{"type":"LINE_BREAK"}},"text":")","confidence":0.991384}],"confidence":0.991384}],"confidence":0.9308248},{"boundingBox":{"normalizedVertices":[{"x":0.029411765,"y":0.4690476},{"x":0.9705882,"y":0.47142857},{"x":0.9705882,"y":0.5190476},{"x":0.029411765,"y":0.51666665}]},"words":[{"property":{"detectedLanguages":[{"languageCode":"de","confidence":1}]},"boundingBox":{"normalizedVertices":[{"x":0.029411765,"y":0.47142857},{"x":0.19411765,"y":0.47142857},{"x":0.19411765,"y":0.49285713},{"x":0.029411765,"y":0.4904762}]},"symbols":[{"text":"a","confidence":0.24201846},{"text":"s","confidence":0.3104933},{"text":"o","confidence":0.37524003},{"text":"o","confidence":0.6086299},{"property":{"detectedBreak":{"type":"SPACE"}},"text":"m","confidence":0.3755624}],"confidence":0.3823888},{"property":{"detectedLanguages":[{"languageCode":"de","confidence":1}]},"boundingBox":{"normalizedVertices":[{"x":0.22941177,"y":0.47142857},{"x":0.29411766,"y":0.47142857},{"x":0.29411766,"y":0.49285713},{"x":0.22941177,"y":0.49285713}]},"symbols":[{"text":"f","confidence":0.9884956},{"text":"ü","confidence":0.96496105},{"property":{"detectedBreak":{"type":"SPACE"}},"text":"r","confidence":0.9892562}],"confidence":0.9809043},{"property":{"detectedLanguages":[{"languageCode":"de","confidence":1}]},"boundingBox":{"normalizedVertices":[{"x":0.32352942,"y":0.47142857},{"x":0.5294118,"y":0.47142857},{"x":0.5294118,"y":0.49285713},{"x":0.32352942,"y":0.49285713}]},"symbols":[{"text":"u","confidence":0.9907895},{"text":"n","confidence":0.9925493},{"text":"g","confidence":0.99343663},{"text":"ü","confidence":0.9849273},{"text":"l","confidence":0.9980083},{"text":"t","confidence":0.99729526},{"text":"i","confidence":0.9965967},{"text":"g","confidence":0.99172336}],"confidence":0.9931658},{"property":{"detectedLanguages":[{"languageCode":"de","confidence":1}]},"boundingBox":{"normalizedVertices":[{"x":0.5294118,"y":0.47142857},{"x":0.5588235,"y":0.47142857},{"x":0.5588235,"y":0.49285713},{"x":0.5294118,"y":0.49285713}]},"symbols":[{"text":"/","confidence":0.9815732}],"confidence":0.9815732},{"property":{"detectedLanguages":[{"languageCode":"de","confidence":1}]},"boundingBox":{"normalizedVertices":[{"x":0.5588235,"y":0.47142857},{"x":0.7352941,"y":0.47142857},{"x":0.7352941,"y":0.49285713},{"x":0.5588235,"y":0.49285713}]},"symbols":[{"text":"n","confidence":0.9960569},{"text":"i","confidence":0.99535173},{"text":"c","confidence":0.99700975},{"text":"h","confidence":0.9961326},{"text":"t","confidence":0.9922459},{"text":"i","confidence":0.99850535},{"property":{"detectedBreak":{"type":"SPACE"}},"text":"g","confidence":0.99438083}],"confidence":0.995669},{"property":{"detectedLanguages":[{"languageCode":"de","confidence":1}]},"boundingBox":{"normalizedVertices":[{"x":0.7588235,"y":0.47142857},{"x":0.9588235,"y":0.47142857},{"x":0.9588235,"y":0.49285713},{"x":0.7588235,"y":0.49285713}]},"symbols":[{"text":"e","confidence":0.9936795},{"text":"r","confidence":0.9913133},{"text":"k","confidence":0.9933154},{"text":"l","confidence":0.988538},{"text":"ä","confidence":0.98248696},{"text":"r","confidence":0.98942995},{"text":"e","confidence":0.98856336},{"text":"n","confidence":0.99306697}],"confidence":0.9900492},{"property":{"detectedLanguages":[{"languageCode":"de","confidence":1}]},"boundingBox":{"normalizedVertices":[{"x":0.9588235,"y":0.47142857},{"x":0.9705882,"y":0.47142857},{"x":0.9705882,"y":0.49285713},{"x":0.9588235,"y":0.49285713}]},"symbols":[{"property":{"detectedBreak":{"type":"EOL_SURE_SPACE"}},"text":",","confidence":0.97179294}],"confidence":0.97179294},{"property":{"detectedLanguages":[{"languageCode":"de","confidence":1}]},"boundingBox":{"normalizedVertices":[{"x":0.08235294,"y":0.5},{"x":0.37058824,"y":0.50238097},{"x":0.37058824,"y":0.51666665},{"x":0.08235294,"y":0.51666665}]},"symbols":[{"text":"a","confidence":0.9926835},{"text":"n","confidence":0.9955707},{"text":"n","confidence":0.9962431},{"text":"u","confidence":0.98017997},{"text":"l","confidence":0.9717785},{"text":"l","confidence":0.96296895},{"text":"i","confidence":0.98970485},{"text":"e","confidence":0.9931791},{"text":"r","confidence":0.99240965},{"text":"e","confidence":0.9948204},{"property":{"detectedBreak":{"type":"LINE_BREAK"}},"text":"n","confidence":0.9905182}],"confidence":0.9872779}],"confidence":0.9205337}],"blockType":"TEXT","confidence":0.91366184},{"boundingBox":{"normalizedVertices":[{"x":0.03529412,"y":0.5285714},{"x":0.59411764,"y":0.52619046},{"x":0.59411764,"y":0.5809524},{"x":0.03529412,"y":0.5809524}]},"paragraphs":[{"boundingBox":{"normalizedVertices":[{"x":0.03529412,"y":0.5285714},{"x":0.5117647,"y":0.5285714},{"x":0.5117647,"y":0.552381},{"x":0.03529412,"y":0.552381}]},"words":[{"property":{"detectedLanguages":[{"languageCode":"ka","confidence":1}]},"boundingBox":{"normalizedVertices":[{"x":0.03529412,"y":0.5285714},{"x":0.22352941,"y":0.5285714},{"x":0.22352941,"y":0.552381},{"x":0.03529412,"y":0.552381}]},"symbols":[{"text":"ბ","confidence":0.9987879},{"text":"ა","confidence":0.99869996},{"text":"თ","confidence":0.9989986},{"text":"ქ","confidence":0.9993547},{"text":"ა","confidence":0.9935059},{"property":{"detectedBreak":{"type":"SPACE"}},"text":"შ","confidence":0.979041}],"confidence":0.9947313},{"property":{"detectedLanguages":[{"languageCode":"ka","confidence":1}]},"boundingBox":{"normalizedVertices":[{"x":0.2529412,"y":0.5285714},{"x":0.5117647,"y":0.5285714},{"x":0.5117647,"y":0.552381},{"x":0.2529412,"y":0.552381}]},"symbols":[{"text":"s","confidence":0.99678916},{"text":"t","confidence":0.9987357},{"text":"u","confidence":0.9998757},{"text":"c","confidence":0.999965},{"text":"k","confidence":0.9999583},{"text":"i","confidence":0.9990737},{"text":"e","confidence":0.9988919},{"text":"r","confidence":0.9982506},{"text":"e","confidence":0.9949901},{"property":{"detectedBreak":{"type":"LINE_BREAK"}},"text":"n","confidence":0.9386114}],"confidence":0.99251413}],"confidence":0.9933456},{"boundingBox":{"normalizedVertices":[{"x":0.03529412,"y":0.55714285},{"x":0.59411764,"y":0.5547619},{"x":0.59411764,"y":0.57857144},{"x":0.03529412,"y":0.5809524}]},"words":[{"property":{"detectedLanguages":[{"languageCode":"de","confidence":1}]},"boundingBox":{"normalizedVertices":[{"x":0.03529412,"y":0.55714285},{"x":0.22941177,"y":0.55714285},{"x":0.22941177,"y":0.5809524},{"x":0.03529412,"y":0.5809524}]},"symbols":[{"text":"ბ","confidence":0.99937415},{"text":"ა","confidence":0.9996263},{"text":"ი","confidence":0.99975497},{"text":"ყ","confidence":0.9995033},{"text":"უ","confidence":0.9988976},{"property":{"detectedBreak":{"type":"SPACE"}},"text":"შ","confidence":0.99019194}],"confidence":0.99789137},{"property":{"detectedLanguages":[{"languageCode":"de","confidence":1}]},"boundingBox":{"normalizedVertices":[{"x":0.2529412,"y":0.55714285},{"x":0.46470588,"y":0.5547619},{"x":0.46470588,"y":0.57857144},{"x":0.2529412,"y":0.5809524}]},"symbols":[{"text":"m","confidence":0.9978457},{"text":"ü","confidence":0.99768126},{"text":"r","confidence":0.99964523},{"text":"r","confidence":0.99885666},{"text":"i","confidence":0.9997337},{"text":"s","confidence":0.99987185},{"text":"c","confidence":0.99998367},{"property":{"detectedBreak":{"type":"SPACE"}},"text":"h","confidence":0.9996711}],"confidence":0.9991611},{"property":{"detectedLanguages":[{"languageCode":"de","confidence":1}]},"boundingBox":{"normalizedVertices":[{"x":0.4882353,"y":0.5547619},{"x":0.59411764,"y":0.5547619},{"x":0.59411764,"y":0.57857144},{"x":0.4882353,"y":0.57857144}]},"symbols":[{"text":"s","confidence":0.98834556},{"text":"e","confidence":0.99348927},{"text":"i","confidence":0.99888515},{"property":{"detectedBreak":{"type":"LINE_BREAK"}},"text":"n","confidence":0.9659264}],"confidence":0.9866616}],"confidence":0.99596024}],"blockType":"TEXT","confidence":0.9947298},{"boundingBox":{"normalizedVertices":[{"x":0.03529412,"y":0.5857143},{"x":0.69411767,"y":0.5857143},{"x":0.69411767,"y":0.6666667},{"x":0.03529412,"y":0.6666667}]},"paragraphs":[{"boundingBox":{"normalizedVertices":[{"x":0.03529412,"y":0.5857143},{"x":0.69411767,"y":0.5857143},{"x":0.69411767,"y":0.6666667},{"x":0.03529412,"y":0.6666667}]},"words":[{"property":{"detectedLanguages":[{"languageCode":"de","confidence":1}]},"boundingBox":{"normalizedVertices":[{"x":0.03529412,"y":0.5857143},{"x":0.1882353,"y":0.58809525},{"x":0.1882353,"y":0.60952383},{"x":0.03529412,"y":0.60952383}]},"symbols":[{"text":"ბ","confidence":0.9988388},{"text":"ა","confidence":0.99994487},{"text":"კ","confidence":0.9999771},{"text":"უ","confidence":0.9997155},{"property":{"detectedBreak":{"type":"SPACE"}},"text":"ნ","confidence":0.98230934}],"confidence":0.9961571},{"property":{"detectedLanguages":[{"languageCode":"de","confidence":1}]},"boundingBox":{"normalizedVertices":[{"x":0.21176471,"y":0.58809525},{"x":0.42352942,"y":0.58809525},{"x":0.42352942,"y":0.60952383},{"x":0.21176471,"y":0.60952383}]},"symbols":[{"text":"t","confidence":0.9969897},{"text":"r","confidence":0.9996383},{"text":"a","confidence":0.99991274},{"text":"m","confidence":0.9998091},{"text":"p","confidence":0.99953765},{"text":"e","confidence":0.9944194},{"text":"l","confidence":0.97228885},{"text":"n","confidence":0.99323106}],"confidence":0.99447834},{"property":{"detectedLanguages":[{"languageCode":"de","confidence":1}]},"boundingBox":{"normalizedVertices":[{"x":0.42941177,"y":0.58809525},{"x":0.44117647,"y":0.58809525},{"x":0.44117647,"y":0.60952383},{"x":0.42941177,"y":0.60952383}]},"symbols":[{"property":{"detectedBreak":{"type":"SPACE"}},"text":",","confidence":0.99596786}],"confidence":0.99596786},{"property":{"detectedLanguages":[{"languageCode":"de","confidence":1}]},"boundingBox":{"normalizedVertices":[{"x":0.47058824,"y":0.58809525},{"x":0.69411767,"y":0.58809525},{"x":0.6882353,"y":0.61190474},{"x":0.47058824,"y":0.60952383}]},"symbols":[{"text":"s","confidence":0.9995968},{"text":"t","confidence":0.99987376},{"text":"a","confidence":0.9997337},{"text":"m","confidence":0.99965936},{"text":"p","confidence":0.9998234},{"text":"f","confidence":0.9999177},{"text":"e","confidence":0.99983597},{"property":{"detectedBreak":{"type":"EOL_SURE_SPACE"}},"text":"n","confidence":0.9929039}],"confidence":0.99891806},{"property":{"detectedLanguages":[{"languageCode":"ka","confidence":1}]},"boundingBox":{"normalizedVertices":[{"x":0.03529412,"y":0.6142857},{"x":0.21764706,"y":0.6142857},{"x":0.21764706,"y":0.63809526},{"x":0.03529412,"y":0.63809526}]},"symbols":[{"text":"ბ","confidence":0.99087197},{"text":"ა","confidence":0.9986152},{"text":"ლ","confidence":0.99858785},{"text":"ა","confidence":0.9986773},{"text":"ნ","confidence":0.98812056},{"property":{"detectedBreak":{"type":"SPACE"}},"text":"ს","confidence":0.9847654}],"confidence":0.993273},{"property":{"detectedLanguages":[{"languageCode":"ka","confidence":1}]},"boundingBox":{"normalizedVertices":[{"x":0.24117647,"y":0.6142857},{"x":0.5176471,"y":0.6142857},{"x":0.5176471,"y":0.63809526},{"x":0.24117647,"y":0.63809526}]},"symbols":[{"text":"b","confidence":0.9958039},{"text":"i","confidence":0.9959259},{"text":"l","confidence":0.9993621},{"text":"a","confidence":0.99818194},{"text":"n","confidence":0.9996975},{"text":"z","confidence":0.99977684},{"text":"i","confidence":0.9999441},{"text":"e","confidence":0.9997997},{"text":"r","confidence":0.9997417},{"text":"e","confidence":0.9966335},{"property":{"detectedBreak":{"type":"EOL_SURE_SPACE"}},"text":"n","confidence":0.98429686}],"confidence":0.99719673},{"property":{"detectedLanguages":[{"languageCode":"ka","confidence":1}]},"boundingBox":{"normalizedVertices":[{"x":0.03529412,"y":0.6452381},{"x":0.1882353,"y":0.6452381},{"x":0.1882353,"y":0.6666667},{"x":0.03529412,"y":0.6666667}]},"symbols":[{"text":"ბ","confidence":0.9895124},{"text":"ა","confidence":0.9969782},{"text":"ლ","confidence":0.99613106},{"text":"ა","confidence":0.9924992},{"property":{"detectedBreak":{"type":"SPACE"}},"text":"ხ","confidence":0.9499101}],"confidence":0.9850062},{"property":{"detectedLanguages":[{"languageCode":"ka","confidence":1}]},"boundingBox":{"normalizedVertices":[{"x":0.21176471,"y":0.6452381},{"x":0.38235295,"y":0.6452381},{"x":0.38235295,"y":0.6666667},{"x":0.21176471,"y":0.6666667}]},"symbols":[{"text":"w","confidence":0.99605715},{"text":"e","confidence":0.99567896},{"text":"i","confidence":0.99963653},{"text":"d","confidence":0.9996492},{"text":"e","confidence":0.99967813},{"property":{"detectedBreak":{"type":"LINE_BREAK"}},"text":"n","confidence":0.9885041}],"confidence":0.996534}],"confidence":0.99513924}],"blockType":"TEXT","confidence":0.99513924},{"boundingBox":{"normalizedVertices":[{"x":0.029411765,"y":0.67142856},{"x":0.9647059,"y":0.67142856},{"x":0.9647059,"y":0.98333335},{"x":0.029411765,"y":0.98333335}]},"paragraphs":[{"boundingBox":{"normalizedVertices":[{"x":0.03529412,"y":0.67142856},{"x":0.5411765,"y":0.6738095},{"x":0.5411765,"y":0.697619},{"x":0.03529412,"y":0.6952381}]},"words":[{"property":{"detectedLanguages":[{"languageCode":"ka","confidence":1}]},"boundingBox":{"normalizedVertices":[{"x":0.03529412,"y":0.67142856},{"x":0.29411766,"y":0.6738095},{"x":0.29411766,"y":0.6952381},{"x":0.03529412,"y":0.6952381}]},"symbols":[{"text":"ბ","confidence":0.9975325},{"text":"ა","confidence":0.99940336},{"text":"ლ","confidence":0.99954534},{"text":"ა","confidence":0.9994791},{"text":"ხ","confidence":0.9998566},{"text":"ტ","confidence":0.99997646},{"text":"ა","confidence":0.9995883},{"property":{"detectedBreak":{"type":"SPACE"}},"text":"რ","confidence":0.99480605}],"confidence":0.99877346},{"property":{"detectedLanguages":[{"languageCode":"ka","confidence":1}]},"boundingBox":{"normalizedVertices":[{"x":0.32352942,"y":0.6738095},{"x":0.5411765,"y":0.6738095},{"x":0.5411765,"y":0.697619},{"x":0.31764707,"y":0.6952381}]},"symbols":[{"text":"p","confidence":0.99274075},{"text":"f","confidence":0.9973717},{"text":"u","confidence":0.99978393},{"text":"s","confidence":0.9998479},{"text":"c","confidence":0.9998706},{"text":"h","confidence":0.99988264},{"text":"e","confidence":0.9995321},{"property":{"detectedBreak":{"type":"LINE_BREAK"}},"text":"n","confidence":0.99076897}],"confidence":0.9974748}],"confidence":0.9981241},{"boundingBox":{"normalizedVertices":[{"x":0.03529412,"y":0.70238096},{"x":0.85882354,"y":0.70238096},{"x":0.85882354,"y":0.72380954},{"x":0.03529412,"y":0.72380954}]},"words":[{"property":{"detectedLanguages":[{"languageCode":"de","confidence":1}]},"boundingBox":{"normalizedVertices":[{"x":0.03529412,"y":0.70238096},{"x":0.16470589,"y":0.70238096},{"x":0.16470589,"y":0.72380954},{"x":0.03529412,"y":0.72380954}]},"symbols":[{"text":"d","confidence":0.75898707},{"text":"u","confidence":0.4979698},{"text":"m","confidence":0.8265209},{"property":{"detectedBreak":{"type":"SPACE"}},"text":"o","confidence":0.587904}],"confidence":0.6678454},{"property":{"detectedLanguages":[{"languageCode":"de","confidence":1}]},"boundingBox":{"normalizedVertices":[{"x":0.19411765,"y":0.70238096},{"x":0.20588236,"y":0.70238096},{"x":0.20588236,"y":0.72380954},{"x":0.19411765,"y":0.72380954}]},"symbols":[{"text":"(","confidence":0.9841383}],"confidence":0.9841383},{"property":{"detectedLanguages":[{"languageCode":"de","confidence":1}]},"boundingBox":{"normalizedVertices":[{"x":0.21176471,"y":0.70238096},{"x":0.32352942,"y":0.70238096},{"x":0.32352942,"y":0.72380954},{"x":0.21176471,"y":0.72380954}]},"symbols":[{"text":"k","confidence":0.995908},{"text":"a","confidence":0.9952164},{"text":"c","confidence":0.992744},{"text":"h","confidence":0.99321145}],"confidence":0.99426997},{"property":{"detectedLanguages":[{"languageCode":"de","confidence":1}]},"boundingBox":{"normalizedVertices":[{"x":0.32941177,"y":0.70238096},{"x":0.34117648,"y":0.70238096},{"x":0.34117648,"y":0.72380954},{"x":0.32941177,"y":0.72380954}]},"symbols":[{"text":".","confidence":0.97535217}],"confidence":0.97535217},{"property":{"detectedLanguages":[{"languageCode":"de","confidence":1}]},"boundingBox":{"normalizedVertices":[{"x":0.3529412,"y":0.70238096},{"x":0.35882354,"y":0.70238096},{"x":0.35882354,"y":0.72380954},{"x":0.3529412,"y":0.72380954}]},"symbols":[{"property":{"detectedBreak":{"type":"SPACE"}},"text":",","confidence":0.9653383}],"confidence":0.9653383},{"property":{"detectedLanguages":[{"languageCode":"de","confidence":1}]},"boundingBox":{"normalizedVertices":[{"x":0.3882353,"y":0.70238096},{"x":0.5058824,"y":0.70238096},{"x":0.5058824,"y":0.72380954},{"x":0.3882353,"y":0.72380954}]},"symbols":[{"text":"p","confidence":0.9941836},{"text":"s","confidence":0.9965765},{"text":"c","confidence":0.99635494},{"text":"h","confidence":0.99738276}],"confidence":0.99612445},{"property":{"detectedLanguages":[{"languageCode":"de","confidence":1}]},"boundingBox":{"normalizedVertices":[{"x":0.5117647,"y":0.70238096},{"x":0.5176471,"y":0.70238096},{"x":0.5176471,"y":0.72380954},{"x":0.5117647,"y":0.72380954}]},"symbols":[{"text":".","confidence":0.9920911}],"confidence":0.9920911},{"property":{"detectedLanguages":[{"languageCode":"de","confidence":1}]},"boundingBox":{"normalizedVertices":[{"x":0.5294118,"y":0.70238096},{"x":0.5411765,"y":0.70238096},{"x":0.5411765,"y":0.72380954},{"x":0.5294118,"y":0.72380954}]},"symbols":[{"property":{"detectedBreak":{"type":"SPACE"}},"text":")","confidence":0.99782693}],"confidence":0.99782693},{"property":{"detectedLanguages":[{"languageCode":"de","confidence":1}]},"boundingBox":{"normalizedVertices":[{"x":0.57058823,"y":0.70238096},{"x":0.85882354,"y":0.70238096},{"x":0.85882354,"y":0.72380954},{"x":0.57058823,"y":0.72380954}]},"symbols":[{"text":"z","confidence":0.9988441},{"text":"e","confidence":0.9987846},{"text":"r","confidence":0.9988908},{"text":"s","confidence":0.99848133},{"text":"t","confidence":0.99761117},{"text":"ü","confidence":0.99648213},{"text":"c","confidence":0.999522},{"text":"k","confidence":0.9972172},{"text":"e","confidence":0.99860185},{"text":"l","confidence":0.98065317},{"property":{"detectedBreak":{"type":"LINE_BREAK"}},"text":"n","confidence":0.98675716}],"confidence":0.99562234}],"confidence":0.94641256},{"boundingBox":{"normalizedVertices":[{"x":0.03529412,"y":0.7309524},{"x":0.5294118,"y":0.7285714},{"x":0.5294118,"y":0.75238097},{"x":0.03529412,"y":0.75476193}]},"words":[{"property":{"detectedLanguages":[{"languageCode":"de","confidence":1}]},"boundingBox":{"normalizedVertices":[{"x":0.03529412,"y":0.7309524},{"x":0.16470589,"y":0.7309524},{"x":0.16470589,"y":0.75238097},{"x":0.03529412,"y":0.75476193}]},"symbols":[{"text":"ბ","confidence":0.9990633},{"text":"ა","confidence":0.9997176},{"text":"ლ","confidence":0.99406415},{"property":{"detectedBreak":{"type":"SPACE"}},"text":"ღ","confidence":0.96411705}],"confidence":0.9892405},{"property":{"detectedLanguages":[{"languageCode":"de","confidence":1}]},"boundingBox":{"normalizedVertices":[{"x":0.19411765,"y":0.7309524},{"x":0.4,"y":0.7285714},{"x":0.4,"y":0.75238097},{"x":0.19411765,"y":0.75238097}]},"symbols":[{"text":"k","confidence":0.9987946},{"text":"i","confidence":0.99526894},{"text":"n","confidence":0.9984167},{"text":"d","confidence":0.9969352},{"text":"i","confidence":0.998167},{"text":"s","confidence":0.9997351},{"text":"c","confidence":0.99952084},{"property":{"detectedBreak":{"type":"SPACE"}},"text":"h","confidence":0.9987506}],"confidence":0.9981986},{"property":{"detectedLanguages":[{"languageCode":"de","confidence":1}]},"boundingBox":{"normalizedVertices":[{"x":0.42941177,"y":0.7285714},{"x":0.5294118,"y":0.7285714},{"x":0.5294118,"y":0.75238097},{"x":0.42941177,"y":0.75238097}]},"symbols":[{"text":"s","confidence":0.98788255},{"text":"e","confidence":0.9938822},{"text":"i","confidence":0.99921083},{"property":{"detectedBreak":{"type":"LINE_BREAK"}},"text":"n","confidence":0.9848994}],"confidence":0.9914687}],"confidence":0.99427664},{"boundingBox":{"normalizedVertices":[{"x":0.03529412,"y":0.7595238},{"x":0.9647059,"y":0.7595238},{"x":0.9647059,"y":0.78333336},{"x":0.03529412,"y":0.78333336}]},"words":[{"property":{"detectedLanguages":[{"languageCode":"ka","confidence":1}]},"boundingBox":{"normalizedVertices":[{"x":0.03529412,"y":0.7595238},{"x":0.22941177,"y":0.7595238},{"x":0.22941177,"y":0.78333336},{"x":0.03529412,"y":0.78333336}]},"symbols":[{"text":"ბ","confidence":0.98998976},{"text":"ა","confidence":0.99847347},{"text":"ლ","confidence":0.993574},{"text":"ღ","confidence":0.99838114},{"text":"ა","confidence":0.9591071},{"property":{"detectedBreak":{"type":"SPACE"}},"text":"მ","confidence":0.97387326}],"confidence":0.98556644},{"property":{"detectedLanguages":[{"languageCode":"ka","confidence":1}]},"boundingBox":{"normalizedVertices":[{"x":0.3,"y":0.7595238},{"x":0.33529413,"y":0.7595238},{"x":0.33529413,"y":0.78333336},{"x":0.3,"y":0.78333336}]},"symbols":[{"text":"1","confidence":0.5630074},{"property":{"detectedBreak":{"type":"SPACE"}},"text":".","confidence":0.46892026}],"confidence":0.51596385},{"property":{"detectedLanguages":[{"languageCode":"ka","confidence":1}]},"boundingBox":{"normalizedVertices":[{"x":0.38235295,"y":0.7595238},{"x":0.4117647,"y":0.7595238},{"x":0.4117647,"y":0.78333336},{"x":0.38235295,"y":0.78333336}]},"symbols":[{"text":"(","confidence":0.9540587}],"confidence":0.9540587},{"property":{"detectedLanguages":[{"languageCode":"ka","confidence":1}]},"boundingBox":{"normalizedVertices":[{"x":0.41764706,"y":0.7595238},{"x":0.5235294,"y":0.7595238},{"x":0.5235294,"y":0.78333336},{"x":0.41764706,"y":0.78333336}]},"symbols":[{"text":"i","confidence":0.99137247},{"text":"m","confidence":0.9993897},{"text":"e","confidence":0.995224},{"text":"r","confidence":0.92898405}],"confidence":0.97874254},{"property":{"detectedLanguages":[{"languageCode":"ka","confidence":1}]},"boundingBox":{"normalizedVertices":[{"x":0.5294118,"y":0.7595238},{"x":0.5411765,"y":0.7595238},{"x":0.5411765,"y":0.78333336},{"x":0.5294118,"y":0.78333336}]},"symbols":[{"text":".","confidence":0.5032713}],"confidence":0.5032713},{"property":{"detectedLanguages":[{"languageCode":"ka","confidence":1}]},"boundingBox":{"normalizedVertices":[{"x":0.5470588,"y":0.7595238},{"x":0.5647059,"y":0.7595238},{"x":0.5647059,"y":0.78333336},{"x":0.5470588,"y":0.78333336}]},"symbols":[{"property":{"detectedBreak":{"type":"SPACE"}},"text":")","confidence":0.6887723}],"confidence":0.6887723},{"property":{"detectedLanguages":[{"languageCode":"ka","confidence":1}]},"boundingBox":{"normalizedVertices":[{"x":0.61764705,"y":0.7595238},{"x":0.7588235,"y":0.7595238},{"x":0.7588235,"y":0.78333336},{"x":0.61764705,"y":0.78333336}]},"symbols":[{"text":"e","confidence":0.93915033},{"text":"i","confidence":0.9958376},{"text":"t","confidence":0.9990268},{"text":"e","confidence":0.99785876},{"text":"r","confidence":0.99387074},{"property":{"detectedBreak":{"type":"SPACE"}},"text":"n","confidence":0.9322005}],"confidence":0.97632414},{"property":{"detectedLanguages":[{"languageCode":"ka","confidence":1}]},"boundingBox":{"normalizedVertices":[{"x":0.8117647,"y":0.7595238},{"x":0.9647059,"y":0.7595238},{"x":0.9647059,"y":0.78333336},{"x":0.8117647,"y":0.78333336}]},"symbols":[{"text":"l","confidence":0.95987964},{"text":"a","confidence":0.9912918},{"text":"s","confidence":0.9994098},{"text":"s","confidence":0.9992603},{"text":"e","confidence":0.9988425},{"property":{"detectedBreak":{"type":"LINE_BREAK"}},"text":"n","confidence":0.9908962}],"confidence":0.98993003}],"confidence":0.91866386},{"boundingBox":{"normalizedVertices":[{"x":0.0882353,"y":0.7904762},{"x":0.59411764,"y":0.7904762},{"x":0.59411764,"y":0.80714285},{"x":0.0882353,"y":0.80714285}]},"words":[{"property":{"detectedLanguages":[{"languageCode":"lb","confidence":1}]},"boundingBox":{"normalizedVertices":[{"x":0.0882353,"y":0.7904762},{"x":0.12941177,"y":0.7904762},{"x":0.12941177,"y":0.80714285},{"x":0.0882353,"y":0.80714285}]},"symbols":[{"text":"2","confidence":0.97426224},{"property":{"detectedBreak":{"type":"SPACE"}},"text":".","confidence":0.97886527}],"confidence":0.97656375},{"property":{"detectedLanguages":[{"languageCode":"lb","confidence":1}]},"boundingBox":{"normalizedVertices":[{"x":0.15294118,"y":0.7904762},{"x":0.17058824,"y":0.7904762},{"x":0.17058824,"y":0.80714285},{"x":0.15294118,"y":0.80714285}]},"symbols":[{"text":"(","confidence":0.97629887}],"confidence":0.97629887},{"property":{"detectedLanguages":[{"languageCode":"lb","confidence":1}]},"boundingBox":{"normalizedVertices":[{"x":0.17058824,"y":0.7904762},{"x":0.2882353,"y":0.7904762},{"x":0.2882353,"y":0.80714285},{"x":0.17058824,"y":0.80714285}]},"symbols":[{"text":"k","confidence":0.9787947},{"text":"a","confidence":0.9935386},{"text":"c","confidence":0.9911689},{"text":"h","confidence":0.9879468}],"confidence":0.9878622},{"property":{"detectedLanguages":[{"languageCode":"lb","confidence":1}]},"boundingBox":{"normalizedVertices":[{"x":0.29411766,"y":0.7904762},{"x":0.30588236,"y":0.7904762},{"x":0.30588236,"y":0.80714285},{"x":0.29411766,"y":0.80714285}]},"symbols":[{"text":".","confidence":0.9600068}],"confidence":0.9600068},{"property":{"detectedLanguages":[{"languageCode":"lb","confidence":1}]},"boundingBox":{"normalizedVertices":[{"x":0.31176472,"y":0.7904762},{"x":0.32941177,"y":0.7904762},{"x":0.32941177,"y":0.80714285},{"x":0.31176472,"y":0.80714285}]},"symbols":[{"property":{"detectedBreak":{"type":"SPACE"}},"text":")","confidence":0.965379}],"confidence":0.965379},{"property":{"detectedLanguages":[{"languageCode":"lb","confidence":1}]},"boundingBox":{"normalizedVertices":[{"x":0.3529412,"y":0.7904762},{"x":0.59411764,"y":0.7904762},{"x":0.59411764,"y":0.80714285},{"x":0.3529412,"y":0.80714285}]},"symbols":[{"text":"v","confidence":0.99253225},{"text":"e","confidence":0.99331415},{"text":"r","confidence":0.9920005},{"text":"b","confidence":0.9928679},{"text":"i","confidence":0.9947172},{"text":"t","confidence":0.9920491},{"text":"t","confidence":0.9918094},{"text":"e","confidence":0.9951841},{"text":"r","confidence":0.99617577},{"property":{"detectedBreak":{"type":"LINE_BREAK"}},"text":"n","confidence":0.9939878}],"confidence":0.9934638}],"confidence":0.9863631},{"boundingBox":{"normalizedVertices":[{"x":0.03529412,"y":0.8142857},{"x":0.7470588,"y":0.81666666},{"x":0.7411765,"y":0.9},{"x":0.03529412,"y":0.89761907}]},"words":[{"property":{"detectedLanguages":[{"languageCode":"af","confidence":1}]},"boundingBox":{"normalizedVertices":[{"x":0.03529412,"y":0.8142857},{"x":0.14705883,"y":0.8142857},{"x":0.14117648,"y":0.8357143},{"x":0.03529412,"y":0.8357143}]},"symbols":[{"text":"d","confidence":0.30760545},{"text":"s","confidence":0.2805663},{"text":"a","confidence":0.34222558},{"property":{"detectedBreak":{"type":"SPACE"}},"text":"d","confidence":0.27979085}],"confidence":0.30254704},{"property":{"detectedLanguages":[{"languageCode":"af","confidence":1}]},"boundingBox":{"normalizedVertices":[{"x":0.17058824,"y":0.8142857},{"x":0.40588236,"y":0.81666666},{"x":0.40588236,"y":0.83809525},{"x":0.17058824,"y":0.8357143}]},"symbols":[{"text":"w","confidence":0.9731426},{"text":"a","confidence":0.9939864},{"text":"t","confidence":0.99140716},{"text":"t","confidence":0.9918391},{"text":"i","confidence":0.9928339},{"text":"e","confidence":0.9942345},{"text":"r","confidence":0.9949974},{"text":"e","confidence":0.9920459},{"text":"n","confidence":0.99117166}],"confidence":0.9906287},{"property":{"detectedLanguages":[{"languageCode":"af","confidence":1}]},"boundingBox":{"normalizedVertices":[{"x":0.4117647,"y":0.81666666},{"x":0.42352942,"y":0.81666666},{"x":0.42352942,"y":0.83809525},{"x":0.4117647,"y":0.83809525}]},"symbols":[{"property":{"detectedBreak":{"type":"SPACE"}},"text":",","confidence":0.98795646}],"confidence":0.98795646},{"property":{"detectedLanguages":[{"languageCode":"af","confidence":1}]},"boundingBox":{"normalizedVertices":[{"x":0.44705883,"y":0.81666666},{"x":0.7470588,"y":0.81904763},{"x":0.7411765,"y":0.8404762},{"x":0.44705883,"y":0.83809525}]},"symbols":[{"text":"a","confidence":0.9954943},{"text":"u","confidence":0.99178356},{"text":"s","confidence":0.99024063},{"text":"p","confidence":0.9887433},{"text":"o","confidence":0.9918102},{"text":"l","confidence":0.9902987},{"text":"s","confidence":0.9864462},{"text":"t","confidence":0.9916099},{"text":"e","confidence":0.995048},{"text":"r","confidence":0.99566835},{"property":{"detectedBreak":{"type":"EOL_SURE_SPACE"}},"text":"n","confidence":0.9926696}],"confidence":0.99180114},{"property":{"detectedLanguages":[{"languageCode":"de","confidence":1}]},"boundingBox":{"normalizedVertices":[{"x":0.064705886,"y":0.8452381},{"x":0.12941177,"y":0.8452381},{"x":0.12941177,"y":0.8666667},{"x":0.064705886,"y":0.8666667}]},"symbols":[{"text":"s","confidence":0.4674488},{"property":{"detectedBreak":{"type":"SPACE"}},"text":"б","confidence":0.29574102}],"confidence":0.3815949},{"property":{"detectedLanguages":[{"languageCode":"de","confidence":1}]},"boundingBox":{"normalizedVertices":[{"x":0.14117648,"y":0.8452381},{"x":0.35882354,"y":0.8452381},{"x":0.35882354,"y":0.8666667},{"x":0.14117648,"y":0.8666667}]},"symbols":[{"text":"w","confidence":0.9908004},{"text":"a","confidence":0.99374855},{"text":"s","confidence":0.9946991},{"text":"c","confidence":0.9912519},{"text":"h","confidence":0.99496996},{"text":"e","confidence":0.9903111},{"text":"n","confidence":0.9931139}],"confidence":0.99269927},{"property":{"detectedLanguages":[{"languageCode":"de","confidence":1}]},"boundingBox":{"normalizedVertices":[{"x":0.3647059,"y":0.8452381},{"x":0.37058824,"y":0.8452381},{"x":0.37058824,"y":0.8666667},{"x":0.3647059,"y":0.8666667}]},"symbols":[{"property":{"detectedBreak":{"type":"SPACE"}},"text":",","confidence":0.98791015}],"confidence":0.98791015},{"property":{"detectedLanguages":[{"languageCode":"de","confidence":1}]},"boundingBox":{"normalizedVertices":[{"x":0.4,"y":0.8452381},{"x":0.5470588,"y":0.8452381},{"x":0.5470588,"y":0.8666667},{"x":0.4,"y":0.8666667}]},"symbols":[{"text":"b","confidence":0.9948271},{"text":"a","confidence":0.9963958},{"text":"d","confidence":0.9968529},{"text":"e","confidence":0.9965813},{"property":{"detectedBreak":{"type":"EOL_SURE_SPACE"}},"text":"n","confidence":0.99275285}],"confidence":0.99548197},{"property":{"detectedLanguages":[{"languageCode":"ka","confidence":1}]},"boundingBox":{"normalizedVertices":[{"x":0.03529412,"y":0.8738095},{"x":0.14705883,"y":0.87142855},{"x":0.14705883,"y":0.89761907},{"x":0.03529412,"y":0.89761907}]},"symbols":[{"text":"ბ","confidence":0.9967623},{"text":"ა","confidence":0.9987869},{"text":"ნ","confidence":0.99745923},{"text":"ა","confidence":0.99905103}],"confidence":0.99801487},{"property":{"detectedLanguages":[{"languageCode":"ka","confidence":1}]},"boundingBox":{"normalizedVertices":[{"x":0.15294118,"y":0.8738095},{"x":0.16470589,"y":0.8738095},{"x":0.16470589,"y":0.89761907},{"x":0.15294118,"y":0.89761907}]},"symbols":[{"text":"(","confidence":0.9990541}],"confidence":0.9990541},{"property":{"detectedLanguages":[{"languageCode":"ka","confidence":1}]},"boundingBox":{"normalizedVertices":[{"x":0.17058824,"y":0.8738095},{"x":0.19411765,"y":0.8738095},{"x":0.19411765,"y":0.89761907},{"x":0.17058824,"y":0.89761907}]},"symbols":[{"text":"ვ","confidence":0.9980728}],"confidence":0.9980728},{"property":{"detectedLanguages":[{"languageCode":"ka","confidence":1}]},"boundingBox":{"normalizedVertices":[{"x":0.20588236,"y":0.87142855},{"x":0.21764706,"y":0.87142855},{"x":0.21764706,"y":0.89761907},{"x":0.20588236,"y":0.89761907}]},"symbols":[{"property":{"detectedBreak":{"type":"SPACE"}},"text":")","confidence":0.991812}],"confidence":0.991812},{"property":{"detectedLanguages":[{"languageCode":"ka","confidence":1}]},"boundingBox":{"normalizedVertices":[{"x":0.24117647,"y":0.87142855},{"x":0.38235295,"y":0.87142855},{"x":0.38235295,"y":0.89761907},{"x":0.24117647,"y":0.89761907}]},"symbols":[{"text":"b","confidence":0.99543196},{"text":"a","confidence":0.9986733},{"text":"d","confidence":0.9995977},{"text":"e","confidence":0.9988351},{"property":{"detectedBreak":{"type":"LINE_BREAK"}},"text":"n","confidence":0.9795276}],"confidence":0.99441314}],"confidence":0.9164247},{"boundingBox":{"normalizedVertices":[{"x":0.029411765,"y":0.90238094},{"x":0.7529412,"y":0.9047619},{"x":0.7529412,"y":0.98333335},{"x":0.029411765,"y":0.98333335}]},"words":[{"property":{"detectedLanguages":[{"languageCode":"de","confidence":1}]},"boundingBox":{"normalizedVertices":[{"x":0.029411765,"y":0.90238094},{"x":0.15294118,"y":0.90238094},{"x":0.15294118,"y":0.9238095},{"x":0.029411765,"y":0.9238095}]},"symbols":[{"text":"3","confidence":0.24908793},{"text":"3","confidence":0.1785983},{"text":"б","confidence":0.19619139},{"property":{"detectedBreak":{"type":"SPACE"}},"text":"s","confidence":0.2800022}],"confidence":0.22596996},{"property":{"detectedLanguages":[{"languageCode":"de","confidence":1}]},"boundingBox":{"normalizedVertices":[{"x":0.2,"y":0.9047619},{"x":0.35882354,"y":0.9047619},{"x":0.35882354,"y":0.9238095},{"x":0.2,"y":0.9238095}]},"symbols":[{"text":"l","confidence":0.97824866},{"text":"a","confidence":0.99390244},{"text":"g","confidence":0.9955355},{"text":"e","confidence":0.99561894},{"text":"r","confidence":0.9927757},{"text":"n","confidence":0.97643805}],"confidence":0.9887532},{"property":{"detectedLanguages":[{"languageCode":"de","confidence":1}]},"boundingBox":{"normalizedVertices":[{"x":0.35882354,"y":0.9047619},{"x":0.3764706,"y":0.9047619},{"x":0.3764706,"y":0.9238095},{"x":0.35882354,"y":0.9238095}]},"symbols":[{"property":{"detectedBreak":{"type":"SPACE"}},"text":",","confidence":0.97253793}],"confidence":0.97253793},{"property":{"detectedLanguages":[{"languageCode":"de","confidence":1}]},"boundingBox":{"normalizedVertices":[{"x":0.4,"y":0.9047619},{"x":0.65294117,"y":0.9047619},{"x":0.65294117,"y":0.9261905},{"x":0.4,"y":0.9238095}]},"symbols":[{"text":"k","confidence":0.9853626},{"text":"a","confidence":0.99323285},{"text":"m","confidence":0.9917347},{"text":"p","confidence":0.99004406},{"text":"i","confidence":0.9871703},{"text":"e","confidence":0.9933572},{"text":"r","confidence":0.9905576},{"text":"e","confidence":0.9946464},{"property":{"detectedBreak":{"type":"EOL_SURE_SPACE"}},"text":"n","confidence":0.990838}],"confidence":0.99077153},{"property":{"detectedLanguages":[{"languageCode":"de","confidence":1}]},"boundingBox":{"normalizedVertices":[{"x":0.064705886,"y":0.93333334},{"x":0.14705883,"y":0.93333334},{"x":0.14705883,"y":0.95238096},{"x":0.064705886,"y":0.95238096}]},"symbols":[{"text":"s","confidence":0.24567875},{"text":"б","confidence":0.25348124},{"property":{"detectedBreak":{"type":"SPACE"}},"text":"3","confidence":0.27617213}],"confidence":0.25844404},{"property":{"detectedLanguages":[{"languageCode":"de","confidence":1}]},"boundingBox":{"normalizedVertices":[{"x":0.1764706,"y":0.93333334},{"x":0.4,"y":0.93333334},{"x":0.4,"y":0.95238096},{"x":0.1764706,"y":0.95238096}]},"symbols":[{"text":"b","confidence":0.98951024},{"text":"e","confidence":0.99240816},{"text":"t","confidence":0.9897147},{"text":"ä","confidence":0.9628357},{"text":"u","confidence":0.99397504},{"text":"b","confidence":0.9911931},{"text":"e","confidence":0.989071},{"text":"n","confidence":0.9882935}],"confidence":0.98712516},{"property":{"detectedLanguages":[{"languageCode":"de","confidence":1}]},"boundingBox":{"normalizedVertices":[{"x":0.4,"y":0.93333334},{"x":0.4117647,"y":0.93333334},{"x":0.4117647,"y":0.95238096},{"x":0.4,"y":0.95238096}]},"symbols":[{"property":{"detectedBreak":{"type":"SPACE"}},"text":",","confidence":0.98685014}],"confidence":0.98685014},{"property":{"detectedLanguages":[{"languageCode":"de","confidence":1}]},"boundingBox":{"normalizedVertices":[{"x":0.44117647,"y":0.93333334},{"x":0.7529412,"y":0.93333334},{"x":0.7529412,"y":0.95238096},{"x":0.44117647,"y":0.95238096}]},"symbols":[{"text":"e","confidence":0.9952107},{"text":"i","confidence":0.9959234},{"text":"n","confidence":0.9953019},{"text":"s","confidence":0.99003273},{"text":"c","confidence":0.97809225},{"text":"h","confidence":0.95921224},{"text":"l","confidence":0.9827741},{"text":"ä","confidence":0.9877842},{"text":"f","confidence":0.9937237},{"text":"e","confidence":0.9942408},{"text":"r","confidence":0.995646},{"property":{"detectedBreak":{"type":"EOL_SURE_SPACE"}},"text":"n","confidence":0.990952}],"confidence":0.9882412},{"property":{"detectedLanguages":[{"languageCode":"qu","confidence":1}]},"boundingBox":{"normalizedVertices":[{"x":0.03529412,"y":0.96190476},{"x":0.18235295,"y":0.96190476},{"x":0.18235295,"y":0.98333335},{"x":0.03529412,"y":0.98333335}]},"symbols":[{"text":"d","confidence":0.3243133},{"text":"ə","confidence":0.28109008},{"text":"á","confidence":0.25478965},{"text":"º","confidence":0.21694592},{"property":{"detectedBreak":{"type":"SPACE"}},"text":"¹","confidence":0.30703208}],"confidence":0.27683422},{"property":{"detectedLanguages":[{"languageCode":"qu","confidence":1}]},"boundingBox":{"normalizedVertices":[{"x":0.21176471,"y":0.96190476},{"x":0.40588236,"y":0.96190476},{"x":0.40588236,"y":0.98333335},{"x":0.21176471,"y":0.98333335}]},"symbols":[{"text":"k","confidence":0.98724145},{"text":"n","confidence":0.99136966},{"text":"ü","confidence":0.98935056},{"text":"p","confidence":0.9651471},{"text":"f","confidence":0.9920207},{"text":"e","confidence":0.98947686},{"text":"n","confidence":0.99022657}],"confidence":0.9864047},{"property":{"detectedLanguages":[{"languageCode":"qu","confidence":1}]},"boundingBox":{"normalizedVertices":[{"x":0.4117647,"y":0.96190476},{"x":0.42352942,"y":0.96190476},{"x":0.42352942,"y":0.98333335},{"x":0.4117647,"y":0.98333335}]},"symbols":[{"property":{"detectedBreak":{"type":"SPACE"}},"text":",","confidence":0.9879993}],"confidence":0.9879993},{"property":{"detectedLanguages":[{"languageCode":"qu","confidence":1}]},"boundingBox":{"normalizedVertices":[{"x":0.44705883,"y":0.96190476},{"x":0.6,"y":0.96190476},{"x":0.6,"y":0.98333335},{"x":0.44705883,"y":0.98333335}]},"symbols":[{"text":"h","confidence":0.9935998},{"text":"e","confidence":0.99385667},{"text":"f","confidence":0.9921487},{"text":"t","confidence":0.99286413},{"text":"e","confidence":0.9953674},{"property":{"detectedBreak":{"type":"LINE_BREAK"}},"text":"n","confidence":0.99207604}],"confidence":0.9933188}],"confidence":0.84890276}],"blockType":"TEXT","confidence":0.91881335},{"boundingBox":{"normalizedVertices":[{"x":0.3764706,"y":0.7690476},{"x":0.3882353,"y":0.7690476},{"x":0.3882353,"y":0.7714286},{"x":0.3764706,"y":0.7714286}]},"paragraphs":[{"boundingBox":{"normalizedVertices":[{"x":0.3764706,"y":0.7690476},{"x":0.3882353,"y":0.7690476},{"x":0.3882353,"y":0.7714286},{"x":0.3764706,"y":0.7714286}]},"words":[{"boundingBox":{"normalizedVertices":[{"x":0.3764706,"y":0.7690476},{"x":0.3882353,"y":0.7690476},{"x":0.3882353,"y":0.7714286},{"x":0.3764706,"y":0.7714286}]},"symbols":[{"property":{"detectedBreak":{"type":"LINE_BREAK"}},"text":"+","confidence":0.38273612}],"confidence":0.38273612}],"confidence":0.38273612}],"blockType":"TEXT","confidence":0.38273612}],"confidence":0.8525354}],"text":"à binden\nბაას sich unterhalten\ndsdsб zittern, beben\ndug (khar.) 1. ausputzen (Krippe)\n2. setzen (junge Weinreben)\ndsgdsg (psch.) zittern, beben\ndâmб trappeln, trampeln\nso gebären; verursachen\nasosa einkochen (Traubensaft)\nsom ebenbürtig sein; ersetzen\ndom zunehmen (v. Mond); schön w.\n(z.B. Frau)\ndsomag begleiten, geleiten\nბავშვ kindisch sein\nd5% (imer., gur.) reifen\n%% + handeln (mit Stoffen)\nasoom für ungültig/nichtig erklären,\nannullieren\nბათქაშ stuckieren\nბაიყუშ mürrisch sein\nბაკუნ trampeln, stampfen\nბალანს bilanzieren\nბალახ weiden\nბალახტარ pfuschen\ndumo (kach., psch.) zerstückeln\nბალღ kindisch sein\nბალღამ 1. (imer.) eitern lassen\n2. (kach.) verbittern\ndsad wattieren, auspolstern\nsб waschen, baden\nბანა(ვ) baden\n33бs lagern, kampieren\nsб3 betäuben, einschläfern\ndəáº¹ knüpfen, heften\n+"},"context":{"uri":"gs://ocr-test-bucket-466/merged.pdf","pageNumber":6}}]}