{"inputConfig":{"gcsSource":{"uri":"gs://ocr-test-bucket-466/merged.pdf"},"mimeType":"application/pdf"},"responses":[{"fullTextAnnotation":{"pages":[{"property":{"detectedLanguages":[{"languageCode":"de","confidence":0.70141065},{"languageCode":"ka","confidence":0.1510122},{"languageCode":"lb","confidence":0.09220559},{"languageCode":"nl","confidence":0.008459076}]},"width":169,"height":418,"blocks":[{"boundingBox":{"normalizedVertices":[{"x":0.01775148,"y":0.021531101},{"x":0.964497,"y":0.021531101},{"x":0.964497,"y":0.102870815},{"x":0.01775148,"y":0.102870815}]},"paragraphs":[{"boundingBox":{"normalizedVertices":[{"x":0.06508876,"y":0.021531101},{"x":0.964497,"y":0.02631579},{"x":0.964497,"y":0.07177033},{"x":0.06508876,"y":0.06937799}]},"words":[{"property":{"detectedLanguages":[{"languageCode":"de","confidence":1}]},"boundingBox":{"normalizedVertices":[{"x":0.06508876,"y":0.02631579},{"x":0.14201184,"y":0.02631579},{"x":0.14201184,"y":0.045454547},{"x":0.06508876,"y":0.045454547}]},"symbols":[{"text":"t","confidence":0.9888727},{"text":"e","confidence":0.98739666},{"text":"n","confidence":0.98974556}],"confidence":0.98867166},{"property":{"detectedLanguages":[{"languageCode":"de","confidence":1}]},"boundingBox":{"normalizedVertices":[{"x":0.147929,"y":0.02631579},{"x":0.15384616,"y":0.02631579},{"x":0.15384616,"y":0.045454547},{"x":0.147929,"y":0.045454547}]},"symbols":[{"property":{"detectedBreak":{"type":"SPACE"}},"text":";","confidence":0.95649755}],"confidence":0.95649755},{"property":{"detectedLanguages":[{"languageCode":"de","confidence":1}]},"boundingBox":{"normalizedVertices":[{"x":0.18934911,"y":0.02631579},{"x":0.37869823,"y":0.02631579},{"x":0.37869823,"y":0.045454547},{"x":0.18934911,"y":0.045454547}]},"symbols":[{"text":"z","confidence":0.98512214},{"text":"ä","confidence":0.9411197},{"text":"r","confidence":0.99366474},{"text":"t","confidence":0.99480295},{"text":"l","confidence":0.99560994},{"text":"i","confidence":0.9955963},{"text":"c","confidence":0.98953784},{"property":{"detectedBreak":{"type":"SPACE"}},"text":"h","confidence":0.98560894}],"confidence":0.9851328},{"property":{"detectedLanguages":[{"languageCode":"de","confidence":1}]},"boundingBox":{"normalizedVertices":[{"x":0.40236688,"y":0.02631579},{"x":0.42011833,"y":0.02631579},{"x":0.42011833,"y":0.045454547},{"x":0.40236688,"y":0.045454547}]},"symbols":[{"text":"(","confidence":0.99199206}],"confidence":0.99199206},{"property":{"detectedLanguages":[{"languageCode":"de","confidence":1}]},"boundingBox":{"normalizedVertices":[{"x":0.4260355,"y":0.02631579},{"x":0.5029586,"y":0.02631579},{"x":0.5029586,"y":0.045454547},{"x":0.4260355,"y":0.045454547}]},"symbols":[{"text":"z","confidence":0.9945342},{"text":"u","confidence":0.990722},{"text":"j","confidence":0.98488235}],"confidence":0.9900462},{"property":{"detectedLanguages":[{"languageCode":"de","confidence":1}]},"boundingBox":{"normalizedVertices":[{"x":0.5088757,"y":0.02631579},{"x":0.52662724,"y":0.02631579},{"x":0.52662724,"y":0.045454547},{"x":0.5088757,"y":0.045454547}]},"symbols":[{"text":"-","confidence":0.9536582}],"confidence":0.9536582},{"property":{"detectedLanguages":[{"languageCode":"de","confidence":1}]},"boundingBox":{"normalizedVertices":[{"x":0.5325444,"y":0.02631579},{"x":0.56804734,"y":0.02631579},{"x":0.56804734,"y":0.045454547},{"x":0.5325444,"y":0.045454547}]},"symbols":[{"text":"m","confidence":0.9694975}],"confidence":0.9694975},{"property":{"detectedLanguages":[{"languageCode":"de","confidence":1}]},"boundingBox":{"normalizedVertices":[{"x":0.5739645,"y":0.02631579},{"x":0.5857988,"y":0.02631579},{"x":0.5857988,"y":0.045454547},{"x":0.5739645,"y":0.045454547}]},"symbols":[{"property":{"detectedBreak":{"type":"SPACE"}},"text":")","confidence":0.9766479}],"confidence":0.9766479},{"property":{"detectedLanguages":[{"languageCode":"de","confidence":1}]},"boundingBox":{"normalizedVertices":[{"x":0.61538464,"y":0.02631579},{"x":0.84023666,"y":0.02631579},{"x":0.84023666,"y":0.045454547},{"x":0.61538464,"y":0.045454547}]},"symbols":[{"text":"s","confidence":0.992184},{"text":"p","confidence":0.99333924},{"text":"r","confidence":0.9931812},{"text":"e","confidence":0.9938942},{"text":"c","confidence":0.99359137},{"text":"h","confidence":0.9946968},{"text":"e","confidence":0.99054587},{"text":"n","confidence":0.99395245}],"confidence":0.9931731},{"property":{"detectedLanguages":[{"languageCode":"de","confidence":1}]},"boundingBox":{"normalizedVertices":[{"x":0.84023666,"y":0.02631579},{"x":0.852071,"y":0.02631579},{"x":0.852071,"y":0.045454547},{"x":0.84023666,"y":0.045454547}]},"symbols":[{"property":{"detectedBreak":{"type":"SPACE"}},"text":",","confidence":0.9944208}],"confidence":0.9944208},{"property":{"detectedLanguages":[{"languageCode":"de","confidence":1}]},"boundingBox":{"normalizedVertices":[{"x":0.8816568,"y":0.02631579},{"x":0.964497,"y":0.02631579},{"x":0.964497,"y":0.045454547},{"x":0.8816568,"y":0.045454547}]},"symbols":[{"text":"d","confidence":0.99760306},{"text":"e","confidence":0.9978869},{"property":{"detectedBreak":{"type":"EOL_SURE_SPACE"}},"text":"n","confidence":0.99409115}],"confidence":0.996527},{"property":{"detectedLanguages":[{"languageCode":"de","confidence":1}]},"boundingBox":{"normalizedVertices":[{"x":0.06508876,"y":0.05263158},{"x":0.15384616,"y":0.05263158},{"x":0.15384616,"y":0.06937799},{"x":0.06508876,"y":0.066985644}]},"symbols":[{"text":"H","confidence":0.97896576},{"text":"o","confidence":0.98587036},{"property":{"detectedBreak":{"type":"SPACE"}},"text":"f","confidence":0.98651266}],"confidence":0.98378295},{"property":{"detectedLanguages":[{"languageCode":"de","confidence":1}]},"boundingBox":{"normalizedVertices":[{"x":0.17159763,"y":0.05263158},{"x":0.36094674,"y":0.055023924},{"x":0.36094674,"y":0.06937799},{"x":0.17159763,"y":0.06937799}]},"symbols":[{"text":"m","confidence":0.99482214},{"text":"a","confidence":0.994496},{"text":"c","confidence":0.98970544},{"text":"h","confidence":0.9880234},{"text":"e","confidence":0.9849146},{"property":{"detectedBreak":{"type":"LINE_BREAK"}},"text":"n","confidence":0.99138093}],"confidence":0.9905571}],"confidence":0.9872397},{"boundingBox":{"normalizedVertices":[{"x":0.01775148,"y":0.08133971},{"x":0.5739645,"y":0.078947365},{"x":0.5739645,"y":0.102870815},{"x":0.01775148,"y":0.102870815}]},"words":[{"property":{"detectedLanguages":[{"languageCode":"de","confidence":1}]},"boundingBox":{"normalizedVertices":[{"x":0.01775148,"y":0.08133971},{"x":0.147929,"y":0.08133971},{"x":0.147929,"y":0.102870815},{"x":0.01775148,"y":0.102870815}]},"symbols":[{"text":"კ","confidence":0.99799687},{"text":"უ","confidence":0.998103},{"text":"რ","confidence":0.9988394},{"property":{"detectedBreak":{"type":"SPACE"}},"text":"ნ","confidence":0.962112}],"confidence":0.9892628},{"property":{"detectedLanguages":[{"languageCode":"de","confidence":1}]},"boundingBox":{"normalizedVertices":[{"x":0.17159763,"y":0.08133971},{"x":0.32544377,"y":0.078947365},{"x":0.32544377,"y":0.102870815},{"x":0.17159763,"y":0.102870815}]},"symbols":[{"text":"h","confidence":0.9995119},{"text":"e","confidence":0.99787503},{"text":"i","confidence":0.9992997},{"text":"l","confidence":0.9982022},{"text":"e","confidence":0.997096},{"text":"n","confidence":0.99905765}],"confidence":0.9985071},{"property":{"detectedLanguages":[{"languageCode":"de","confidence":1}]},"boundingBox":{"normalizedVertices":[{"x":0.3372781,"y":0.078947365},{"x":0.34319526,"y":0.078947365},{"x":0.34319526,"y":0.102870815},{"x":0.3372781,"y":0.102870815}]},"symbols":[{"property":{"detectedBreak":{"type":"SPACE"}},"text":",","confidence":0.9975168}],"confidence":0.9975168},{"property":{"detectedLanguages":[{"languageCode":"de","confidence":1}]},"boundingBox":{"normalizedVertices":[{"x":0.37278107,"y":0.078947365},{"x":0.5739645,"y":0.078947365},{"x":0.5739645,"y":0.102870815},{"x":0.37278107,"y":0.102870815}]},"symbols":[{"text":"k","confidence":0.99950325},{"text":"u","confidence":0.9997365},{"text":"r","confidence":0.999876},{"text":"i","confidence":0.999707},{"text":"e","confidence":0.99963635},{"text":"r","confidence":0.9997984},{"text":"e","confidence":0.99963856},{"property":{"detectedBreak":{"type":"LINE_BREAK"}},"text":"n","confidence":0.99571866}],"confidence":0.99920183}],"confidence":0.9968013}],"blockType":"TEXT","confidence":0.99031883},{"boundingBox":{"normalizedVertices":[{"x":0.01775148,"y":0.11244019},{"x":0.9585799,"y":0.11004785},{"x":0.9585799,"y":0.16028708},{"x":0.01775148,"y":0.16028708}]},"paragraphs":[{"boundingBox":{"normalizedVertices":[{"x":0.01775148,"y":0.11244019},{"x":0.9585799,"y":0.11004785},{"x":0.9585799,"y":0.16028708},{"x":0.01775148,"y":0.16028708}]},"words":[{"property":{"detectedLanguages":[{"languageCode":"lb","confidence":1}]},"boundingBox":{"normalizedVertices":[{"x":0.01775148,"y":0.11244019},{"x":0.25443786,"y":0.11004785},{"x":0.25443786,"y":0.13157895},{"x":0.01775148,"y":0.13157895}]},"symbols":[{"text":"j","confidence":0.30334845},{"text":"m","confidence":0.30054548},{"text":"m","confidence":0.33446512},{"text":"b","confidence":0.45153135},{"text":"s","confidence":0.37209508},{"property":{"detectedBreak":{"type":"SPACE"}},"text":"m","confidence":0.76251036}],"confidence":0.4207493},{"property":{"detectedLanguages":[{"languageCode":"lb","confidence":1}]},"boundingBox":{"normalizedVertices":[{"x":0.28402367,"y":0.11004785},{"x":0.295858,"y":0.11004785},{"x":0.295858,"y":0.13157895},{"x":0.28402367,"y":0.13157895}]},"symbols":[{"text":"(","confidence":0.9698303}],"confidence":0.9698303},{"property":{"detectedLanguages":[{"languageCode":"lb","confidence":1}]},"boundingBox":{"normalizedVertices":[{"x":0.30177516,"y":0.11004785},{"x":0.41420117,"y":0.11004785},{"x":0.41420117,"y":0.13157895},{"x":0.30177516,"y":0.13157895}]},"symbols":[{"text":"i","confidence":0.96414524},{"text":"m","confidence":0.9931945},{"text":"e","confidence":0.9929304},{"text":"r","confidence":0.98838085}],"confidence":0.9846628},{"property":{"detectedLanguages":[{"languageCode":"lb","confidence":1}]},"boundingBox":{"normalizedVertices":[{"x":0.41420117,"y":0.11004785},{"x":0.4260355,"y":0.11004785},{"x":0.4260355,"y":0.13157895},{"x":0.41420117,"y":0.13157895}]},"symbols":[{"text":".","confidence":0.9823481}],"confidence":0.9823481},{"property":{"detectedLanguages":[{"languageCode":"lb","confidence":1}]},"boundingBox":{"normalizedVertices":[{"x":0.43786982,"y":0.11004785},{"x":0.44378698,"y":0.11004785},{"x":0.44378698,"y":0.13157895},{"x":0.43786982,"y":0.13157895}]},"symbols":[{"property":{"detectedBreak":{"type":"SPACE"}},"text":",","confidence":0.9845522}],"confidence":0.9845522},{"property":{"detectedLanguages":[{"languageCode":"lb","confidence":1}]},"boundingBox":{"normalizedVertices":[{"x":0.4733728,"y":0.11004785},{"x":0.62721896,"y":0.11004785},{"x":0.62721896,"y":0.13157895},{"x":0.4733728,"y":0.13157895}]},"symbols":[{"text":"r","confidence":0.9936315},{"text":"a","confidence":0.99552816},{"text":"t","confidence":0.99210185},{"text":"s","confidence":0.987388},{"text":"c","confidence":0.97457945},{"text":"h","confidence":0.96920645}],"confidence":0.9854059},{"property":{"detectedLanguages":[{"languageCode":"lb","confidence":1}]},"boundingBox":{"normalizedVertices":[{"x":0.6331361,"y":0.11004785},{"x":0.6449704,"y":0.11004785},{"x":0.6449704,"y":0.13157895},{"x":0.6331361,"y":0.13157895}]},"symbols":[{"text":".","confidence":0.98474336}],"confidence":0.98474336},{"property":{"detectedLanguages":[{"languageCode":"lb","confidence":1}]},"boundingBox":{"normalizedVertices":[{"x":0.65088755,"y":0.11004785},{"x":0.66863906,"y":0.11004785},{"x":0.66863906,"y":0.13157895},{"x":0.65088755,"y":0.13157895}]},"symbols":[{"property":{"detectedBreak":{"type":"SPACE"}},"text":")","confidence":0.9831695}],"confidence":0.9831695},{"property":{"detectedLanguages":[{"languageCode":"lb","confidence":1}]},"boundingBox":{"normalizedVertices":[{"x":0.6923077,"y":0.11004785},{"x":0.82840234,"y":0.11004785},{"x":0.82840234,"y":0.1291866},{"x":0.6923077,"y":0.13157895}]},"symbols":[{"text":"d","confidence":0.99065113},{"text":"i","confidence":0.9909388},{"text":"c","confidence":0.9906075},{"text":"k","confidence":0.9879236},{"property":{"detectedBreak":{"type":"SPACE"}},"text":"e","confidence":0.99370426}],"confidence":0.99076504},{"property":{"detectedLanguages":[{"languageCode":"lb","confidence":1}]},"boundingBox":{"normalizedVertices":[{"x":0.852071,"y":0.11004785},{"x":0.9408284,"y":0.11004785},{"x":0.9408284,"y":0.1291866},{"x":0.852071,"y":0.1291866}]},"symbols":[{"text":"T","confidence":0.9894952},{"text":"r","confidence":0.9882759},{"property":{"detectedBreak":{"type":"HYPHEN"}},"text":"ä","confidence":0.97268176}],"confidence":0.9717393},{"property":{"detectedLanguages":[{"languageCode":"lb","confidence":1}]},"boundingBox":{"normalizedVertices":[{"x":0.06508876,"y":0.14354067},{"x":0.147929,"y":0.14354067},{"x":0.147929,"y":0.16028708},{"x":0.06508876,"y":0.16028708}]},"symbols":[{"text":"n","confidence":0.99002093},{"text":"e","confidence":0.9935453},{"property":{"detectedBreak":{"type":"SPACE"}},"text":"n","confidence":0.99186397}],"confidence":0.9918101},{"property":{"detectedLanguages":[{"languageCode":"lb","confidence":1}]},"boundingBox":{"normalizedVertices":[{"x":0.17159763,"y":0.14354067},{"x":0.44970414,"y":0.14114833},{"x":0.44970414,"y":0.16028708},{"x":0.17159763,"y":0.16028708}]},"symbols":[{"text":"v","confidence":0.994028},{"text":"e","confidence":0.99588025},{"text":"r","confidence":0.9935966},{"text":"g","confidence":0.99209386},{"text":"i","confidence":0.9932153},{"text":"e","confidence":0.993426},{"text":"s","confidence":0.99104077},{"text":"s","confidence":0.9921526},{"text":"e","confidence":0.99155384},{"property":{"detectedBreak":{"type":"LINE_BREAK"}},"text":"n","confidence":0.99336773}],"confidence":0.9930355}],"confidence":0.90759987}],"blockType":"TEXT","confidence":0.90759987},{"boundingBox":{"normalizedVertices":[{"x":0.01183432,"y":0.16267942},{"x":0.964497,"y":0.16267942},{"x":0.964497,"y":0.27751195},{"x":0.01183432,"y":0.27751195}]},"paragraphs":[{"boundingBox":{"normalizedVertices":[{"x":0.01775148,"y":0.16267942},{"x":0.964497,"y":0.16267942},{"x":0.964497,"y":0.2200957},{"x":0.01775148,"y":0.2200957}]},"words":[{"property":{"detectedLanguages":[{"languageCode":"ka","confidence":1}]},"boundingBox":{"normalizedVertices":[{"x":0.01775148,"y":0.16267942},{"x":0.28402367,"y":0.16267942},{"x":0.28402367,"y":0.1937799},{"x":0.01775148,"y":0.1937799}]},"symbols":[{"text":"კ","confidence":0.9982034},{"text":"უ","confidence":0.99976},{"text":"რ","confidence":0.99998033},{"text":"ც","confidence":0.99998957},{"text":"ხ","confidence":0.9999665},{"text":"ა","confidence":0.9998464},{"text":"ლ","confidence":0.9971889},{"text":"ა","confidence":0.98319805}],"confidence":0.99726665},{"property":{"detectedLanguages":[{"languageCode":"ka","confidence":1}]},"boundingBox":{"normalizedVertices":[{"x":0.28994083,"y":0.16267942},{"x":0.30769232,"y":0.16267942},{"x":0.30769232,"y":0.1937799},{"x":0.28994083,"y":0.1937799}]},"symbols":[{"text":"(","confidence":0.99821174}],"confidence":0.99821174},{"property":{"detectedLanguages":[{"languageCode":"ka","confidence":1}]},"boundingBox":{"normalizedVertices":[{"x":0.31360948,"y":0.16267942},{"x":0.3372781,"y":0.16267942},{"x":0.3372781,"y":0.1937799},{"x":0.31360948,"y":0.1937799}]},"symbols":[{"text":"ვ","confidence":0.99334687}],"confidence":0.99334687},{"property":{"detectedLanguages":[{"languageCode":"ka","confidence":1}]},"boundingBox":{"normalizedVertices":[{"x":0.34911242,"y":0.16267942},{"x":0.36094674,"y":0.16267942},{"x":0.36094674,"y":0.1937799},{"x":0.34911242,"y":0.1937799}]},"symbols":[{"property":{"detectedBreak":{"type":"SPACE"}},"text":")","confidence":0.97478855}],"confidence":0.97478855},{"property":{"detectedLanguages":[{"languageCode":"ka","confidence":1}]},"boundingBox":{"normalizedVertices":[{"x":0.3846154,"y":0.16267942},{"x":0.3964497,"y":0.16267942},{"x":0.3964497,"y":0.1937799},{"x":0.3846154,"y":0.1937799}]},"symbols":[{"text":"(","confidence":0.956886}],"confidence":0.956886},{"property":{"detectedLanguages":[{"languageCode":"ka","confidence":1}]},"boundingBox":{"normalizedVertices":[{"x":0.40236688,"y":0.16267942},{"x":0.5088757,"y":0.16267942},{"x":0.5088757,"y":0.1937799},{"x":0.40236688,"y":0.1937799}]},"symbols":[{"text":"i","confidence":0.99412376},{"text":"m","confidence":0.99982685},{"text":"e","confidence":0.9984998},{"text":"r","confidence":0.9855006}],"confidence":0.99448776},{"property":{"detectedLanguages":[{"languageCode":"ka","confidence":1}]},"boundingBox":{"normalizedVertices":[{"x":0.5147929,"y":0.16267942},{"x":0.52071005,"y":0.16267942},{"x":0.52071005,"y":0.1937799},{"x":0.5147929,"y":0.1937799}]},"symbols":[{"text":".","confidence":0.63832635}],"confidence":0.63832635},{"property":{"detectedLanguages":[{"languageCode":"ka","confidence":1}]},"boundingBox":{"normalizedVertices":[{"x":0.5325444,"y":0.16267942},{"x":0.5443787,"y":0.16267942},{"x":0.5443787,"y":0.1937799},{"x":0.5325444,"y":0.1937799}]},"symbols":[{"property":{"detectedBreak":{"type":"SPACE"}},"text":",","confidence":0.7422856}],"confidence":0.7422856},{"property":{"detectedLanguages":[{"languageCode":"ka","confidence":1}]},"boundingBox":{"normalizedVertices":[{"x":0.56213015,"y":0.16267942},{"x":0.71597636,"y":0.16267942},{"x":0.71597636,"y":0.1937799},{"x":0.56213015,"y":0.1937799}]},"symbols":[{"text":"r","confidence":0.9959582},{"text":"a","confidence":0.9983472},{"text":"t","confidence":0.9989946},{"text":"s","confidence":0.99983734},{"text":"c","confidence":0.99998343},{"text":"h","confidence":0.9999969}],"confidence":0.99885297},{"property":{"detectedLanguages":[{"languageCode":"ka","confidence":1}]},"boundingBox":{"normalizedVertices":[{"x":0.7218935,"y":0.16267942},{"x":0.7278106,"y":0.16267942},{"x":0.7278106,"y":0.1937799},{"x":0.7218935,"y":0.1937799}]},"symbols":[{"text":".","confidence":0.99980044}],"confidence":0.99980044},{"property":{"detectedLanguages":[{"languageCode":"ka","confidence":1}]},"boundingBox":{"normalizedVertices":[{"x":0.74556214,"y":0.16267942},{"x":0.75739646,"y":0.16267942},{"x":0.75739646,"y":0.1937799},{"x":0.74556214,"y":0.1937799}]},"symbols":[{"property":{"detectedBreak":{"type":"SPACE"}},"text":")","confidence":0.9953875}],"confidence":0.9953875},{"property":{"detectedLanguages":[{"languageCode":"ka","confidence":1}]},"boundingBox":{"normalizedVertices":[{"x":0.7810651,"y":0.16267942},{"x":0.80473375,"y":0.16267942},{"x":0.80473375,"y":0.1937799},{"x":0.7810651,"y":0.1937799}]},"symbols":[{"text":"s","confidence":0.7179902}],"confidence":0.7179902},{"property":{"detectedLanguages":[{"languageCode":"ka","confidence":1}]},"boundingBox":{"normalizedVertices":[{"x":0.8106509,"y":0.16267942},{"x":0.8165681,"y":0.16267942},{"x":0.8165681,"y":0.1937799},{"x":0.8106509,"y":0.1937799}]},"symbols":[{"property":{"detectedBreak":{"type":"SPACE"}},"text":".","confidence":0.9361679}],"confidence":0.9361679},{"property":{"detectedLanguages":[{"languageCode":"ka","confidence":1}]},"boundingBox":{"normalizedVertices":[{"x":0.84023666,"y":0.16267942},{"x":0.93491125,"y":0.16267942},{"x":0.93491125,"y":0.1937799},{"x":0.84023666,"y":0.1937799}]},"symbols":[{"text":"კ","confidence":0.9991141},{"text":"უ","confidence":0.999745},{"property":{"detectedBreak":{"type":"HYPHEN"}},"text":"რ","confidence":0.9998147}],"confidence":0.99294513},{"boundingBox":{"normalizedVertices":[{"x":0.06508876,"y":0.19617225},{"x":0.20118344,"y":0.19617225},{"x":0.20118344,"y":0.2200957},{"x":0.06508876,"y":0.2200957}]},"symbols":[{"text":"ც","confidence":0.99963427},{"text":"ხ","confidence":0.9998554},{"text":"ა","confidence":0.99993974},{"property":{"detectedBreak":{"type":"LINE_BREAK"}},"text":"ლ","confidence":0.98532057}],"confidence":0.9961875}],"confidence":0.96830344},{"boundingBox":{"normalizedVertices":[{"x":0.01775148,"y":0.22248805},{"x":0.74556214,"y":0.22248805},{"x":0.74556214,"y":0.24880382},{"x":0.01775148,"y":0.24880382}]},"words":[{"property":{"detectedLanguages":[{"languageCode":"ka","confidence":1}]},"boundingBox":{"normalizedVertices":[{"x":0.01775148,"y":0.22248805},{"x":0.26035503,"y":0.22248805},{"x":0.26035503,"y":0.24880382},{"x":0.01775148,"y":0.24880382}]},"symbols":[{"text":"კ","confidence":0.9927101},{"text":"უ","confidence":0.99904674},{"text":"რ","confidence":0.99992466},{"text":"ც","confidence":0.9999447},{"text":"ხ","confidence":0.9998073},{"text":"ვ","confidence":0.9932193},{"property":{"detectedBreak":{"type":"SPACE"}},"text":"ლ","confidence":0.87170416}],"confidence":0.97947955},{"property":{"detectedLanguages":[{"languageCode":"ka","confidence":1}]},"boundingBox":{"normalizedVertices":[{"x":0.2781065,"y":0.22248805},{"x":0.295858,"y":0.22248805},{"x":0.295858,"y":0.24880382},{"x":0.2781065,"y":0.24880382}]},"symbols":[{"text":"(","confidence":0.9994309}],"confidence":0.9994309},{"property":{"detectedLanguages":[{"languageCode":"ka","confidence":1}]},"boundingBox":{"normalizedVertices":[{"x":0.30177516,"y":0.22248805},{"x":0.3964497,"y":0.22248805},{"x":0.3964497,"y":0.24880382},{"x":0.30177516,"y":0.24880382}]},"symbols":[{"text":"u","confidence":0.99437314},{"text":"m","confidence":0.9985655},{"text":"g","confidence":0.99252325}],"confidence":0.99515396},{"property":{"detectedLanguages":[{"languageCode":"ka","confidence":1}]},"boundingBox":{"normalizedVertices":[{"x":0.40828404,"y":0.22248805},{"x":0.41420117,"y":0.22248805},{"x":0.41420117,"y":0.24880382},{"x":0.40828404,"y":0.24880382}]},"symbols":[{"text":".","confidence":0.994174}],"confidence":0.994174},{"property":{"detectedLanguages":[{"languageCode":"ka","confidence":1}]},"boundingBox":{"normalizedVertices":[{"x":0.4260355,"y":0.22248805},{"x":0.43786982,"y":0.22248805},{"x":0.43786982,"y":0.24880382},{"x":0.4260355,"y":0.24880382}]},"symbols":[{"property":{"detectedBreak":{"type":"SPACE"}},"text":")","confidence":0.98225206}],"confidence":0.98225206},{"property":{"detectedLanguages":[{"languageCode":"ka","confidence":1}]},"boundingBox":{"normalizedVertices":[{"x":0.46745563,"y":0.22248805},{"x":0.4852071,"y":0.22248805},{"x":0.4852071,"y":0.24880382},{"x":0.46745563,"y":0.24880382}]},"symbols":[{"text":"s","confidence":0.94999284}],"confidence":0.94999284},{"property":{"detectedLanguages":[{"languageCode":"ka","confidence":1}]},"boundingBox":{"normalizedVertices":[{"x":0.49112427,"y":0.22248805},{"x":0.5029586,"y":0.22248805},{"x":0.5029586,"y":0.24880382},{"x":0.49112427,"y":0.24880382}]},"symbols":[{"property":{"detectedBreak":{"type":"SPACE"}},"text":".","confidence":0.9149761}],"confidence":0.9149761},{"property":{"detectedLanguages":[{"languageCode":"ka","confidence":1}]},"boundingBox":{"normalizedVertices":[{"x":0.5325444,"y":0.22248805},{"x":0.74556214,"y":0.22248805},{"x":0.74556214,"y":0.24880382},{"x":0.5325444,"y":0.24880382}]},"symbols":[{"text":"კ","confidence":0.99975526},{"text":"უ","confidence":0.999925},{"text":"რ","confidence":0.9999741},{"text":"ც","confidence":0.9998529},{"text":"ხ","confidence":0.99958843},{"property":{"detectedBreak":{"type":"LINE_BREAK"}},"text":"ლ","confidence":0.9769093}],"confidence":0.9960008}],"confidence":0.9837452},{"boundingBox":{"normalizedVertices":[{"x":0.01183432,"y":0.25598085},{"x":0.964497,"y":0.25598085},{"x":0.964497,"y":0.27751195},{"x":0.01183432,"y":0.27751195}]},"words":[{"property":{"detectedLanguages":[{"languageCode":"de","confidence":1}]},"boundingBox":{"normalizedVertices":[{"x":0.01183432,"y":0.25598085},{"x":0.25443786,"y":0.25598085},{"x":0.25443786,"y":0.27751195},{"x":0.01183432,"y":0.27751195}]},"symbols":[{"text":"J","confidence":0.26240605},{"text":"b","confidence":0.22944826},{"property":{"detectedBreak":{"type":"SPACE"}},"text":"¹","confidence":0.26219076}],"confidence":0.25134835},{"property":{"detectedLanguages":[{"languageCode":"de","confidence":1}]},"boundingBox":{"normalizedVertices":[{"x":0.2781065,"y":0.25598085},{"x":0.30177516,"y":0.25598085},{"x":0.30177516,"y":0.27751195},{"x":0.2781065,"y":0.27751195}]},"symbols":[{"text":"(","confidence":0.9586775}],"confidence":0.9586775},{"property":{"detectedLanguages":[{"languageCode":"de","confidence":1}]},"boundingBox":{"normalizedVertices":[{"x":0.30177516,"y":0.25598085},{"x":0.40236688,"y":0.25598085},{"x":0.40236688,"y":0.27751195},{"x":0.30177516,"y":0.27751195}]},"symbols":[{"text":"u","confidence":0.97298443},{"text":"m","confidence":0.98488045},{"text":"g","confidence":0.9748866}],"confidence":0.9775838},{"property":{"detectedLanguages":[{"languageCode":"de","confidence":1}]},"boundingBox":{"normalizedVertices":[{"x":0.40236688,"y":0.25598085},{"x":0.42011833,"y":0.25598085},{"x":0.42011833,"y":0.27751195},{"x":0.40236688,"y":0.27751195}]},"symbols":[{"text":".","confidence":0.894123}],"confidence":0.894123},{"property":{"detectedLanguages":[{"languageCode":"de","confidence":1}]},"boundingBox":{"normalizedVertices":[{"x":0.42011833,"y":0.25598085},{"x":0.43786982,"y":0.25598085},{"x":0.43786982,"y":0.27751195},{"x":0.42011833,"y":0.27751195}]},"symbols":[{"property":{"detectedBreak":{"type":"SPACE"}},"text":")","confidence":0.92371345}],"confidence":0.92371345},{"property":{"detectedLanguages":[{"languageCode":"de","confidence":1}]},"boundingBox":{"normalizedVertices":[{"x":0.44970414,"y":0.25598085},{"x":0.46745563,"y":0.25598085},{"x":0.46745563,"y":0.27751195},{"x":0.44970414,"y":0.27751195}]},"symbols":[{"text":"(","confidence":0.98355895}],"confidence":0.98355895},{"property":{"detectedLanguages":[{"languageCode":"de","confidence":1}]},"boundingBox":{"normalizedVertices":[{"x":0.4733728,"y":0.25598085},{"x":0.6331361,"y":0.25598085},{"x":0.6331361,"y":0.27751195},{"x":0.4733728,"y":0.27751195}]},"symbols":[{"text":"d","confidence":0.9913043},{"text":"a","confidence":0.995309},{"text":"v","confidence":0.99446356},{"text":"o","confidence":0.9919545},{"text":"n","confidence":0.99109876},{"text":"-","confidence":0.94376564}],"confidence":0.9846493},{"property":{"detectedLanguages":[{"languageCode":"de","confidence":1}]},"boundingBox":{"normalizedVertices":[{"x":0.6390532,"y":0.25598085},{"x":0.65680474,"y":0.25598085},{"x":0.65680474,"y":0.27751195},{"x":0.6390532,"y":0.27751195}]},"symbols":[{"text":")","confidence":0.9777731}],"confidence":0.9777731},{"property":{"detectedLanguages":[{"languageCode":"de","confidence":1}]},"boundingBox":{"normalizedVertices":[{"x":0.65680474,"y":0.25598085},{"x":0.8165681,"y":0.25598085},{"x":0.8165681,"y":0.27751195},{"x":0.65680474,"y":0.27751195}]},"symbols":[{"text":"l","confidence":0.7793842},{"text":"a","confidence":0.9874205},{"text":"u","confidence":0.9964937},{"text":"f","confidence":0.99540967},{"text":"e","confidence":0.99340373},{"text":"n","confidence":0.9854907}],"confidence":0.95626706},{"property":{"detectedLanguages":[{"languageCode":"de","confidence":1}]},"boundingBox":{"normalizedVertices":[{"x":0.8165681,"y":0.25598085},{"x":0.82840234,"y":0.25598085},{"x":0.82840234,"y":0.27751195},{"x":0.8165681,"y":0.27751195}]},"symbols":[{"property":{"detectedBreak":{"type":"SPACE"}},"text":",","confidence":0.96541077}],"confidence":0.96541077},{"property":{"detectedLanguages":[{"languageCode":"de","confidence":1}]},"boundingBox":{"normalizedVertices":[{"x":0.84615386,"y":0.25598085},{"x":0.9408284,"y":0.25598085},{"x":0.9408284,"y":0.27751195},{"x":0.84615386,"y":0.27751195}]},"symbols":[{"text":"-","confidence":0.9649998},{"text":"r","confidence":0.984111},{"text":"e","confidence":0.9856739},{"property":{"detectedBreak":{"type":"HYPHEN"}},"text":"n","confidence":0.9907722}],"confidence":0.9777851}],"confidence":0.8939475}],"blockType":"TEXT","confidence":0.94700056},{"boundingBox":{"normalizedVertices":[{"x":0.2366864,"y":0.25598085},{"x":0.26035503,"y":0.25598085},{"x":0.26035503,"y":0.2631579},{"x":0.2366864,"y":0.2631579}]},"paragraphs":[{"boundingBox":{"normalizedVertices":[{"x":0.2366864,"y":0.25598085},{"x":0.26035503,"y":0.25598085},{"x":0.26035503,"y":0.2631579},{"x":0.2366864,"y":0.2631579}]},"words":[{"boundingBox":{"normalizedVertices":[{"x":0.2366864,"y":0.25598085},{"x":0.26035503,"y":0.25598085},{"x":0.26035503,"y":0.2631579},{"x":0.2366864,"y":0.2631579}]},"symbols":[{"property":{"detectedBreak":{"type":"LINE_BREAK"}},"text":"1","confidence":0.95311105}],"confidence":0.95311105}],"confidence":0.95311105}],"blockType":"TEXT","confidence":0.95311105},{"boundingBox":{"normalizedVertices":[{"x":0.75739646,"y":0.22727273},{"x":0.7751479,"y":0.22727273},{"x":0.7751479,"y":0.23444976},{"x":0.75739646,"y":0.23444976}]},"paragraphs":[{"boundingBox":{"normalizedVertices":[{"x":0.75739646,"y":0.22727273},{"x":0.7751479,"y":0.22727273},{"x":0.7751479,"y":0.23444976},{"x":0.75739646,"y":0.23444976}]},"words":[{"boundingBox":{"normalizedVertices":[{"x":0.75739646,"y":0.22727273},{"x":0.7751479,"y":0.22727273},{"x":0.7751479,"y":0.23444976},{"x":0.75739646,"y":0.23444976}]},"symbols":[{"property":{"detectedBreak":{"type":"LINE_BREAK"}},"text":"1","confidence":0.95700145}],"confidence":0.95700145}],"confidence":0.95700145}],"blockType":"TEXT","confidence":0.95700145},{"boundingBox":{"normalizedVertices":[{"x":0.01183432,"y":0.284689},{"x":0.9585799,"y":0.284689},{"x":0.9585799,"y":0.45215312},{"x":0.01183432,"y":0.45454547}]},"paragraphs":[{"boundingBox":{"normalizedVertices":[{"x":0.06508876,"y":0.28708133},{"x":0.5147929,"y":0.284689},{"x":0.5147929,"y":0.30622008},{"x":0.06508876,"y":0.30622008}]},"words":[{"property":{"detectedLanguages":[{"languageCode":"de","confidence":1}]},"boundingBox":{"normalizedVertices":[{"x":0.06508876,"y":0.28708133},{"x":0.147929,"y":0.28708133},{"x":0.147929,"y":0.30622008},{"x":0.06508876,"y":0.30622008}]},"symbols":[{"text":"n","confidence":0.99091524},{"text":"e","confidence":0.99035317},{"text":"n","confidence":0.9803082}],"confidence":0.9871922},{"property":{"detectedLanguages":[{"languageCode":"de","confidence":1}]},"boundingBox":{"normalizedVertices":[{"x":0.15384616,"y":0.28708133},{"x":0.16568047,"y":0.28708133},{"x":0.16568047,"y":0.30622008},{"x":0.15384616,"y":0.30622008}]},"symbols":[{"property":{"detectedBreak":{"type":"SPACE"}},"text":",","confidence":0.9345704}],"confidence":0.9345704},{"property":{"detectedLanguages":[{"languageCode":"de","confidence":1}]},"boundingBox":{"normalizedVertices":[{"x":0.18934911,"y":0.284689},{"x":0.5088757,"y":0.284689},{"x":0.5088757,"y":0.30622008},{"x":0.18934911,"y":0.30622008}]},"symbols":[{"text":"-","confidence":0.73026794},{"text":"g","confidence":0.9843784},{"text":"a","confidence":0.99273425},{"text":"l","confidence":0.9908753},{"text":"o","confidence":0.98354465},{"text":"p","confidence":0.9729016},{"text":"p","confidence":0.970108},{"text":"i","confidence":0.9876344},{"text":"e","confidence":0.9922917},{"text":"r","confidence":0.9948839},{"text":"e","confidence":0.98064464},{"text":"n","confidence":0.9800177}],"confidence":0.96335685},{"property":{"detectedLanguages":[{"languageCode":"de","confidence":1}]},"boundingBox":{"normalizedVertices":[{"x":0.4852071,"y":0.284689},{"x":0.5147929,"y":0.284689},{"x":0.5147929,"y":0.30622008},{"x":0.4852071,"y":0.30622008}]},"symbols":[{"property":{"detectedBreak":{"type":"LINE_BREAK"}},"text":".","confidence":0.4727691}],"confidence":0.4727691}],"confidence":0.93701166},{"boundingBox":{"normalizedVertices":[{"x":0.01183432,"y":0.3110048},{"x":0.9112426,"y":0.3110048},{"x":0.9112426,"y":0.39473686},{"x":0.01183432,"y":0.39473686}]},"words":[{"property":{"detectedLanguages":[{"languageCode":"lb","confidence":1}]},"boundingBox":{"normalizedVertices":[{"x":0.01183432,"y":0.3110048},{"x":0.23076923,"y":0.3110048},{"x":0.23076923,"y":0.33732057},{"x":0.01183432,"y":0.33732057}]},"symbols":[{"text":"კ","confidence":0.983215},{"text":"უ","confidence":0.99860597},{"text":"რ","confidence":0.9997856},{"text":"ც","confidence":0.9999541},{"text":"ხ","confidence":0.9988699},{"property":{"detectedBreak":{"type":"SPACE"}},"text":"ლ","confidence":0.98912674}],"confidence":0.9949262},{"property":{"detectedLanguages":[{"languageCode":"lb","confidence":1}]},"boundingBox":{"normalizedVertices":[{"x":0.28402367,"y":0.3110048},{"x":0.42011833,"y":0.31339714},{"x":0.42011833,"y":0.33732057},{"x":0.28402367,"y":0.33732057}]},"symbols":[{"text":"d","confidence":0.99731314},{"text":"i","confidence":0.9990731},{"text":"c","confidence":0.9998029},{"text":"k","confidence":0.9997462},{"property":{"detectedBreak":{"type":"SPACE"}},"text":"e","confidence":0.9995647}],"confidence":0.9991},{"property":{"detectedLanguages":[{"languageCode":"lb","confidence":1}]},"boundingBox":{"normalizedVertices":[{"x":0.44378698,"y":0.3110048},{"x":0.61538464,"y":0.31339714},{"x":0.61538464,"y":0.33732057},{"x":0.44378698,"y":0.33732057}]},"symbols":[{"text":"T","confidence":0.99984455},{"text":"r","confidence":0.99952996},{"text":"ä","confidence":0.99958235},{"text":"n","confidence":0.99942195},{"text":"e","confidence":0.99828696},{"property":{"detectedBreak":{"type":"SPACE"}},"text":"n","confidence":0.9980838}],"confidence":0.99912494},{"property":{"detectedLanguages":[{"languageCode":"lb","confidence":1}]},"boundingBox":{"normalizedVertices":[{"x":0.6449704,"y":0.31339714},{"x":0.9112426,"y":0.31339714},{"x":0.9112426,"y":0.33732057},{"x":0.6449704,"y":0.33732057}]},"symbols":[{"text":"v","confidence":0.9970898},{"text":"e","confidence":0.9998268},{"text":"r","confidence":0.99991846},{"text":"g","confidence":0.9998019},{"text":"i","confidence":0.99932927},{"text":"e","confidence":0.9984613},{"text":"s","confidence":0.9976324},{"text":"s","confidence":0.99868715},{"text":"e","confidence":0.99891967},{"property":{"detectedBreak":{"type":"EOL_SURE_SPACE"}},"text":"n","confidence":0.9843583}],"confidence":0.9974025},{"property":{"detectedLanguages":[{"languageCode":"de","confidence":1}]},"boundingBox":{"normalizedVertices":[{"x":0.01183432,"y":0.34449762},{"x":0.10650887,"y":0.34449762},{"x":0.10650887,"y":0.36363637},{"x":0.01183432,"y":0.36363637}]},"symbols":[{"text":"j","confidence":0.25430387},{"property":{"detectedBreak":{"type":"SPACE"}},"text":"b","confidence":0.40032837}],"confidence":0.3273161},{"property":{"detectedLanguages":[{"languageCode":"de","confidence":1}]},"boundingBox":{"normalizedVertices":[{"x":0.13609467,"y":0.34449762},{"x":0.21301775,"y":0.34449762},{"x":0.21301775,"y":0.3660287},{"x":0.13609467,"y":0.36363637}]},"symbols":[{"text":"d","confidence":0.989025},{"text":"i","confidence":0.9937763},{"property":{"detectedBreak":{"type":"SPACE"}},"text":"e","confidence":0.9939821}],"confidence":0.9922611},{"property":{"detectedLanguages":[{"languageCode":"de","confidence":1}]},"boundingBox":{"normalizedVertices":[{"x":0.2366864,"y":0.34449762},{"x":0.39053255,"y":0.34449762},{"x":0.39053255,"y":0.3660287},{"x":0.2366864,"y":0.36363637}]},"symbols":[{"text":"A","confidence":0.9761295},{"text":"u","confidence":0.973133},{"text":"g","confidence":0.9818362},{"text":"e","confidence":0.9941173},{"property":{"detectedBreak":{"type":"SPACE"}},"text":"n","confidence":0.99485743}],"confidence":0.9840147},{"property":{"detectedLanguages":[{"languageCode":"de","confidence":1}]},"boundingBox":{"normalizedVertices":[{"x":0.40828404,"y":0.34449762},{"x":0.556213,"y":0.34449762},{"x":0.556213,"y":0.3660287},{"x":0.40828404,"y":0.3660287}]},"symbols":[{"text":"r","confidence":0.988629},{"text":"o","confidence":0.98812395},{"text":"l","confidence":0.97382385},{"text":"l","confidence":0.97861505},{"text":"e","confidence":0.981321},{"text":"n","confidence":0.9887954}],"confidence":0.983218},{"property":{"detectedLanguages":[{"languageCode":"de","confidence":1}]},"boundingBox":{"normalizedVertices":[{"x":0.56213015,"y":0.34449762},{"x":0.5739645,"y":0.34449762},{"x":0.5739645,"y":0.3660287},{"x":0.56213015,"y":0.3660287}]},"symbols":[{"property":{"detectedBreak":{"type":"SPACE"}},"text":",","confidence":0.9848525}],"confidence":0.9848525},{"property":{"detectedLanguages":[{"languageCode":"de","confidence":1}]},"boundingBox":{"normalizedVertices":[{"x":0.6035503,"y":0.34449762},{"x":0.78698224,"y":0.34449762},{"x":0.78698224,"y":0.3660287},{"x":0.6035503,"y":0.3660287}]},"symbols":[{"text":"g","confidence":0.9948204},{"text":"l","confidence":0.9944507},{"text":"o","confidence":0.9960942},{"text":"t","confidence":0.99461293},{"text":"z","confidence":0.9955004},{"text":"e","confidence":0.995572},{"property":{"detectedBreak":{"type":"EOL_SURE_SPACE"}},"text":"n","confidence":0.99339616}],"confidence":0.99492097},{"property":{"detectedLanguages":[{"languageCode":"de","confidence":1}]},"boundingBox":{"normalizedVertices":[{"x":0.07100592,"y":0.37320575},{"x":0.21301775,"y":0.37320575},{"x":0.21301775,"y":0.39473686},{"x":0.07100592,"y":0.39473686}]},"symbols":[{"text":"b","confidence":0.37345186},{"text":"m","confidence":0.2575962},{"property":{"detectedBreak":{"type":"SPACE"}},"text":"b","confidence":0.34677374}],"confidence":0.3259406},{"property":{"detectedLanguages":[{"languageCode":"de","confidence":1}]},"boundingBox":{"normalizedVertices":[{"x":0.23076923,"y":0.3708134},{"x":0.42011833,"y":0.3708134},{"x":0.42011833,"y":0.3923445},{"x":0.23076923,"y":0.39473686}]},"symbols":[{"text":"u","confidence":0.9704767},{"text":"n","confidence":0.98702055},{"text":"r","confidence":0.98287296},{"text":"u","confidence":0.98837626},{"text":"h","confidence":0.98441863},{"text":"i","confidence":0.9850217},{"text":"g","confidence":0.9893736}],"confidence":0.9839372},{"property":{"detectedLanguages":[{"languageCode":"de","confidence":1}]},"boundingBox":{"normalizedVertices":[{"x":0.42011833,"y":0.3708134},{"x":0.44970414,"y":0.3708134},{"x":0.44970414,"y":0.3923445},{"x":0.42011833,"y":0.3923445}]},"symbols":[{"text":"/","confidence":0.9830934}],"confidence":0.9830934},{"property":{"detectedLanguages":[{"languageCode":"de","confidence":1}]},"boundingBox":{"normalizedVertices":[{"x":0.44970414,"y":0.3708134},{"x":0.62721896,"y":0.3708134},{"x":0.62721896,"y":0.3923445},{"x":0.44970414,"y":0.3923445}]},"symbols":[{"text":"r","confidence":0.99632657},{"text":"a","confidence":0.9958954},{"text":"s","confidence":0.99340147},{"text":"t","confidence":0.9935198},{"text":"l","confidence":0.98773193},{"text":"o","confidence":0.9929159},{"property":{"detectedBreak":{"type":"SPACE"}},"text":"s","confidence":0.99470115}],"confidence":0.99349886},{"property":{"detectedLanguages":[{"languageCode":"de","confidence":1}]},"boundingBox":{"normalizedVertices":[{"x":0.65680474,"y":0.3708134},{"x":0.75739646,"y":0.3708134},{"x":0.75739646,"y":0.3923445},{"x":0.65680474,"y":0.3923445}]},"symbols":[{"text":"s","confidence":0.9960621},{"text":"e","confidence":0.99613637},{"text":"i","confidence":0.99271774},{"property":{"detectedBreak":{"type":"LINE_BREAK"}},"text":"n","confidence":0.99117893}],"confidence":0.9940238}],"confidence":0.9467533},{"boundingBox":{"normalizedVertices":[{"x":0.01775148,"y":0.40191388},{"x":0.9585799,"y":0.39952153},{"x":0.9585799,"y":0.45215312},{"x":0.01775148,"y":0.45454547}]},"words":[{"property":{"detectedLanguages":[{"languageCode":"de","confidence":1}]},"boundingBox":{"normalizedVertices":[{"x":0.01775148,"y":0.40430623},{"x":0.1183432,"y":0.40430623},{"x":0.1183432,"y":0.42105263},{"x":0.01775148,"y":0.423445}]},"symbols":[{"text":"3","confidence":0.27246067},{"property":{"detectedBreak":{"type":"SPACE"}},"text":"8","confidence":0.3011172}],"confidence":0.28678894},{"property":{"detectedLanguages":[{"languageCode":"de","confidence":1}]},"boundingBox":{"normalizedVertices":[{"x":0.14201184,"y":0.40430623},{"x":0.1597633,"y":0.40430623},{"x":0.1597633,"y":0.42105263},{"x":0.14201184,"y":0.42105263}]},"symbols":[{"text":"(","confidence":0.9609528}],"confidence":0.9609528},{"property":{"detectedLanguages":[{"languageCode":"de","confidence":1}]},"boundingBox":{"normalizedVertices":[{"x":0.16568047,"y":0.40430623},{"x":0.21893491,"y":0.40191388},{"x":0.21893491,"y":0.42105263},{"x":0.16568047,"y":0.42105263}]},"symbols":[{"text":"a","confidence":0.9869844},{"property":{"detectedBreak":{"type":"SPACE"}},"text":"n","confidence":0.9934773}],"confidence":0.9902308},{"property":{"detectedLanguages":[{"languageCode":"de","confidence":1}]},"boundingBox":{"normalizedVertices":[{"x":0.24260356,"y":0.40191388},{"x":0.33136094,"y":0.40191388},{"x":0.33136094,"y":0.42105263},{"x":0.24260356,"y":0.42105263}]},"symbols":[{"text":"d","confidence":0.9890773},{"text":"e","confidence":0.9913459},{"property":{"detectedBreak":{"type":"SPACE"}},"text":"n","confidence":0.9914266}],"confidence":0.9906166},{"property":{"detectedLanguages":[{"languageCode":"de","confidence":1}]},"boundingBox":{"normalizedVertices":[{"x":0.35502958,"y":0.40191388},{"x":0.52662724,"y":0.40191388},{"x":0.52662724,"y":0.42105263},{"x":0.35502958,"y":0.42105263}]},"symbols":[{"text":"B","confidence":0.9930955},{"text":"e","confidence":0.99573755},{"text":"i","confidence":0.99717706},{"text":"n","confidence":0.9977828},{"text":"e","confidence":0.99574804},{"text":"n","confidence":0.9916575}],"confidence":0.99519974},{"property":{"detectedLanguages":[{"languageCode":"de","confidence":1}]},"boundingBox":{"normalizedVertices":[{"x":0.5325444,"y":0.40191388},{"x":0.5502958,"y":0.40191388},{"x":0.5502958,"y":0.41866028},{"x":0.53846157,"y":0.41866028}]},"symbols":[{"property":{"detectedBreak":{"type":"SPACE"}},"text":")","confidence":0.9885232}],"confidence":0.9885232},{"property":{"detectedLanguages":[{"languageCode":"de","confidence":1}]},"boundingBox":{"normalizedVertices":[{"x":0.56804734,"y":0.40191388},{"x":0.6863905,"y":0.40191388},{"x":0.6863905,"y":0.41866028},{"x":0.56804734,"y":0.41866028}]},"symbols":[{"text":"l","confidence":0.6508827},{"text":"a","confidence":0.9841289},{"text":"h","confidence":0.99179894},{"property":{"detectedBreak":{"type":"SPACE"}},"text":"m","confidence":0.9800716}],"confidence":0.9017205},{"property":{"detectedLanguages":[{"languageCode":"de","confidence":1}]},"boundingBox":{"normalizedVertices":[{"x":0.71005917,"y":0.40191388},{"x":0.88757396,"y":0.39952153},{"x":0.88757396,"y":0.41866028},{"x":0.71005917,"y":0.41866028}]},"symbols":[{"text":"w","confidence":0.99090624},{"text":"e","confidence":0.9957471},{"text":"r","confidence":0.99313176},{"text":"d","confidence":0.9937417},{"text":"e","confidence":0.994467},{"property":{"detectedBreak":{"type":"EOL_SURE_SPACE"}},"text":"n","confidence":0.9918375}],"confidence":0.9933052},{"property":{"detectedLanguages":[{"languageCode":"de","confidence":1}]},"boundingBox":{"normalizedVertices":[{"x":0.28402367,"y":0.430622},{"x":0.41420117,"y":0.430622},{"x":0.41420117,"y":0.45215312},{"x":0.28402367,"y":0.45215312}]},"symbols":[{"text":"r","confidence":0.9458443},{"text":"u","confidence":0.9620384},{"text":"f","confidence":0.9875894},{"text":"e","confidence":0.9913579},{"text":"n","confidence":0.99334687}],"confidence":0.97603536},{"property":{"detectedLanguages":[{"languageCode":"de","confidence":1}]},"boundingBox":{"normalizedVertices":[{"x":0.42011833,"y":0.430622},{"x":0.4260355,"y":0.430622},{"x":0.4260355,"y":0.45215312},{"x":0.42011833,"y":0.45215312}]},"symbols":[{"property":{"detectedBreak":{"type":"SPACE"}},"text":",","confidence":0.99101186}],"confidence":0.99101186},{"property":{"detectedLanguages":[{"languageCode":"de","confidence":1}]},"boundingBox":{"normalizedVertices":[{"x":0.4852071,"y":0.430622},{"x":0.65088755,"y":0.430622},{"x":0.65088755,"y":0.45215312},{"x":0.4852071,"y":0.45215312}]},"symbols":[{"text":"l","confidence":0.9907043},{"text":"o","confidence":0.9869092},{"text":"c","confidence":0.98970354},{"text":"k","confidence":0.98847437},{"text":"e","confidence":0.99735785},{"text":"n","confidence":0.9952752}],"confidence":0.99140406},{"property":{"detectedLanguages":[{"languageCode":"de","confidence":1}]},"boundingBox":{"normalizedVertices":[{"x":0.65680474,"y":0.430622},{"x":0.6627219,"y":0.430622},{"x":0.6627219,"y":0.45215312},{"x":0.65680474,"y":0.45215312}]},"symbols":[{"property":{"detectedBreak":{"type":"SPACE"}},"text":",","confidence":0.9939421}],"confidence":0.9939421},{"property":{"detectedLanguages":[{"languageCode":"de","confidence":1}]},"boundingBox":{"normalizedVertices":[{"x":0.7218935,"y":0.430622},{"x":0.852071,"y":0.430622},{"x":0.852071,"y":0.45215312},{"x":0.7218935,"y":0.45215312}]},"symbols":[{"text":"g","confidence":0.99195945},{"text":"l","confidence":0.9882572},{"text":"u","confidence":0.98499},{"text":"c","confidence":0.98838925},{"property":{"detectedBreak":{"type":"SPACE"}},"text":"k","confidence":0.9915131}],"confidence":0.9890218},{"property":{"detectedLanguages":[{"languageCode":"de","confidence":1}]},"boundingBox":{"normalizedVertices":[{"x":0.8639053,"y":0.430622},{"x":0.9408284,"y":0.430622},{"x":0.9408284,"y":0.45215312},{"x":0.8639053,"y":0.45215312}]},"symbols":[{"text":"s","confidence":0.99317366},{"text":"e","confidence":0.99135935},{"text":"n","confidence":0.9924604}],"confidence":0.99233115},{"property":{"detectedLanguages":[{"languageCode":"de","confidence":1}]},"boundingBox":{"normalizedVertices":[{"x":0.9526627,"y":0.430622},{"x":0.9585799,"y":0.430622},{"x":0.9585799,"y":0.45215312},{"x":0.9526627,"y":0.45215312}]},"symbols":[{"property":{"detectedBreak":{"type":"LINE_BREAK"}},"text":",","confidence":0.97866464}],"confidence":0.97866464}],"confidence":0.95165104}],"blockType":"TEXT","confidence":0.94722474},{"boundingBox":{"normalizedVertices":[{"x":0.24260356,"y":0.31339714},{"x":0.26035503,"y":0.31339714},{"x":0.26035503,"y":0.32296652},{"x":0.24260356,"y":0.32296652}]},"paragraphs":[{"boundingBox":{"normalizedVertices":[{"x":0.24260356,"y":0.31339714},{"x":0.26035503,"y":0.31339714},{"x":0.26035503,"y":0.32296652},{"x":0.24260356,"y":0.32296652}]},"words":[{"boundingBox":{"normalizedVertices":[{"x":0.24260356,"y":0.31339714},{"x":0.26035503,"y":0.31339714},{"x":0.26035503,"y":0.32296652},{"x":0.24260356,"y":0.32296652}]},"symbols":[{"property":{"detectedBreak":{"type":"LINE_BREAK"}},"text":"2","confidence":0.9658872}],"confidence":0.9658872}],"confidence":0.9658872}],"blockType":"TEXT","confidence":0.9658872},{"boundingBox":{"normalizedVertices":[{"x":0.01183432,"y":0.4617225},{"x":0.9704142,"y":0.45933014},{"x":0.97633135,"y":0.9449761},{"x":0.01775148,"y":0.94736844}]},"paragraphs":[{"boundingBox":{"normalizedVertices":[{"x":0.0591716,"y":0.4617225},{"x":0.2366864,"y":0.45933014},{"x":0.2366864,"y":0.48086125},{"x":0.06508876,"y":0.4832536}]},"words":[{"property":{"detectedLanguages":[{"languageCode":"nl","confidence":1}]},"boundingBox":{"normalizedVertices":[{"x":0.0591716,"y":0.4617225},{"x":0.2366864,"y":0.45933014},{"x":0.2366864,"y":0.48086125},{"x":0.06508876,"y":0.4832536}]},"symbols":[{"text":"p","confidence":0.9872138},{"text":"i","confidence":0.99291277},{"text":"e","confidence":0.9966439},{"text":"p","confidence":0.99633193},{"text":"e","confidence":0.9965581},{"property":{"detectedBreak":{"type":"LINE_BREAK"}},"text":"n","confidence":0.9925152}],"confidence":0.993696}],"confidence":0.993696},{"boundingBox":{"normalizedVertices":[{"x":0.01183432,"y":0.48564592},{"x":0.964497,"y":0.48086125},{"x":0.9704142,"y":0.5645933},{"x":0.01775148,"y":0.569378}]},"words":[{"property":{"detectedLanguages":[{"languageCode":"ka","confidence":1}]},"boundingBox":{"normalizedVertices":[{"x":0.01775148,"y":0.48564592},{"x":0.147929,"y":0.48564592},{"x":0.147929,"y":0.5119617},{"x":0.01775148,"y":0.5119617}]},"symbols":[{"text":"კ","confidence":0.98319},{"text":"უ","confidence":0.99491423},{"text":"ფ","confidence":0.9959498},{"text":"ხ","confidence":0.99598867}],"confidence":0.9925107},{"property":{"detectedLanguages":[{"languageCode":"ka","confidence":1}]},"boundingBox":{"normalizedVertices":[{"x":0.1597633,"y":0.48564592},{"x":0.17159763,"y":0.48564592},{"x":0.17159763,"y":0.5119617},{"x":0.1597633,"y":0.5119617}]},"symbols":[{"text":"(","confidence":0.9963269}],"confidence":0.9963269},{"property":{"detectedLanguages":[{"languageCode":"ka","confidence":1}]},"boundingBox":{"normalizedVertices":[{"x":0.17751479,"y":0.48564592},{"x":0.19526628,"y":0.48564592},{"x":0.19526628,"y":0.5119617},{"x":0.17751479,"y":0.5119617}]},"symbols":[{"text":"ვ","confidence":0.97911495}],"confidence":0.97911495},{"property":{"detectedLanguages":[{"languageCode":"ka","confidence":1}]},"boundingBox":{"normalizedVertices":[{"x":0.20710059,"y":0.48564592},{"x":0.22485207,"y":0.48564592},{"x":0.22485207,"y":0.5119617},{"x":0.20710059,"y":0.5119617}]},"symbols":[{"text":")","confidence":0.80305785}],"confidence":0.80305785},{"property":{"detectedLanguages":[{"languageCode":"ka","confidence":1}]},"boundingBox":{"normalizedVertices":[{"x":0.22485207,"y":0.48564592},{"x":0.26035503,"y":0.48564592},{"x":0.26035503,"y":0.5119617},{"x":0.22485207,"y":0.5119617}]},"symbols":[{"property":{"detectedBreak":{"type":"SPACE"}},"text":"ლ","confidence":0.83328855}],"confidence":0.83328855},{"property":{"detectedLanguages":[{"languageCode":"ka","confidence":1}]},"boundingBox":{"normalizedVertices":[{"x":0.295858,"y":0.48564592},{"x":0.556213,"y":0.48564592},{"x":0.556213,"y":0.5119617},{"x":0.295858,"y":0.5119617}]},"symbols":[{"text":"n","confidence":0.99859464},{"text":"a","confidence":0.9995063},{"text":"c","confidence":0.9998445},{"text":"h","confidence":0.99960667},{"text":"l","confidence":0.99976593},{"text":"e","confidence":0.99955946},{"text":"s","confidence":0.9998536},{"text":"e","confidence":0.9990057},{"property":{"detectedBreak":{"type":"SPACE"}},"text":"n","confidence":0.99941283}],"confidence":0.99946105},{"property":{"detectedLanguages":[{"languageCode":"ka","confidence":1}]},"boundingBox":{"normalizedVertices":[{"x":0.5739645,"y":0.48564592},{"x":0.591716,"y":0.48564592},{"x":0.591716,"y":0.5119617},{"x":0.5739645,"y":0.5119617}]},"symbols":[{"text":"(","confidence":0.99898475}],"confidence":0.99898475},{"property":{"detectedLanguages":[{"languageCode":"ka","confidence":1}]},"boundingBox":{"normalizedVertices":[{"x":0.5976331,"y":0.48564592},{"x":0.65088755,"y":0.48564592},{"x":0.65088755,"y":0.5119617},{"x":0.5976331,"y":0.5119617}]},"symbols":[{"text":"i","confidence":0.9970995},{"property":{"detectedBreak":{"type":"SPACE"}},"text":"m","confidence":0.9863333}],"confidence":0.9917164},{"property":{"detectedLanguages":[{"languageCode":"ka","confidence":1}]},"boundingBox":{"normalizedVertices":[{"x":0.6745562,"y":0.48564592},{"x":0.89349115,"y":0.48564592},{"x":0.89349115,"y":0.5119617},{"x":0.6745562,"y":0.5119617}]},"symbols":[{"text":"W","confidence":0.985413},{"text":"e","confidence":0.9975804},{"text":"i","confidence":0.99956197},{"text":"n","confidence":0.9986634},{"text":"b","confidence":0.9989452},{"text":"e","confidence":0.9993922},{"text":"r","confidence":0.99984723},{"text":"g","confidence":0.9998632}],"confidence":0.99740833},{"property":{"detectedLanguages":[{"languageCode":"ka","confidence":1}]},"boundingBox":{"normalizedVertices":[{"x":0.9053255,"y":0.48564592},{"x":0.91715974,"y":0.48564592},{"x":0.91715974,"y":0.5119617},{"x":0.9053255,"y":0.5119617}]},"symbols":[{"property":{"detectedBreak":{"type":"EOL_SURE_SPACE"}},"text":")","confidence":0.99336845}],"confidence":0.99336845},{"property":{"detectedLanguages":[{"languageCode":"de","confidence":1}]},"boundingBox":{"normalizedVertices":[{"x":0.01775148,"y":0.51913875},{"x":0.04733728,"y":0.51913875},{"x":0.04733728,"y":0.54066986},{"x":0.01775148,"y":0.54066986}]},"symbols":[{"property":{"detectedBreak":{"type":"SPACE"}},"text":"¿","confidence":0.38518354}],"confidence":0.38518354},{"property":{"detectedLanguages":[{"languageCode":"de","confidence":1}]},"boundingBox":{"normalizedVertices":[{"x":0.18934911,"y":0.51913875},{"x":0.41420117,"y":0.5167464},{"x":0.41420117,"y":0.54066986},{"x":0.19526628,"y":0.54066986}]},"symbols":[{"text":"m","confidence":0.9882632},{"text":"ü","confidence":0.97951925},{"text":"r","confidence":0.99265826},{"text":"r","confidence":0.9934018},{"text":"i","confidence":0.9958783},{"text":"s","confidence":0.99364275},{"text":"c","confidence":0.992141},{"text":"h","confidence":0.97936094}],"confidence":0.9893582},{"property":{"detectedLanguages":[{"languageCode":"de","confidence":1}]},"boundingBox":{"normalizedVertices":[{"x":0.40828404,"y":0.5167464},{"x":0.44378698,"y":0.5167464},{"x":0.44378698,"y":0.5382775},{"x":0.41420117,"y":0.5382775}]},"symbols":[{"text":"/","confidence":0.96048796}],"confidence":0.96048796},{"property":{"detectedLanguages":[{"languageCode":"de","confidence":1}]},"boundingBox":{"normalizedVertices":[{"x":0.44378698,"y":0.5167464},{"x":0.73964494,"y":0.5167464},{"x":0.73964494,"y":0.5382775},{"x":0.44378698,"y":0.5382775}]},"symbols":[{"text":"g","confidence":0.9938701},{"text":"r","confidence":0.9939422},{"text":"i","confidence":0.994715},{"text":"e","confidence":0.9952057},{"text":"s","confidence":0.9937718},{"text":"g","confidence":0.984951},{"text":"r","confidence":0.98654383},{"text":"ä","confidence":0.89676803},{"text":"m","confidence":0.98915184},{"text":"i","confidence":0.98343545},{"text":"g","confidence":0.98358566}],"confidence":0.9814491},{"property":{"detectedLanguages":[{"languageCode":"de","confidence":1}]},"boundingBox":{"normalizedVertices":[{"x":0.73964494,"y":0.5167464},{"x":0.7692308,"y":0.5167464},{"x":0.7692308,"y":0.5382775},{"x":0.73964494,"y":0.5382775}]},"symbols":[{"text":"/","confidence":0.9777829}],"confidence":0.9777829},{"property":{"detectedLanguages":[{"languageCode":"de","confidence":1}]},"boundingBox":{"normalizedVertices":[{"x":0.7692308,"y":0.5167464},{"x":0.9408284,"y":0.51435405},{"x":0.9467456,"y":0.5382775},{"x":0.7692308,"y":0.5382775}]},"symbols":[{"text":"t","confidence":0.9925693},{"text":"r","confidence":0.9889534},{"text":"ü","confidence":0.9488876},{"text":"b","confidence":0.9900658},{"text":"s","confidence":0.97185683},{"text":"i","confidence":0.98736274},{"property":{"detectedBreak":{"type":"HYPHEN"}},"text":"n","confidence":0.99202466}],"confidence":0.97865885},{"property":{"detectedLanguages":[{"languageCode":"de","confidence":1}]},"boundingBox":{"normalizedVertices":[{"x":0.06508876,"y":0.5478469},{"x":0.14201184,"y":0.5478469},{"x":0.14201184,"y":0.56698567},{"x":0.06508876,"y":0.569378}]},"symbols":[{"text":"n","confidence":0.9893414},{"text":"i","confidence":0.99021935},{"property":{"detectedBreak":{"type":"SPACE"}},"text":"g","confidence":0.9928828}],"confidence":0.9908145},{"property":{"detectedLanguages":[{"languageCode":"de","confidence":1}]},"boundingBox":{"normalizedVertices":[{"x":0.16568047,"y":0.5478469},{"x":0.34911242,"y":0.54545456},{"x":0.35502958,"y":0.5645933},{"x":0.16568047,"y":0.56698567}]},"symbols":[{"text":"m","confidence":0.9905761},{"text":"a","confidence":0.9933104},{"text":"c","confidence":0.99009836},{"text":"h","confidence":0.98868847},{"text":"e","confidence":0.992921},{"property":{"detectedBreak":{"type":"LINE_BREAK"}},"text":"n","confidence":0.99330056}],"confidence":0.9914825}],"confidence":0.9752486},{"boundingBox":{"normalizedVertices":[{"x":0.7218935,"y":0.54545456},{"x":0.964497,"y":0.54545456},{"x":0.964497,"y":0.56220096},{"x":0.7218935,"y":0.56220096}]},"words":[{"property":{"detectedLanguages":[{"languageCode":"de","confidence":1}]},"boundingBox":{"normalizedVertices":[{"x":0.7218935,"y":0.54545456},{"x":0.964497,"y":0.54545456},{"x":0.964497,"y":0.56220096},{"x":0.7218935,"y":0.56220096}]},"symbols":[{"text":"d","confidence":0.99599737},{"text":"e","confidence":0.99758947},{"text":"r","confidence":0.9944143},{"text":"s","confidence":0.99003536},{"text":"ä","confidence":0.9444486},{"text":"b","confidence":0.99552786},{"text":"e","confidence":0.99406415},{"text":"l","confidence":0.98155695},{"property":{"detectedBreak":{"type":"LINE_BREAK"}},"text":"n","confidence":0.9566824}],"confidence":0.9833685}],"confidence":0.9833685},{"boundingBox":{"normalizedVertices":[{"x":0.01775148,"y":0.576555},{"x":0.964497,"y":0.57416266},{"x":0.964497,"y":0.6267943},{"x":0.01775148,"y":0.6267943}]},"words":[{"property":{"detectedLanguages":[{"languageCode":"de","confidence":1}]},"boundingBox":{"normalizedVertices":[{"x":0.01775148,"y":0.57894737},{"x":0.19526628,"y":0.576555},{"x":0.20118344,"y":0.59569377},{"x":0.01775148,"y":0.59569377}]},"symbols":[{"text":"3","confidence":0.39121777},{"text":"1","confidence":0.7958252},{"property":{"detectedBreak":{"type":"SPACE"}},"text":".","confidence":0.7732565}],"confidence":0.65343314},{"property":{"detectedLanguages":[{"languageCode":"de","confidence":1}]},"boundingBox":{"normalizedVertices":[{"x":0.2366864,"y":0.576555},{"x":0.31360948,"y":0.576555},{"x":0.31360948,"y":0.59569377},{"x":0.2366864,"y":0.59569377}]},"symbols":[{"text":"z","confidence":0.977793},{"text":"e","confidence":0.99151915},{"text":"r","confidence":0.99298203}],"confidence":0.9874314},{"property":{"detectedLanguages":[{"languageCode":"de","confidence":1}]},"boundingBox":{"normalizedVertices":[{"x":0.30769232,"y":0.576555},{"x":0.32544377,"y":0.576555},{"x":0.32544377,"y":0.59569377},{"x":0.30769232,"y":0.59569377}]},"symbols":[{"text":"-","confidence":0.96325713}],"confidence":0.96325713},{"property":{"detectedLanguages":[{"languageCode":"de","confidence":1}]},"boundingBox":{"normalizedVertices":[{"x":0.33136094,"y":0.576555},{"x":0.4733728,"y":0.576555},{"x":0.4733728,"y":0.5933014},{"x":0.33136094,"y":0.59569377}]},"symbols":[{"text":"h","confidence":0.9942442},{"text":"a","confidence":0.99052656},{"text":"u","confidence":0.9920508},{"text":"e","confidence":0.99363226},{"text":"n","confidence":0.98875666}],"confidence":0.9918421},{"property":{"detectedLanguages":[{"languageCode":"de","confidence":1}]},"boundingBox":{"normalizedVertices":[{"x":0.4852071,"y":0.576555},{"x":0.49112427,"y":0.576555},{"x":0.49112427,"y":0.5933014},{"x":0.4852071,"y":0.5933014}]},"symbols":[{"property":{"detectedBreak":{"type":"SPACE"}},"text":",","confidence":0.9830618}],"confidence":0.9830618},{"property":{"detectedLanguages":[{"languageCode":"de","confidence":1}]},"boundingBox":{"normalizedVertices":[{"x":0.52662724,"y":0.576555},{"x":0.7633136,"y":0.57416266},{"x":0.7633136,"y":0.5933014},{"x":0.52662724,"y":0.5933014}]},"symbols":[{"text":"-","confidence":0.9639203},{"text":"s","confidence":0.99408895},{"text":"t","confidence":0.9905419},{"text":"ü","confidence":0.97438264},{"text":"c","confidence":0.9911972},{"text":"k","confidence":0.9871792},{"text":"e","confidence":0.9912662},{"text":"l","confidence":0.98732775},{"property":{"detectedBreak":{"type":"SPACE"}},"text":"n","confidence":0.9779915}],"confidence":0.9842106},{"property":{"detectedLanguages":[{"languageCode":"de","confidence":1}]},"boundingBox":{"normalizedVertices":[{"x":0.7928994,"y":0.57416266},{"x":0.83431953,"y":0.57416266},{"x":0.83431953,"y":0.5933014},{"x":0.7928994,"y":0.5933014}]},"symbols":[{"text":"2","confidence":0.97382903},{"property":{"detectedBreak":{"type":"SPACE"}},"text":".","confidence":0.98801637}],"confidence":0.9809227},{"property":{"detectedLanguages":[{"languageCode":"de","confidence":1}]},"boundingBox":{"normalizedVertices":[{"x":0.8698225,"y":0.57416266},{"x":0.9467456,"y":0.57416266},{"x":0.9467456,"y":0.5933014},{"x":0.8698225,"y":0.5933014}]},"symbols":[{"text":"n","confidence":0.9942925},{"text":"i","confidence":0.9923925},{"property":{"detectedBreak":{"type":"HYPHEN"}},"text":"e","confidence":0.9944128}],"confidence":0.9867575},{"property":{"detectedLanguages":[{"languageCode":"ka","confidence":1}]},"boundingBox":{"normalizedVertices":[{"x":0.01775148,"y":0.6028708},{"x":0.21893491,"y":0.6028708},{"x":0.21893491,"y":0.6267943},{"x":0.01775148,"y":0.6267943}]},"symbols":[{"text":"კ","confidence":0.9857277},{"text":"უ","confidence":0.9959952},{"text":"წ","confidence":0.9987566},{"text":"მ","confidence":0.9991235},{"text":"ა","confidence":0.99560636},{"text":"წ","confidence":0.9694233}],"confidence":0.9907721},{"property":{"detectedLanguages":[{"languageCode":"ka","confidence":1}]},"boundingBox":{"normalizedVertices":[{"x":0.2366864,"y":0.6028708},{"x":0.24852072,"y":0.6028708},{"x":0.24852072,"y":0.6267943},{"x":0.2366864,"y":0.6267943}]},"symbols":[{"property":{"detectedBreak":{"type":"SPACE"}},"text":"‘","confidence":0.91667014}],"confidence":0.91667014},{"property":{"detectedLanguages":[{"languageCode":"ka","confidence":1}]},"boundingBox":{"normalizedVertices":[{"x":0.2781065,"y":0.6028708},{"x":0.30177516,"y":0.6028708},{"x":0.30177516,"y":0.6267943},{"x":0.2781065,"y":0.6267943}]},"symbols":[{"text":"s","confidence":0.7626664}],"confidence":0.7626664},{"property":{"detectedLanguages":[{"languageCode":"ka","confidence":1}]},"boundingBox":{"normalizedVertices":[{"x":0.30769232,"y":0.6028708},{"x":0.3195266,"y":0.6028708},{"x":0.3195266,"y":0.6267943},{"x":0.30769232,"y":0.6267943}]},"symbols":[{"property":{"detectedBreak":{"type":"SPACE"}},"text":".","confidence":0.8896694}],"confidence":0.8896694},{"property":{"detectedLanguages":[{"languageCode":"ka","confidence":1}]},"boundingBox":{"normalizedVertices":[{"x":0.34911242,"y":0.6028708},{"x":0.5443787,"y":0.6028708},{"x":0.5443787,"y":0.6267943},{"x":0.34911242,"y":0.6267943}]},"symbols":[{"text":"ქ","confidence":0.99566096},{"text":"უ","confidence":0.99832636},{"text":"ც","confidence":0.9997421},{"text":"მ","confidence":0.9999395},{"text":"ა","confidence":0.9999797},{"property":{"detectedBreak":{"type":"LINE_BREAK"}},"text":"ც","confidence":0.9986084}],"confidence":0.9987095}],"confidence":0.9558323},{"boundingBox":{"normalizedVertices":[{"x":0.01775148,"y":0.6339713},{"x":0.9704142,"y":0.6315789},{"x":0.9704142,"y":0.88755983},{"x":0.01775148,"y":0.8899522}]},"words":[{"property":{"detectedLanguages":[{"languageCode":"de","confidence":1}]},"boundingBox":{"normalizedVertices":[{"x":0.01775148,"y":0.6339713},{"x":0.25443786,"y":0.6339713},{"x":0.25443786,"y":0.6555024},{"x":0.01775148,"y":0.6555024}]},"symbols":[{"text":"3","confidence":0.29083684},{"property":{"detectedBreak":{"type":"SPACE"}},"text":"2","confidence":0.42605633}],"confidence":0.3584466},{"property":{"detectedLanguages":[{"languageCode":"de","confidence":1}]},"boundingBox":{"normalizedVertices":[{"x":0.27218935,"y":0.6339713},{"x":0.295858,"y":0.6339713},{"x":0.295858,"y":0.6555024},{"x":0.27218935,"y":0.6555024}]},"symbols":[{"text":"(","confidence":0.9495548}],"confidence":0.9495548},{"property":{"detectedLanguages":[{"languageCode":"de","confidence":1}]},"boundingBox":{"normalizedVertices":[{"x":0.295858,"y":0.6339713},{"x":0.37278107,"y":0.6339713},{"x":0.37278107,"y":0.6555024},{"x":0.295858,"y":0.6555024}]},"symbols":[{"text":"g","confidence":0.9655373},{"text":"u","confidence":0.99033475},{"text":"r","confidence":0.9850989}],"confidence":0.9803237},{"property":{"detectedLanguages":[{"languageCode":"de","confidence":1}]},"boundingBox":{"normalizedVertices":[{"x":0.37869823,"y":0.6339713},{"x":0.39053255,"y":0.6339713},{"x":0.39053255,"y":0.6555024},{"x":0.37869823,"y":0.6555024}]},"symbols":[{"text":".","confidence":0.97896606}],"confidence":0.97896606},{"property":{"detectedLanguages":[{"languageCode":"de","confidence":1}]},"boundingBox":{"normalizedVertices":[{"x":0.3964497,"y":0.6339713},{"x":0.41420117,"y":0.6339713},{"x":0.41420117,"y":0.6555024},{"x":0.3964497,"y":0.6555024}]},"symbols":[{"property":{"detectedBreak":{"type":"SPACE"}},"text":")","confidence":0.98120993}],"confidence":0.98120993},{"property":{"detectedLanguages":[{"languageCode":"de","confidence":1}]},"boundingBox":{"normalizedVertices":[{"x":0.43195266,"y":0.6339713},{"x":0.5502958,"y":0.6339713},{"x":0.5502958,"y":0.6555024},{"x":0.43195266,"y":0.6555024}]},"symbols":[{"text":"b","confidence":0.98787814},{"text":"ö","confidence":0.9605683},{"text":"s","confidence":0.9914201},{"text":"e","confidence":0.98791015}],"confidence":0.9819442},{"property":{"detectedLanguages":[{"languageCode":"de","confidence":1}]},"boundingBox":{"normalizedVertices":[{"x":0.556213,"y":0.6339713},{"x":0.57988167,"y":0.6339713},{"x":0.57988167,"y":0.6555024},{"x":0.556213,"y":0.6555024}]},"symbols":[{"text":"/","confidence":0.9812441}],"confidence":0.9812441},{"property":{"detectedLanguages":[{"languageCode":"de","confidence":1}]},"boundingBox":{"normalizedVertices":[{"x":0.5857988,"y":0.6339713},{"x":0.73964494,"y":0.6339713},{"x":0.73964494,"y":0.6555024},{"x":0.5857988,"y":0.6555024}]},"symbols":[{"text":"z","confidence":0.99280834},{"text":"o","confidence":0.99115795},{"text":"r","confidence":0.9910732},{"text":"n","confidence":0.9939975},{"text":"i","confidence":0.9934804},{"property":{"detectedBreak":{"type":"SPACE"}},"text":"g","confidence":0.99538344}],"confidence":0.99298346},{"property":{"detectedLanguages":[{"languageCode":"de","confidence":1}]},"boundingBox":{"normalizedVertices":[{"x":0.7633136,"y":0.6339713},{"x":0.87573963,"y":0.6339713},{"x":0.87573963,"y":0.6555024},{"x":0.7633136,"y":0.6555024}]},"symbols":[{"text":"s","confidence":0.9904892},{"text":"e","confidence":0.9921742},{"text":"i","confidence":0.989847},{"property":{"detectedBreak":{"type":"EOL_SURE_SPACE"}},"text":"n","confidence":0.9875032}],"confidence":0.9900034},{"property":{"detectedLanguages":[{"languageCode":"de","confidence":1}]},"boundingBox":{"normalizedVertices":[{"x":0.01775148,"y":0.66267943},{"x":0.04733728,"y":0.66267943},{"x":0.04733728,"y":0.6818182},{"x":0.01775148,"y":0.6818182}]},"symbols":[{"text":"¿","confidence":0.3880233}],"confidence":0.3880233},{"property":{"detectedLanguages":[{"languageCode":"de","confidence":1}]},"boundingBox":{"normalizedVertices":[{"x":0.147929,"y":0.66267943},{"x":0.18934911,"y":0.66267943},{"x":0.18934911,"y":0.6818182},{"x":0.147929,"y":0.6818182}]},"symbols":[{"text":"1","confidence":0.6468562},{"property":{"detectedBreak":{"type":"SPACE"}},"text":".","confidence":0.89734}],"confidence":0.77209806},{"property":{"detectedLanguages":[{"languageCode":"de","confidence":1}]},"boundingBox":{"normalizedVertices":[{"x":0.22485207,"y":0.66267943},{"x":0.49704143,"y":0.66267943},{"x":0.49704143,"y":0.6818182},{"x":0.22485207,"y":0.6818182}]},"symbols":[{"text":"a","confidence":0.9899881},{"text":"u","confidence":0.99377435},{"text":"s","confidence":0.9863404},{"text":"n","confidence":0.9901769},{"text":"e","confidence":0.99580127},{"text":"h","confidence":0.9844241},{"text":"m","confidence":0.99829245},{"text":"e","confidence":0.9982074},{"property":{"detectedBreak":{"type":"SPACE"}},"text":"n","confidence":0.9979439}],"confidence":0.9927721},{"property":{"detectedLanguages":[{"languageCode":"de","confidence":1}]},"boundingBox":{"normalizedVertices":[{"x":0.52662724,"y":0.66267943},{"x":0.5443787,"y":0.66267943},{"x":0.5443787,"y":0.6818182},{"x":0.52662724,"y":0.6818182}]},"symbols":[{"text":"(","confidence":0.99430525}],"confidence":0.99430525},{"property":{"detectedLanguages":[{"languageCode":"de","confidence":1}]},"boundingBox":{"normalizedVertices":[{"x":0.5502958,"y":0.66267943},{"x":0.65088755,"y":0.66267943},{"x":0.65088755,"y":0.6818182},{"x":0.5502958,"y":0.6818182}]},"symbols":[{"text":"z","confidence":0.9936947},{"text":".","confidence":0.9931273},{"text":"B","confidence":0.98393667},{"property":{"detectedBreak":{"type":"SPACE"}},"text":".","confidence":0.99385405}],"confidence":0.9911532},{"property":{"detectedLanguages":[{"languageCode":"de","confidence":1}]},"boundingBox":{"normalizedVertices":[{"x":0.6863905,"y":0.66267943},{"x":0.8106509,"y":0.66267943},{"x":0.8106509,"y":0.6818182},{"x":0.6863905,"y":0.6818182}]},"symbols":[{"text":"H","confidence":0.98988754},{"text":"u","confidence":0.9945862},{"text":"h","confidence":0.9963385},{"text":"n","confidence":0.9986286}],"confidence":0.99486023},{"property":{"detectedLanguages":[{"languageCode":"de","confidence":1}]},"boundingBox":{"normalizedVertices":[{"x":0.8165681,"y":0.66267943},{"x":0.82840234,"y":0.66267943},{"x":0.82840234,"y":0.6818182},{"x":0.8165681,"y":0.6818182}]},"symbols":[{"text":")","confidence":0.99842376}],"confidence":0.99842376},{"property":{"detectedLanguages":[{"languageCode":"de","confidence":1}]},"boundingBox":{"normalizedVertices":[{"x":0.83431953,"y":0.66267943},{"x":0.84023666,"y":0.66267943},{"x":0.84023666,"y":0.6818182},{"x":0.83431953,"y":0.6818182}]},"symbols":[{"property":{"detectedBreak":{"type":"SPACE"}},"text":";","confidence":0.9989289}],"confidence":0.9989289},{"property":{"detectedLanguages":[{"languageCode":"de","confidence":1}]},"boundingBox":{"normalizedVertices":[{"x":0.8816568,"y":0.66267943},{"x":0.964497,"y":0.66267943},{"x":0.964497,"y":0.6818182},{"x":0.8816568,"y":0.6818182}]},"symbols":[{"text":"d","confidence":0.9997278},{"text":"e","confidence":0.9987601},{"property":{"detectedBreak":{"type":"EOL_SURE_SPACE"}},"text":"n","confidence":0.99568427}],"confidence":0.99805737},{"property":{"detectedLanguages":[{"languageCode":"de","confidence":1}]},"boundingBox":{"normalizedVertices":[{"x":0.06508876,"y":0.6937799},{"x":0.30177516,"y":0.6937799},{"x":0.30177516,"y":0.708134},{"x":0.06508876,"y":0.708134}]},"symbols":[{"text":"N","confidence":0.9372408},{"text":"u","confidence":0.89760906},{"text":"s","confidence":0.9032507},{"text":"s","confidence":0.92516494},{"text":"k","confidence":0.9624877},{"text":"e","confidence":0.9955377},{"text":"r","confidence":0.98649144},{"property":{"detectedBreak":{"type":"SPACE"}},"text":"n","confidence":0.976323}],"confidence":0.9480132},{"property":{"detectedLanguages":[{"languageCode":"de","confidence":1}]},"boundingBox":{"normalizedVertices":[{"x":0.34911242,"y":0.6937799},{"x":0.43195266,"y":0.6937799},{"x":0.43195266,"y":0.708134},{"x":0.34911242,"y":0.708134}]},"symbols":[{"text":"a","confidence":0.98682207},{"text":"u","confidence":0.9941389},{"property":{"detectedBreak":{"type":"SPACE"}},"text":"s","confidence":0.99371314}],"confidence":0.991558},{"property":{"detectedLanguages":[{"languageCode":"de","confidence":1}]},"boundingBox":{"normalizedVertices":[{"x":0.46745563,"y":0.6937799},{"x":0.5502958,"y":0.6937799},{"x":0.5502958,"y":0.708134},{"x":0.46745563,"y":0.708134}]},"symbols":[{"text":"d","confidence":0.9938209},{"text":"e","confidence":0.99374795},{"property":{"detectedBreak":{"type":"SPACE"}},"text":"r","confidence":0.9918182}],"confidence":0.993129},{"property":{"detectedLanguages":[{"languageCode":"de","confidence":1}]},"boundingBox":{"normalizedVertices":[{"x":0.57988167,"y":0.6937799},{"x":0.74556214,"y":0.6937799},{"x":0.74556214,"y":0.708134},{"x":0.57988167,"y":0.708134}]},"symbols":[{"text":"S","confidence":0.98453},{"text":"c","confidence":0.98202056},{"text":"h","confidence":0.9841348},{"text":"a","confidence":0.9960124},{"text":"l","confidence":0.99560297},{"property":{"detectedBreak":{"type":"SPACE"}},"text":"e","confidence":0.99433565}],"confidence":0.98943937},{"property":{"detectedLanguages":[{"languageCode":"de","confidence":1}]},"boundingBox":{"normalizedVertices":[{"x":0.7810651,"y":0.6937799},{"x":0.9467456,"y":0.6937799},{"x":0.9467456,"y":0.708134},{"x":0.7810651,"y":0.708134}]},"symbols":[{"text":"h","confidence":0.9913208},{"text":"e","confidence":0.9959709},{"text":"r","confidence":0.9959605},{"text":"a","confidence":0.9964277},{"text":"u","confidence":0.9927682},{"property":{"detectedBreak":{"type":"HYPHEN"}},"text":"s","confidence":0.99039394}],"confidence":0.98558575},{"property":{"detectedLanguages":[{"languageCode":"de","confidence":1}]},"boundingBox":{"normalizedVertices":[{"x":0.07100592,"y":0.72248805},{"x":0.28402367,"y":0.72248805},{"x":0.28402367,"y":0.74401915},{"x":0.07100592,"y":0.74401915}]},"symbols":[{"text":"s","confidence":0.99130404},{"text":"t","confidence":0.9944446},{"text":"o","confidence":0.99198055},{"text":"c","confidence":0.9922375},{"text":"h","confidence":0.9921429},{"text":"e","confidence":0.99229723},{"text":"r","confidence":0.98969525},{"property":{"detectedBreak":{"type":"SPACE"}},"text":"n","confidence":0.98499984}],"confidence":0.99113774},{"property":{"detectedLanguages":[{"languageCode":"de","confidence":1}]},"boundingBox":{"normalizedVertices":[{"x":0.30769232,"y":0.72248805},{"x":0.34911242,"y":0.72248805},{"x":0.34911242,"y":0.74401915},{"x":0.30769232,"y":0.74401915}]},"symbols":[{"text":"2","confidence":0.985692},{"property":{"detectedBreak":{"type":"SPACE"}},"text":".","confidence":0.98780525}],"confidence":0.98674864},{"property":{"detectedLanguages":[{"languageCode":"de","confidence":1}]},"boundingBox":{"normalizedVertices":[{"x":0.37278107,"y":0.72248805},{"x":0.39053255,"y":0.72248805},{"x":0.39053255,"y":0.7416268},{"x":0.37278107,"y":0.7416268}]},"symbols":[{"text":"(","confidence":0.9900365}],"confidence":0.9900365},{"property":{"detectedLanguages":[{"languageCode":"de","confidence":1}]},"boundingBox":{"normalizedVertices":[{"x":0.3964497,"y":0.72248805},{"x":0.5029586,"y":0.72248805},{"x":0.5029586,"y":0.7416268},{"x":0.3964497,"y":0.74401915}]},"symbols":[{"text":"i","confidence":0.9958722},{"text":"m","confidence":0.99426097},{"text":"e","confidence":0.99155927},{"text":"r","confidence":0.98678476}],"confidence":0.9921193},{"property":{"detectedLanguages":[{"languageCode":"de","confidence":1}]},"boundingBox":{"normalizedVertices":[{"x":0.5088757,"y":0.72248805},{"x":0.5147929,"y":0.72248805},{"x":0.5147929,"y":0.7416268},{"x":0.5088757,"y":0.7416268}]},"symbols":[{"text":".","confidence":0.990665}],"confidence":0.990665},{"property":{"detectedLanguages":[{"languageCode":"de","confidence":1}]},"boundingBox":{"normalizedVertices":[{"x":0.52662724,"y":0.72248805},{"x":0.53846157,"y":0.72248805},{"x":0.53846157,"y":0.7416268},{"x":0.52662724,"y":0.7416268}]},"symbols":[{"property":{"detectedBreak":{"type":"SPACE"}},"text":",","confidence":0.9966634}],"confidence":0.9966634},{"property":{"detectedLanguages":[{"languageCode":"de","confidence":1}]},"boundingBox":{"normalizedVertices":[{"x":0.56804734,"y":0.72248805},{"x":0.6390532,"y":0.72248805},{"x":0.6390532,"y":0.7416268},{"x":0.56804734,"y":0.7416268}]},"symbols":[{"text":"g","confidence":0.9973633},{"text":"u","confidence":0.99625266},{"text":"r","confidence":0.9927759}],"confidence":0.99546397},{"property":{"detectedLanguages":[{"languageCode":"de","confidence":1}]},"boundingBox":{"normalizedVertices":[{"x":0.6449704,"y":0.72248805},{"x":0.65680474,"y":0.72248805},{"x":0.65680474,"y":0.7416268},{"x":0.6449704,"y":0.7416268}]},"symbols":[{"text":".","confidence":0.976844}],"confidence":0.976844},{"property":{"detectedLanguages":[{"languageCode":"de","confidence":1}]},"boundingBox":{"normalizedVertices":[{"x":0.6627219,"y":0.72248805},{"x":0.6804734,"y":0.72248805},{"x":0.6804734,"y":0.7416268},{"x":0.6627219,"y":0.7416268}]},"symbols":[{"property":{"detectedBreak":{"type":"SPACE"}},"text":")","confidence":0.98556614}],"confidence":0.98556614},{"property":{"detectedLanguages":[{"languageCode":"de","confidence":1}]},"boundingBox":{"normalizedVertices":[{"x":0.71005917,"y":0.72248805},{"x":0.9704142,"y":0.7200957},{"x":0.9704142,"y":0.7416268},{"x":0.71005917,"y":0.7416268}]},"symbols":[{"text":"z","confidence":0.9957016},{"text":"e","confidence":0.9947807},{"text":"r","confidence":0.9942836},{"text":"k","confidence":0.99063116},{"text":"n","confidence":0.99158496},{"text":"ü","confidence":0.9847807},{"text":"l","confidence":0.9914944},{"text":"l","confidence":0.99158555},{"text":"e","confidence":0.9914229},{"property":{"detectedBreak":{"type":"EOL_SURE_SPACE"}},"text":"n","confidence":0.99199766}],"confidence":0.99182636},{"boundingBox":{"normalizedVertices":[{"x":0.07100592,"y":0.75119615},{"x":0.112426035,"y":0.75119615},{"x":0.112426035,"y":0.77272725},{"x":0.07100592,"y":0.77272725}]},"symbols":[{"text":"3","confidence":0.97415334},{"property":{"detectedBreak":{"type":"SPACE"}},"text":".","confidence":0.9811207}],"confidence":0.97763705},{"boundingBox":{"normalizedVertices":[{"x":0.1597633,"y":0.75119615},{"x":0.17751479,"y":0.75119615},{"x":0.17751479,"y":0.77272725},{"x":0.1597633,"y":0.77272725}]},"symbols":[{"text":"(","confidence":0.9732613}],"confidence":0.9732613},{"boundingBox":{"normalizedVertices":[{"x":0.18343195,"y":0.75119615},{"x":0.28994083,"y":0.75119615},{"x":0.28994083,"y":0.77272725},{"x":0.18343195,"y":0.77272725}]},"symbols":[{"text":"k","confidence":0.9852894},{"text":"h","confidence":0.99187934},{"text":"i","confidence":0.98805},{"text":"s","confidence":0.9786471}],"confidence":0.98596644},{"boundingBox":{"normalizedVertices":[{"x":0.295858,"y":0.75119615},{"x":0.30769232,"y":0.75119615},{"x":0.30769232,"y":0.77272725},{"x":0.295858,"y":0.77272725}]},"symbols":[{"text":".","confidence":0.97859734}],"confidence":0.97859734},{"boundingBox":{"normalizedVertices":[{"x":0.31360948,"y":0.75119615},{"x":0.33136094,"y":0.75119615},{"x":0.33136094,"y":0.77272725},{"x":0.31360948,"y":0.77272725}]},"symbols":[{"property":{"detectedBreak":{"type":"SPACE"}},"text":")","confidence":0.9741141}],"confidence":0.9741141},{"boundingBox":{"normalizedVertices":[{"x":0.37869823,"y":0.75119615},{"x":0.43195266,"y":0.75119615},{"x":0.43195266,"y":0.77272725},{"x":0.37869823,"y":0.77272725}]},"symbols":[{"text":"z","confidence":0.97925466},{"text":"s","confidence":0.9934451}],"confidence":0.9863499},{"boundingBox":{"normalizedVertices":[{"x":0.43786982,"y":0.75119615},{"x":0.44378698,"y":0.75119615},{"x":0.44378698,"y":0.77272725},{"x":0.43786982,"y":0.77272725}]},"symbols":[{"text":".","confidence":0.98659456}],"confidence":0.98659456},{"boundingBox":{"normalizedVertices":[{"x":0.44970414,"y":0.75119615},{"x":0.46745563,"y":0.75119615},{"x":0.46745563,"y":0.77272725},{"x":0.44970414,"y":0.77272725}]},"symbols":[{"text":"-","confidence":0.9530329}],"confidence":0.9530329},{"boundingBox":{"normalizedVertices":[{"x":0.4733728,"y":0.75119615},{"x":0.66863906,"y":0.75119615},{"x":0.66863906,"y":0.77272725},{"x":0.4733728,"y":0.77272725}]},"symbols":[{"text":"k","confidence":0.9825794},{"text":"l","confidence":0.98618627},{"text":"a","confidence":0.9906654},{"text":"p","confidence":0.99200916},{"text":"p","confidence":0.9876893},{"text":"e","confidence":0.9833437},{"property":{"detectedBreak":{"type":"SPACE"}},"text":"n","confidence":0.9920107}],"confidence":0.98778343},{"boundingBox":{"normalizedVertices":[{"x":0.71005917,"y":0.75119615},{"x":0.7278106,"y":0.75119615},{"x":0.7278106,"y":0.77272725},{"x":0.71005917,"y":0.77272725}]},"symbols":[{"text":"(","confidence":0.986502}],"confidence":0.986502},{"boundingBox":{"normalizedVertices":[{"x":0.7337278,"y":0.75119615},{"x":0.7633136,"y":0.75119615},{"x":0.7633136,"y":0.7703349},{"x":0.7337278,"y":0.7703349}]},"symbols":[{"text":"z","confidence":0.94238377}],"confidence":0.94238377},{"boundingBox":{"normalizedVertices":[{"x":0.7633136,"y":0.75119615},{"x":0.7751479,"y":0.75119615},{"x":0.7751479,"y":0.7703349},{"x":0.7633136,"y":0.7703349}]},"symbols":[{"property":{"detectedBreak":{"type":"SPACE"}},"text":".","confidence":0.8641978}],"confidence":0.8641978},{"boundingBox":{"normalizedVertices":[{"x":0.7810651,"y":0.75119615},{"x":0.82840234,"y":0.75119615},{"x":0.82840234,"y":0.7703349},{"x":0.7810651,"y":0.7703349}]},"symbols":[{"text":"B","confidence":0.9598804},{"property":{"detectedBreak":{"type":"SPACE"}},"text":".","confidence":0.9734097}],"confidence":0.96664506},{"boundingBox":{"normalizedVertices":[{"x":0.8816568,"y":0.75119615},{"x":0.9467456,"y":0.75119615},{"x":0.9467456,"y":0.7703349},{"x":0.8816568,"y":0.7703349}]},"symbols":[{"text":"T","confidence":0.98519707},{"property":{"detectedBreak":{"type":"HYPHEN"}},"text":"a","confidence":0.989008}],"confidence":0.9130479},{"property":{"detectedLanguages":[{"languageCode":"de","confidence":1}]},"boundingBox":{"normalizedVertices":[{"x":0.07100592,"y":0.7799043},{"x":0.3964497,"y":0.7799043},{"x":0.3964497,"y":0.7966507},{"x":0.07100592,"y":0.7966507}]},"symbols":[{"text":"s","confidence":0.9884606},{"text":"c","confidence":0.99292016},{"text":"h","confidence":0.9931133},{"text":"e","confidence":0.9925756},{"text":"n","confidence":0.9937252},{"text":"m","confidence":0.9935574},{"text":"e","confidence":0.9953279},{"text":"s","confidence":0.9921075},{"text":"s","confidence":0.99236286},{"text":"e","confidence":0.9853225},{"text":"r","confidence":0.99234396}],"confidence":0.99198335},{"property":{"detectedLanguages":[{"languageCode":"de","confidence":1}]},"boundingBox":{"normalizedVertices":[{"x":0.3964497,"y":0.7799043},{"x":0.41420117,"y":0.7799043},{"x":0.41420117,"y":0.7966507},{"x":0.3964497,"y":0.7966507}]},"symbols":[{"property":{"detectedBreak":{"type":"SPACE"}},"text":")","confidence":0.95628476}],"confidence":0.95628476},{"property":{"detectedLanguages":[{"languageCode":"de","confidence":1}]},"boundingBox":{"normalizedVertices":[{"x":0.4733728,"y":0.7799043},{"x":0.5147929,"y":0.7799043},{"x":0.5147929,"y":0.7966507},{"x":0.4733728,"y":0.7966507}]},"symbols":[{"text":"4","confidence":0.97612894},{"property":{"detectedBreak":{"type":"SPACE"}},"text":".","confidence":0.98852783}],"confidence":0.9823284},{"property":{"detectedLanguages":[{"languageCode":"de","confidence":1}]},"boundingBox":{"normalizedVertices":[{"x":0.5739645,"y":0.7799043},{"x":0.7278106,"y":0.7799043},{"x":0.7278106,"y":0.7966507},{"x":0.5739645,"y":0.7966507}]},"symbols":[{"text":"h","confidence":0.9845889},{"text":"i","confidence":0.99312097},{"text":"n","confidence":0.9894126},{"text":"e","confidence":0.98959434},{"text":"i","confidence":0.9807127},{"text":"n","confidence":0.9908597}],"confidence":0.9880482},{"property":{"detectedLanguages":[{"languageCode":"de","confidence":1}]},"boundingBox":{"normalizedVertices":[{"x":0.7337278,"y":0.7799043},{"x":0.74556214,"y":0.7799043},{"x":0.74556214,"y":0.7966507},{"x":0.7337278,"y":0.7966507}]},"symbols":[{"text":"-","confidence":0.97472316}],"confidence":0.97472316},{"property":{"detectedLanguages":[{"languageCode":"de","confidence":1}]},"boundingBox":{"normalizedVertices":[{"x":0.75739646,"y":0.7799043},{"x":0.9467456,"y":0.7799043},{"x":0.9467456,"y":0.7966507},{"x":0.75739646,"y":0.7966507}]},"symbols":[{"text":"s","confidence":0.99254334},{"text":"t","confidence":0.9934069},{"text":"e","confidence":0.9922381},{"text":"c","confidence":0.9905489},{"text":"k","confidence":0.98849875},{"text":"e","confidence":0.9908887},{"text":"n","confidence":0.99261045}],"confidence":0.9915336},{"property":{"detectedLanguages":[{"languageCode":"de","confidence":1}]},"boundingBox":{"normalizedVertices":[{"x":0.9526627,"y":0.7799043},{"x":0.964497,"y":0.7799043},{"x":0.964497,"y":0.7966507},{"x":0.9526627,"y":0.7966507}]},"symbols":[{"property":{"detectedBreak":{"type":"EOL_SURE_SPACE"}},"text":",","confidence":0.98584497}],"confidence":0.98584497},{"property":{"detectedLanguages":[{"languageCode":"de","confidence":1}]},"boundingBox":{"normalizedVertices":[{"x":0.06508876,"y":0.81100476},{"x":0.27218935,"y":0.80861247},{"x":0.27218935,"y":0.8301435},{"x":0.06508876,"y":0.8301435}]},"symbols":[{"text":"-","confidence":0.78076273},{"text":"s","confidence":0.9622006},{"text":"t","confidence":0.98823136},{"text":"o","confidence":0.9896183},{"text":"p","confidence":0.99110234},{"text":"f","confidence":0.9918838},{"text":"e","confidence":0.9922647},{"property":{"detectedBreak":{"type":"SPACE"}},"text":"n","confidence":0.9922708}],"confidence":0.9610418},{"property":{"detectedLanguages":[{"languageCode":"de","confidence":1}]},"boundingBox":{"normalizedVertices":[{"x":0.30177516,"y":0.80861247},{"x":0.34319526,"y":0.80861247},{"x":0.34911242,"y":0.8301435},{"x":0.30177516,"y":0.8301435}]},"symbols":[{"text":"5","confidence":0.9878296},{"property":{"detectedBreak":{"type":"SPACE"}},"text":".","confidence":0.9820629}],"confidence":0.98494625},{"property":{"detectedLanguages":[{"languageCode":"de","confidence":1}]},"boundingBox":{"normalizedVertices":[{"x":0.37869823,"y":0.80861247},{"x":0.6035503,"y":0.80861247},{"x":0.6035503,"y":0.8301435},{"x":0.37869823,"y":0.8301435}]},"symbols":[{"text":"a","confidence":0.9915958},{"text":"u","confidence":0.9927663},{"text":"f","confidence":0.9938963},{"text":"g","confidence":0.9954462},{"text":"e","confidence":0.9941019},{"text":"h","confidence":0.99173146},{"text":"e","confidence":0.9915962},{"property":{"detectedBreak":{"type":"SPACE"}},"text":"n","confidence":0.9933407}],"confidence":0.99305934},{"property":{"detectedLanguages":[{"languageCode":"de","confidence":1}]},"boundingBox":{"normalizedVertices":[{"x":0.6331361,"y":0.80861247},{"x":0.6449704,"y":0.80861247},{"x":0.6449704,"y":0.8301435},{"x":0.6331361,"y":0.8301435}]},"symbols":[{"text":"(","confidence":0.9895168}],"confidence":0.9895168},{"property":{"detectedLanguages":[{"languageCode":"de","confidence":1}]},"boundingBox":{"normalizedVertices":[{"x":0.65088755,"y":0.80861247},{"x":0.6745562,"y":0.80861247},{"x":0.6804734,"y":0.8301435},{"x":0.65088755,"y":0.8301435}]},"symbols":[{"text":"v","confidence":0.9858288}],"confidence":0.9858288},{"property":{"detectedLanguages":[{"languageCode":"de","confidence":1}]},"boundingBox":{"normalizedVertices":[{"x":0.6863905,"y":0.80861247},{"x":0.6923077,"y":0.80861247},{"x":0.6923077,"y":0.8277512},{"x":0.6863905,"y":0.8277512}]},"symbols":[{"property":{"detectedBreak":{"type":"SPACE"}},"text":".","confidence":0.94606817}],"confidence":0.94606817},{"property":{"detectedLanguages":[{"languageCode":"de","confidence":1}]},"boundingBox":{"normalizedVertices":[{"x":0.7278106,"y":0.80861247},{"x":0.75147927,"y":0.80861247},{"x":0.75147927,"y":0.8277512},{"x":0.7278106,"y":0.8277512}]},"symbols":[{"text":"e","confidence":0.9934634}],"confidence":0.9934634},{"property":{"detectedLanguages":[{"languageCode":"de","confidence":1}]},"boundingBox":{"normalizedVertices":[{"x":0.75739646,"y":0.8062201},{"x":0.7692308,"y":0.8062201},{"x":0.7692308,"y":0.8277512},{"x":0.75739646,"y":0.8277512}]},"symbols":[{"text":"-","confidence":0.9799098}],"confidence":0.9799098},{"property":{"detectedLanguages":[{"languageCode":"de","confidence":1}]},"boundingBox":{"normalizedVertices":[{"x":0.7751479,"y":0.8062201},{"x":0.7928994,"y":0.8062201},{"x":0.7928994,"y":0.8277512},{"x":0.7751479,"y":0.8277512}]},"symbols":[{"property":{"detectedBreak":{"type":"SPACE"}},"text":"r","confidence":0.97604316}],"confidence":0.97604316},{"property":{"detectedLanguages":[{"languageCode":"de","confidence":1}]},"boundingBox":{"normalizedVertices":[{"x":0.8224852,"y":0.8062201},{"x":0.9467456,"y":0.8062201},{"x":0.9467456,"y":0.8277512},{"x":0.8224852,"y":0.8277512}]},"symbols":[{"text":"K","confidence":0.9765715},{"text":"n","confidence":0.99308217},{"text":"o","confidence":0.99064326},{"property":{"detectedBreak":{"type":"HYPHEN"}},"text":"s","confidence":0.9798636}],"confidence":0.97187024},{"property":{"detectedLanguages":[{"languageCode":"de","confidence":1}]},"boundingBox":{"normalizedVertices":[{"x":0.06508876,"y":0.83732057},{"x":0.12426036,"y":0.83732057},{"x":0.12426036,"y":0.8588517},{"x":0.06508876,"y":0.8588517}]},"symbols":[{"text":"p","confidence":0.98576736},{"text":"e","confidence":0.98370975}],"confidence":0.9847386},{"property":{"detectedLanguages":[{"languageCode":"de","confidence":1}]},"boundingBox":{"normalizedVertices":[{"x":0.13017751,"y":0.83732057},{"x":0.14201184,"y":0.83732057},{"x":0.14201184,"y":0.8588517},{"x":0.13017751,"y":0.8588517}]},"symbols":[{"property":{"detectedBreak":{"type":"SPACE"}},"text":")","confidence":0.97022885}],"confidence":0.97022885},{"property":{"detectedLanguages":[{"languageCode":"de","confidence":1}]},"boundingBox":{"normalizedVertices":[{"x":0.16568047,"y":0.83732057},{"x":0.20710059,"y":0.83732057},{"x":0.20710059,"y":0.8588517},{"x":0.16568047,"y":0.8588517}]},"symbols":[{"text":"6","confidence":0.95228535},{"property":{"detectedBreak":{"type":"SPACE"}},"text":".","confidence":0.9610893}],"confidence":0.95668733},{"property":{"detectedLanguages":[{"languageCode":"de","confidence":1}]},"boundingBox":{"normalizedVertices":[{"x":0.2366864,"y":0.83732057},{"x":0.25443786,"y":0.83732057},{"x":0.25443786,"y":0.8588517},{"x":0.2366864,"y":0.8588517}]},"symbols":[{"text":"(","confidence":0.9864274}],"confidence":0.9864274},{"property":{"detectedLanguages":[{"languageCode":"de","confidence":1}]},"boundingBox":{"normalizedVertices":[{"x":0.25443786,"y":0.83732057},{"x":0.33136094,"y":0.83732057},{"x":0.33136094,"y":0.8588517},{"x":0.25443786,"y":0.8588517}]},"symbols":[{"text":"g","confidence":0.9943298},{"text":"u","confidence":0.99170244},{"text":"r","confidence":0.9899229}],"confidence":0.991985},{"property":{"detectedLanguages":[{"languageCode":"de","confidence":1}]},"boundingBox":{"normalizedVertices":[{"x":0.3372781,"y":0.83732057},{"x":0.34911242,"y":0.83732057},{"x":0.34911242,"y":0.8588517},{"x":0.3372781,"y":0.8588517}]},"symbols":[{"text":".","confidence":0.98495615}],"confidence":0.98495615},{"property":{"detectedLanguages":[{"languageCode":"de","confidence":1}]},"boundingBox":{"normalizedVertices":[{"x":0.35502958,"y":0.83732057},{"x":0.37278107,"y":0.83732057},{"x":0.37278107,"y":0.8588517},{"x":0.35502958,"y":0.8588517}]},"symbols":[{"property":{"detectedBreak":{"type":"SPACE"}},"text":")","confidence":0.9813533}],"confidence":0.9813533},{"property":{"detectedLanguages":[{"languageCode":"de","confidence":1}]},"boundingBox":{"normalizedVertices":[{"x":0.40236688,"y":0.83732057},{"x":0.5029586,"y":0.83732057},{"x":0.5029586,"y":0.8588517},{"x":0.40236688,"y":0.8588517}]},"symbols":[{"text":"s","confidence":0.99026275},{"text":"i","confidence":0.99362075},{"text":"c","confidence":0.9904032},{"property":{"detectedBreak":{"type":"SPACE"}},"text":"h","confidence":0.9893783}],"confidence":0.99091625},{"property":{"detectedLanguages":[{"languageCode":"de","confidence":1}]},"boundingBox":{"normalizedVertices":[{"x":0.52662724,"y":0.83732057},{"x":0.73964494,"y":0.83732057},{"x":0.73964494,"y":0.8588517},{"x":0.52662724,"y":0.8588517}]},"symbols":[{"text":"e","confidence":0.9897598},{"text":"r","confidence":0.9873242},{"text":"z","confidence":0.98984295},{"text":"ü","confidence":0.95551497},{"text":"r","confidence":0.9908445},{"text":"n","confidence":0.9891853},{"text":"e","confidence":0.9949574},{"property":{"detectedBreak":{"type":"EOL_SURE_SPACE"}},"text":"n","confidence":0.9941164}],"confidence":0.98644316},{"property":{"detectedLanguages":[{"languageCode":"de","confidence":1}]},"boundingBox":{"normalizedVertices":[{"x":0.01775148,"y":0.8660287},{"x":0.21301775,"y":0.8660287},{"x":0.21301775,"y":0.88755983},{"x":0.01775148,"y":0.8899522}]},"symbols":[{"text":"კ","confidence":0.9934839},{"text":"უ","confidence":0.99387324},{"text":"ჭ","confidence":0.99659854},{"text":"კ","confidence":0.9999747},{"text":"უ","confidence":0.9995072},{"property":{"detectedBreak":{"type":"SPACE"}},"text":"ჭ","confidence":0.9899344}],"confidence":0.995562},{"property":{"detectedLanguages":[{"languageCode":"de","confidence":1}]},"boundingBox":{"normalizedVertices":[{"x":0.26035503,"y":0.8660287},{"x":0.46153846,"y":0.8636364},{"x":0.46153846,"y":0.88755983},{"x":0.26035503,"y":0.88755983}]},"symbols":[{"text":"h","confidence":0.9959897},{"text":"e","confidence":0.99419534},{"text":"r","confidence":0.9989553},{"text":"z","confidence":0.99870485},{"text":"l","confidence":0.99976414},{"text":"i","confidence":0.9995201},{"text":"c","confidence":0.9999604},{"property":{"detectedBreak":{"type":"SPACE"}},"text":"h","confidence":0.99983275}],"confidence":0.99836534},{"property":{"detectedLanguages":[{"languageCode":"de","confidence":1}]},"boundingBox":{"normalizedVertices":[{"x":0.4852071,"y":0.8636364},{"x":0.65088755,"y":0.8636364},{"x":0.65088755,"y":0.88755983},{"x":0.4852071,"y":0.88755983}]},"symbols":[{"text":"l","confidence":0.6053518},{"text":"a","confidence":0.9951687},{"text":"c","confidence":0.9997348},{"text":"h","confidence":0.99996924},{"text":"e","confidence":0.9997705},{"property":{"detectedBreak":{"type":"LINE_BREAK"}},"text":"n","confidence":0.9913456}],"confidence":0.93189013}],"confidence":0.972921},{"boundingBox":{"normalizedVertices":[{"x":0.02366864,"y":0.8971292},{"x":0.964497,"y":0.8923445},{"x":0.9704142,"y":0.94258374},{"x":0.02366864,"y":0.94736844}]},"words":[{"property":{"detectedLanguages":[{"languageCode":"de","confidence":1}]},"boundingBox":{"normalizedVertices":[{"x":0.15384616,"y":0.8971292},{"x":0.18934911,"y":0.8971292},{"x":0.18934911,"y":0.91626793},{"x":0.15384616,"y":0.91626793}]},"symbols":[{"property":{"detectedBreak":{"type":"SPACE"}},"text":"3","confidence":0.40582654}],"confidence":0.40582654},{"property":{"detectedLanguages":[{"languageCode":"de","confidence":1}]},"boundingBox":{"normalizedVertices":[{"x":0.2366864,"y":0.8947368},{"x":0.5029586,"y":0.8947368},{"x":0.5029586,"y":0.91626793},{"x":0.2366864,"y":0.91626793}]},"symbols":[{"text":"a","confidence":0.9812394},{"text":"u","confidence":0.9893045},{"text":"f","confidence":0.9923216},{"text":"q","confidence":0.98249066},{"text":"u","confidence":0.9903053},{"text":"e","confidence":0.99258155},{"text":"l","confidence":0.98993456},{"text":"l","confidence":0.99276394},{"text":"e","confidence":0.99282384},{"property":{"detectedBreak":{"type":"SPACE"}},"text":"n","confidence":0.9908601}],"confidence":0.98946255},{"property":{"detectedLanguages":[{"languageCode":"de","confidence":1}]},"boundingBox":{"normalizedVertices":[{"x":0.5502958,"y":0.8947368},{"x":0.56804734,"y":0.8947368},{"x":0.56804734,"y":0.91626793},{"x":0.5502958,"y":0.91626793}]},"symbols":[{"text":"(","confidence":0.98389006}],"confidence":0.98389006},{"property":{"detectedLanguages":[{"languageCode":"de","confidence":1}]},"boundingBox":{"normalizedVertices":[{"x":0.56804734,"y":0.8947368},{"x":0.591716,"y":0.8947368},{"x":0.5976331,"y":0.9138756},{"x":0.56804734,"y":0.9138756}]},"symbols":[{"text":"v","confidence":0.9930909}],"confidence":0.9930909},{"property":{"detectedLanguages":[{"languageCode":"de","confidence":1}]},"boundingBox":{"normalizedVertices":[{"x":0.6035503,"y":0.8947368},{"x":0.60946745,"y":0.8947368},{"x":0.61538464,"y":0.9138756},{"x":0.6035503,"y":0.9138756}]},"symbols":[{"property":{"detectedBreak":{"type":"SPACE"}},"text":".","confidence":0.98118037}],"confidence":0.98118037},{"property":{"detectedLanguages":[{"languageCode":"de","confidence":1}]},"boundingBox":{"normalizedVertices":[{"x":0.6627219,"y":0.8947368},{"x":0.964497,"y":0.8923445},{"x":0.9704142,"y":0.9138756},{"x":0.6627219,"y":0.9138756}]},"symbols":[{"text":"M","confidence":0.99290687},{"text":"a","confidence":0.99682885},{"text":"i","confidence":0.996811},{"text":"s","confidence":0.99602664},{"text":"k","confidence":0.9926909},{"text":"ö","confidence":0.9447447},{"text":"r","confidence":0.99221796},{"text":"n","confidence":0.9914698},{"text":"e","confidence":0.99266255},{"text":"r","confidence":0.99267906},{"property":{"detectedBreak":{"type":"EOL_SURE_SPACE"}},"text":"n","confidence":0.9582816}],"confidence":0.98612},{"property":{"detectedLanguages":[{"languageCode":"ka","confidence":1}]},"boundingBox":{"normalizedVertices":[{"x":0.02366864,"y":0.92583734},{"x":0.112426035,"y":0.92583734},{"x":0.112426035,"y":0.94736844},{"x":0.02366864,"y":0.94736844}]},"symbols":[{"text":"კ","confidence":0.9757612},{"text":"უ","confidence":0.95848167},{"property":{"detectedBreak":{"type":"SPACE"}},"text":"ხ","confidence":0.9779384}],"confidence":0.9707271},{"property":{"detectedLanguages":[{"languageCode":"ka","confidence":1}]},"boundingBox":{"normalizedVertices":[{"x":0.14201184,"y":0.92583734},{"x":0.4260355,"y":0.923445},{"x":0.4260355,"y":0.9449761},{"x":0.14201184,"y":0.94736844}]},"symbols":[{"text":"a","confidence":0.9978592},{"text":"u","confidence":0.99334145},{"text":"f","confidence":0.97839457},{"text":"k","confidence":0.99905163},{"text":"n","confidence":0.9992885},{"text":"a","confidence":0.9999522},{"text":"c","confidence":0.99982727},{"text":"k","confidence":0.99977636},{"text":"e","confidence":0.9986273},{"property":{"detectedBreak":{"type":"LINE_BREAK"}},"text":"n","confidence":0.9811874}],"confidence":0.9947306}],"confidence":0.9727742},{"boundingBox":{"normalizedVertices":[{"x":0.60946745,"y":0.92105263},{"x":0.964497,"y":0.92105263},{"x":0.964497,"y":0.9449761},{"x":0.60946745,"y":0.9449761}]},"words":[{"property":{"detectedLanguages":[{"languageCode":"de","confidence":1}]},"boundingBox":{"normalizedVertices":[{"x":0.60946745,"y":0.92105263},{"x":0.6331361,"y":0.92105263},{"x":0.62721896,"y":0.9449761},{"x":0.60946745,"y":0.9449761}]},"symbols":[{"text":"[","confidence":0.60439223}],"confidence":0.60439223},{"property":{"detectedLanguages":[{"languageCode":"de","confidence":1}]},"boundingBox":{"normalizedVertices":[{"x":0.6331361,"y":0.92105263},{"x":0.75147927,"y":0.92105263},{"x":0.75147927,"y":0.9449761},{"x":0.6331361,"y":0.9449761}]},"symbols":[{"text":"b","confidence":0.98038584},{"text":"e","confidence":0.9764592},{"text":"i","confidence":0.97892094},{"property":{"detectedBreak":{"type":"SPACE"}},"text":"m","confidence":0.94469666}],"confidence":0.97011566},{"property":{"detectedLanguages":[{"languageCode":"de","confidence":1}]},"boundingBox":{"normalizedVertices":[{"x":0.75739646,"y":0.92105263},{"x":0.9467456,"y":0.92105263},{"x":0.9467456,"y":0.9449761},{"x":0.75739646,"y":0.9449761}]},"symbols":[{"text":"K","confidence":0.90070194},{"text":"o","confidence":0.98474044},{"text":"c","confidence":0.9875546},{"text":"h","confidence":0.9880827},{"text":"e","confidence":0.9818142},{"text":"n","confidence":0.9925999}],"confidence":0.9725823},{"property":{"detectedLanguages":[{"languageCode":"de","confidence":1}]},"boundingBox":{"normalizedVertices":[{"x":0.9467456,"y":0.92105263},{"x":0.964497,"y":0.92105263},{"x":0.964497,"y":0.9449761},{"x":0.9467456,"y":0.9449761}]},"symbols":[{"property":{"detectedBreak":{"type":"LINE_BREAK"}},"text":")","confidence":0.9625424}],"confidence":0.9625424}],"confidence":0.9402409}],"blockType":"TEXT","confidence":0.9710915}],"confidence":0.9549043}],"text":"ten; zärtlich (zuj-m) sprechen, den\nHof machen\nკურნ heilen, kurieren\njmmbsm (imer., ratsch.) dicke Trä-\nnen vergiessen\nკურცხალა(ვ) (imer., ratsch.) s. კურ-\nცხალ\nკურცხვლ (umg.) s. კურცხლ\nJb¹ (umg.) (davon-)laufen, -ren-\n1\n1\nnen, -galoppieren.\nკურცხლ dicke Tränen vergiessen\njb die Augen rollen, glotzen\nbmb unruhig/rastlos sein\n38 (an den Beinen) lahm werden\nrufen, locken, gluck sen,\n2\npiepen\nკუფხ(ვ)ლ nachlesen (im Weinberg)\n¿ mürrisch/griesgrämig/trübsin-\nnig machen\ndersäbeln\n31. zer-hauen, -stückeln 2. nie-\nკუწმაწ‘ s. ქუცმაც\n32 (gur.) böse/zornig sein\n¿1. ausnehmen (z.B. Huhn); den\nNusskern aus der Schale heraus-\nstochern 2. (imer., gur.) zerknüllen\n3. (khis.) zs.-klappen (z. B. Ta-\nschenmesser) 4. hinein-stecken,\n-stopfen 5. aufgehen (v. e-r Knos-\npe) 6. (gur.) sich erzürnen\nკუჭკუჭ herzlich lachen\n3 aufquellen (v. Maiskörnern\nკუხ aufknacken\n[beim Kochen)"},"context":{"uri":"gs://ocr-test-bucket-466/merged.pdf","pageNumber":66}}]}